Workbook

Sheet Dashboard
A1: LORE Labs -- CFO Dashboard
A2: ="Scenario: "&Scenarios!D3&" | all figures USD, live from model" -> Scenario: Base | all figures USD, live from model
B4: FY2026* | C4: FY2027 | D4: FY2028 | E4: FY2029 | F4: FY2030 | G4: FY2031
A5: Units shipped | B5: ='Pricing & Mix'!AG42 -> 0 | C5: ='Pricing & Mix'!AH42 -> 3697.5 | D5: ='Pricing & Mix'!AI42 -> 39252.5 | E5: ='Pricing & Mix'!AJ42 -> 120000 | F5: ='Pricing & Mix'!AK42 -> 250000 | G5: ='Pricing & Mix'!AL42 -> 400000
A6: Total revenue | B6: ='P&L'!AG16 -> 0 | C6: ='P&L'!AH16 -> 656496.72 | D6: ='P&L'!AI16 -> 10020674 | E6: ='P&L'!AJ16 -> 31635040 | F6: ='P&L'!AK16 -> 67070783 | G6: ='P&L'!AL16 -> 1.1133476e+08
A7: Hardware (net) | B7: ='P&L'!AG10 -> 0 | C7: ='P&L'!AH10 -> 605394.72 | D7: ='P&L'!AI10 -> 9016707.1 | E7: ='P&L'!AJ10 -> 26883763 | F7: ='P&L'!AK10 -> 54946080 | G7: ='P&L'!AL10 -> 87913728
A8: Subscriptions (Explorer + Trip Pass) | B8: ='P&L'!AG11+'P&L'!AG12 -> 0 | C8: ='P&L'!AH11+'P&L'!AH12 -> 0 | D8: ='P&L'!AI11+'P&L'!AI12 -> 362493.03 | E8: ='P&L'!AJ11+'P&L'!AJ12 -> 2296154.2 | F8: ='P&L'!AK11+'P&L'!AK12 -> 6214231.9 | G8: ='P&L'!AL11+'P&L'!AL12 -> 12347008
A9: Accessories | B9: ='P&L'!AG13 -> 0 | C9: ='P&L'!AH13 -> 49916.25 | D9: ='P&L'!AI13 -> 529908.75 | E9: ='P&L'!AJ13 -> 1620000 | F9: ='P&L'!AK13 -> 3375000 | G9: ='P&L'!AL13 -> 5400000
A10: Affiliate | B10: ='P&L'!AG14 -> 0 | C10: ='P&L'!AH14 -> 1185.75 | D10: ='P&L'!AI14 -> 62065.291 | E10: ='P&L'!AJ14 -> 425922.73 | F10: ='P&L'!AK14 -> 1413471 | G10: ='P&L'!AL14 -> 3430021.2
A11: B2B fleet | B11: ='P&L'!AG15 -> 0 | C11: ='P&L'!AH15 -> 0 | D11: ='P&L'!AI15 -> 49500 | E11: ='P&L'!AJ15 -> 409200 | F11: ='P&L'!AK15 -> 1122000 | G11: ='P&L'!AL15 -> 2244000
A12: Revenue growth YoY | B12: =0 -> 0 | C12: =IF(B6>0,C6/B6-1,0) -> 0 | D12: =IF(C6>0,D6/C6-1,0) -> 14.26386 | E12: =IF(D6>0,E6/D6-1,0) -> 2.1569772 | F12: =IF(E6>0,F6/E6-1,0) -> 1.1201422 | G12: =IF(F6>0,G6/F6-1,0) -> 0.65995911
A13: Gross profit | B13: ='P&L'!AG23 -> 0 | C13: ='P&L'!AH23 -> 73619.895 | D13: ='P&L'!AI23 -> 2390437.7 | E13: ='P&L'!AJ23 -> 9564896.9 | F13: ='P&L'!AK23 -> 24062948 | G13: ='P&L'!AL23 -> 44237881
A14: Gross margin % | B14: ='P&L'!AG24 -> 0 | C14: ='P&L'!AH24 -> 0.11214054 | D14: ='P&L'!AI24 -> 0.23855058 | E14: ='P&L'!AJ24 -> 0.30235134 | F14: ='P&L'!AK24 -> 0.35876946 | G14: ='P&L'!AL24 -> 0.39734116
A15: Hardware gross margin % | B15: ='P&L'!AG44 -> 0 | C15: ='P&L'!AH44 -> 0.087054829 | D15: ='P&L'!AI44 -> 0.21290764 | E15: ='P&L'!AJ44 -> 0.25284801 | F15: ='P&L'!AK44 -> 0.29527017 | G15: ='P&L'!AL44 -> 0.31801954
A16: EBITDA | B16: ='P&L'!AG32 -> -198666.67 | C16: ='P&L'!AH32 -> -4115400 | D16: ='P&L'!AI32 -> -4613729.6 | E16: ='P&L'!AJ32 -> -8160796.7 | F16: ='P&L'!AK32 -> -6583183.9 | G16: ='P&L'!AL32 -> -621008.36
A17: EBITDA margin % | B17: ='P&L'!AG33 -> 0 | C17: ='P&L'!AH33 -> -6.268729 | D17: ='P&L'!AI33 -> -0.46042108 | E17: ='P&L'!AJ33 -> -0.25796701 | F17: ='P&L'!AK33 -> -0.098152781 | G17: ='P&L'!AL33 -> -0.0055778481
A18: Net income | B18: ='P&L'!AG40 -> -194513.33 | C18: ='P&L'!AH40 -> -4102395.5 | D18: ='P&L'!AI40 -> -4569902 | E18: ='P&L'!AJ40 -> -7748020.6 | F18: ='P&L'!AK40 -> -6678268.7 | G18: ='P&L'!AL40 -> -192459.67
A19: Ending cash | B19: ='Cash Flow'!AG28 -> 1305486.7 | C19: ='Cash Flow'!AH28 -> 2556526.4 | D19: ='Cash Flow'!AI28 -> 23250149 | E19: ='Cash Flow'!AJ28 -> 14378505 | F19: ='Cash Flow'!AK28 -> 38382308 | G19: ='Cash Flow'!AL28 -> 33426498
A20: Net burn (op + inv cash flow) | B20: ='Cash Flow'!AG29 -> 194513.33 | C20: ='Cash Flow'!AH29 -> 4748960.3 | D20: ='Cash Flow'!AI29 -> 7306377.5 | E20: ='Cash Flow'!AJ29 -> 8871643.7 | F20: ='Cash Flow'!AK29 -> 10996197 | G20: ='Cash Flow'!AL29 -> 4955810.2
A21: Equity raised in year | B21: ='Cash Flow'!AG22 -> 1500000 | C21: ='Cash Flow'!AH22 -> 6000000 | D21: ='Cash Flow'!AI22 -> 28000000 | E21: ='Cash Flow'!AJ22 -> 0 | F21: ='Cash Flow'!AK22 -> 35000000 | G21: ='Cash Flow'!AL22 -> 0
A22: Paid subscribers (end) | B22: ='Subscription Cohorts'!AG19 -> 0 | C22: ='Subscription Cohorts'!AH19 -> 0 | D22: ='Subscription Cohorts'!AI19 -> 7626.4187 | E22: ='Subscription Cohorts'!AJ19 -> 32142.086 | F22: ='Subscription Cohorts'!AK19 -> 73636.421 | G22: ='Subscription Cohorts'!AL19 -> 132277.32
A23: Subscription ARR (end) | B23: ='Subscription Cohorts'!AG24 -> 0 | C23: ='Subscription Cohorts'!AH24 -> 0 | D23: ='Subscription Cohorts'!AI24 -> 786259.36 | E23: ='Subscription Cohorts'!AJ24 -> 3313746.3 | F23: ='Subscription Cohorts'!AK24 -> 7591679.4 | G23: ='Subscription Cohorts'!AL24 -> 13637368
A24: Active devices (end) | B24: ='Subscription Cohorts'!AG29 -> 0 | C24: ='Subscription Cohorts'!AH29 -> 3655 | D24: ='Subscription Cohorts'!AI29 -> 39124.509 | E24: ='Subscription Cohorts'!AJ29 -> 138343.29 | F24: ='Subscription Cohorts'!AK29 -> 332813.71 | G24: ='Subscription Cohorts'!AL29 -> 619969.94
A25: Headcount (end) | B25: ='Headcount Plan'!AG104 -> 3 | C25: ='Headcount Plan'!AH104 -> 14 | D25: ='Headcount Plan'!AI104 -> 30 | E25: ='Headcount Plan'!AJ104 -> 61 | F25: ='Headcount Plan'!AK104 -> 92 | G25: ='Headcount Plan'!AL104 -> 121
A26: * FY2026 = Nov-Dec stub
A28: Funding & runway
A29: Total equity raised through FY2031 | B29: ='Funding & Runway'!D12 -> 70500000
A30: Minimum month-end cash, Nov-26..Dec-28 | B30: ='Funding & Runway'!D13 -> 420194.5
A31: Month of minimum cash | B31: ='Funding & Runway'!D14 -> May-27
A32: Peak monthly net burn (monthly periods) | B32: ='Funding & Runway'!D16 -> 1160489.6
A33: Month of peak burn | B33: ='Funding & Runway'!D17 -> Oct-27
A34: Peak average monthly burn (any period incl. FY29-31) | B34: ='Funding & Runway'!D18 -> 1160489.6
A35: First monthly period with positive EBITDA (monthly cols) | B35: ='Funding & Runway'!D20 -> after Dec-28
A36: First fiscal year with positive EBITDA | B36: ='Funding & Runway'!D21 -> after FY31
A37: First fiscal year with positive operating+investing cash flow | B37: ='Funding & Runway'!D22 -> after FY31
A38: Minimum period-end cash incl. FY29-31 | B38: ='Funding & Runway'!D15 -> 420194.5

Sheet Assumptions
A1: Assumptions -- all inputs in BLUE. Estimates unless a source is cited. Prices ex-VAT/sales tax.
B2: Model base year | C2: 2027
A3: Input | B3: Name | C3: Value | D3: Unit | E3: Basis / source
A5: General & finance
A6: Opening cash (Nov-2026, before pre-seed) | B6: opening_cash | C6: 0 | D6: $ | E6: Founder-funded work to date excluded.
A7: Interest earned on cash (annual) | B7: interest_rate | C7: 0.035 | D7: %/yr | E7: US T-bill / treasury MMF yields ~3.5-4% (2026), conservative.
A8: Corporate income tax rate (after NOLs) | B8: tax_rate | C8: 0.21 | D8: % | E8: US federal 21%; state ignored; NOLs offset until cumulative pre-tax > 0.
A9: Employer burden on salary (benefits, payroll tax) | B9: burden | C9: 0.25 | D9: % | E9: Typical US startup 20-30%. Legal-ops owns final salary bands.
A10: Annual salary inflation (from 2028) | B10: salary_infl | C10: 0.03 | D10: %/yr | E10: Estimate.
A12: Hardware pricing (MSRP from COMPANY.md; KS prices = early-bird)
A13: LORE Pebble MSRP | B13: msrp_peb | C13: 149 | D13: $ | E13: COMPANY.md target price.
A14: LORE Square MSRP | B14: msrp_sq | C14: 299 | D14: $ | E14: Research final (holds COMPANY.md). CFO FLAG: with hardware/bom landed $227 @10k the DTC hardware margin is single-digit until DRAM normalises & 100k-tier pricing; see pricing-margin-sensitivity.md.
A15: LORE Atlas MSRP | B15: msrp_atl | C15: 599 | D15: $ | E15: Research recommends $599 (COMPANY.md $549). Atlas launches Sep-2028 (CFO assumption: NTN + camera + titanium need a separate EVT/DVT cycle).
A16: Kickstarter blended pledge price -- Pebble | B16: ks_peb | C16: 112 | D16: $ | E16: Research tiers $99 / $115 / $129, weighted ~25/45/30.
A17: Kickstarter blended pledge price -- Square | B17: ks_sq | C17: 226 | D17: $ | E17: Research tiers $199 / $229 / $259, weighted ~25/45/30.
A18: Post-campaign pre-order price -- Pebble | B18: pre_peb | C18: 129 | D18: $ | E18: BackerKit/website pre-order, ~13% off (Research).
A19: Kickstarter blended pledge price -- Atlas | B19: ks_atl | C19: 442 | D19: $ | E19: Research tiers $399 / $449 / $499.
A20: Post-campaign pre-order price -- Atlas | B20: pre_atl | C20: 499 | D20: $ | E20: Research KS standard tier.
A21: Post-campaign pre-order price -- Square | B21: pre_sq | C21: 259 | D21: $ | E21: ~13% off $299 (Research).
A22: Average DTC promo discount vs MSRP | B22: dtc_disc | C22: 0.06 | D22: % | E22: Blended codes/bundles/Black Friday.
A23: Retailer / distributor margin (off MSRP) | B23: retail_margin | C23: 0.38 | D23: % | E23: Consumer electronics retail margins typically 30-45% incl. distributor; estimate.
A24: Returns & refunds allowance (of HW revenue) | B24: returns_pct | C24: 0.04 | D24: % | E24: Consumer electronics 3-8%; estimate.
A26: Landed COGS per unit, 10k tier (RECONCILED to hardware/bom/cogs_summary.csv, 30-Oct-2026); NRE (cert/tooling) is expensed/capitalised separately
A27: Pebble (ships as Pebble Lite ECR spec) -- FOB incl. conversion & yield | B27: bom_peb | C27: 62.03 | D27: $ | E27: hardware/bom: Pebble Lite (ECR, cloud AI, no DRAM) FOB @10k $62.03. Full-spec Pebble (on-device 1B model) is $125.06 FOB -> negative margin at $149, so CFO base case ships the ECR spec.
A28: Pebble -- royalties | B28: asm_peb | C28: 0 | D28: $ | E28: hardware/bom: none (no cellular).
A29: Pebble -- extra packaging (included in FOB) | B29: pkg_peb | C29: 0 | D29: $ | E29: Included in hardware/bom FOB.
A30: Square -- FOB incl. conversion & yield | B30: bom_sq | C30: 219.11 | D30: $ | E30: hardware/bom @10k (DRAM priced at 2026-27 shortage levels; normalised DRAM saves ~$20).
A31: Square -- cellular SEP royalties | B31: asm_sq | C31: 5.8 | D31: $ | E31: hardware/bom estimate.
A32: Square -- extra packaging (included in FOB) | B32: pkg_sq | C32: 0 | D32: $
A33: Atlas -- FOB incl. conversion & yield | B33: bom_atl | C33: 305.55 | D33: $ | E33: hardware/bom @10k.
A34: Atlas -- royalties | B34: asm_atl | C34: 8.7 | D34: $ | E34: hardware/bom estimate.
A35: Atlas -- extra packaging (included in FOB) | B35: pkg_atl | C35: 0 | D35: $
A36: Inbound freight, insurance & duties (% of FOB) | B36: freight_duty | C36: 0.01 | D36: % | E36: hardware/bom: freight $1.3-2.2/unit; 0% US duty assumes VN/MY FATP (China FATP adds ~20% of FOB -- see sensitivity).
A37: Warranty reserve (% of HW revenue) | B37: warranty_pct | C37: 0.02 | D37: % | E37: 1-2 yr warranty; estimate.
A38: DTC outbound shipping + 3PL pick/pack per unit | B38: dtc_ship | C38: 11 | D38: $ | E38: 3PL ~$3-4 + ground/intl blend.
A39: Retail distribution cost per unit | B39: retail_dist | C39: 4 | D39: $ | E39: Palletised to DC.
A40: Pre-order (KS) fulfilment cost per unit, net of shipping charged | B40: ks_fulfil_net | C40: 6 | D40: $ | E40: Backers pay shipping; residual subsidy + 3PL.
A41: Card processing -- % (DTC) | B41: pay_pct | C41: 0.029 | D41: % | E41: Stripe/Shopify Payments standard 2.9% + $0.30.
A42: Card processing -- fixed per order | B42: pay_fixed | C42: 0.3 | D42: $
A44: Kickstarter / pre-orders (Q2-2027 campaign; ships Nov-2027 to Jan-2028)
A45: Kickstarter backer units (base, before scenario) | B45: ks_units | C45: 4000 | D45: units | E45: ~$0.8M raised (Research internal success $750k-1M; public goal $150k).
A46: Post-campaign pre-order units (BackerKit / website) | B46: pre_units | C46: 1000 | D46: units | E46: Late pledges typically 15-30% of campaign units.
A47: Pre-order SKU mix -- Pebble share | B47: pre_mix_peb | C47: 0.45 | D47: % | E47: Research mix 45/40/15.
A48: Pre-order SKU mix -- Atlas share (Square = remainder) | B48: pre_mix_atl | C48: 0.15 | D48: % | E48: Atlas backers ship Feb-Mar 2028 (separate NTN/camera cert).
A49: Kickstarter platform fee | B49: ks_fee | C49: 0.05 | D49: % | E49: Kickstarter 5% of funds (https://www.launchboom.com/crowdfunding-tips/how-much-does-kickstarter-charge/)
A50: Kickstarter payment processing % | B50: ks_proc | C50: 0.03 | D50: % | E50: 3% + $0.20 per pledge (https://www.pledgebox.com/post/how-much-does-kickstarter-take)
A51: Kickstarter processing fixed per pledge | B51: ks_proc_fixed | C51: 0.2 | D51: $
A52: Average units per pledge | B52: units_per_pledge | C52: 1.15 | D52: units | E52: Estimate (two-packs, gifts).
A54: Subscription -- LORE Pass (COMPANY.md)
A55: Explorer list price per month | B55: sub_price | C55: 9.99 | D55: $/mo | E55: COMPANY.md.
A56: Realised ARPU as % of list (annual-plan discount, promos) | B56: arpu_real | C56: 0.86 | D56: % | E56: ~40% on Research-recommended $79/yr annual plan.
A57: Free Explorer trial included with every device | B57: trial_months | C57: 3 | D57: months | E57: COMPANY.md.
A58: Post-trial paid attach -- Pebble | B58: attach_peb | C58: 0.28 | D58: % | E58: Pebble ships as cloud-AI (ECR) spec, so unlimited live AI needs the Pass; no eSIM. Hardware-subscription comps: Whoop/Oura are mandatory/near-mandatory; ours is optional.
A59: Post-trial paid attach -- Square | B59: attach_sq | C59: 0.4 | D59: % | E59: eSIM data makes Pass the natural default.
A60: Post-trial paid attach -- Atlas | B60: attach_atl | C60: 0.55 | D60: % | E60: Premium buyer; satellite SOS.
A61: Monthly churn of paid Explorer subs (base) | B61: churn | C61: 0.06 | D61: %/mo | E61: Consumer subscription apps lose most subs in month 1; travel is seasonal (https://www.revenuecat.com/state-of-subscription-apps-2025). Annualised ~52%.
A62: Trip Pass price (14 days, 5 GB) | B62: trip_price | C62: 32 | D62: $ | E62: Blend: 85% $29 (14d/5GB) + 15% $49 (30d/10GB) (Research).
A63: Trip Pass purchase rate per month (non-paying eSIM devices) | B63: trip_rate | C63: 0.03 | D63: /mo | E63: ~0.36 trips/yr bought by non-subscribers; estimate.
A64: Device inactivity (abandonment) rate per month | B64: device_inactive | C64: 0.02 | D64: %/mo | E64: ~22%/yr of installed base goes dormant.
A66: Accessories, affiliate, B2B fleet
A67: Accessory attach (orders per device sold) | B67: acc_attach | C67: 0.3 | D67: orders/unit | E67: LORE Kit: clip, lanyard, dock, case, Buds.
A68: Accessory average order value | B68: acc_aov | C68: 45 | D68: $ | E68: Mix of $19-39 straps/cases/docks and $129 LORE Buds (Research price).
A69: Accessory COGS (% of revenue) | B69: acc_cogs_pct | C69: 0.38 | D69: % | E69: Accessories typically 55-70% GM.
A70: B2B fleet rental fee per device per month | B70: fleet_fee | C70: 22 | D70: $/unit/mo | E70: Hostels/tour operators re-rent at ~$5-8/day.
A71: Fleet device cost (capitalised) | B71: fleet_unit_cost | C71: 95 | D71: $/unit | E71: Blend of Pebble/Square landed cost + rugged case.
A72: Fleet cloud + data cost per device per month | B72: fleet_cloud | C72: 3 | D72: $/unit/mo
A73: Fleet device replacement / loss rate per month | B73: fleet_replace | C73: 0.01 | D73: %/mo
A75: Cloud / AI COGS per paid user-month (2027-28 prices; deflation thereafter)
A76: LLM inference (live Q&A, ~150 queries/mo) | B76: llm_cost | C76: 0.3 | D76: $/user-mo | E76: ~300k in / 45k out tokens on a Flash-class model: $0.30/M in, $2.50/M out (https://www.morphllm.com/gemini-api-pricing).
A77: Speech-to-text | B77: stt_cost | C77: 0.15 | D77: $/user-mo | E77: ~25 min/mo at ~$0.006/min.
A78: Cloud neural TTS (stories pre-rendered & cached; live answers only) | B78: tts_cost | C78: 0.7 | D78: $/user-mo | E78: ~45k chars at ~$0.016/1k (standard neural); premium ElevenLabs $0.04-0.10/1k would be 3-6x (https://developer.puter.com/tutorials/elevenlabs-api-pricing/).
A79: Infra: hosting, maps/places API, observability | B79: infra_cost | C79: 0.25 | D79: $/user-mo
A80: Data used per Explorer eSIM user per month | B80: data_gb_used | C80: 0.7 | D80: GB | E80: 1 GB allowance; most users under-consume.
A81: Wholesale eSIM data cost per GB (blended global) | B81: data_cost_gb | C81: 1.6 | D81: $/GB | E81: Wholesale lists ~EUR2.5/GB small-volume, ~$1.85/GB illustrative blend (https://simology.io/blog/wholesale-pricing-forecasting-volume-tiers-commitments-and-margins); target with MVNE at volume.
A82: Billing fees on subscriptions (blend web checkout + app stores) | B82: sub_pay_fee | C82: 0.08 | D82: % of rev | E82: Web checkout ~3%, app stores 15%; blended.
A83: Free-tier / offline active device cost per month | B83: free_cost | C83: 0.12 | D83: $/device-mo | E83: Pack downloads, basic narration.
A84: Trip Pass data actually used | B84: trip_data_gb | C84: 2.5 | D84: GB | E84: Half of the 5 GB allowance.
A85: Trip Pass AI cost | B85: trip_ai | C85: 0.8 | D85: $/pass
A86: AI unit-cost deflation per year (from 2029) | B86: ai_defl | C86: 0.2 | D86: %/yr | E86: Token prices have fallen >50%/yr historically; conservative.
A87: Data cost deflation per year (from 2029) | B87: data_defl | C87: 0.08 | D87: %/yr
A89: Working capital
A90: ODM deposit at PO (% of landed cost) | B90: odm_dep | C90: 0.3 | D90: % | E90: 30/70 is the common opening term (https://harris-sliwoski.com/chinalawblog/china-manufacturing-payment-terms/).
A91: Deposit paid N months before shipment month | B91: dep_lead | C91: 3 | D91: months | E91: Component lead time (LTE modules, AMOLED).
A92: Balance (70%) paid N months before shipment month | B92: bal_lead | C92: 1 | D92: months | E92: Against B/L, ~4-5 wk ocean.
A93: Inventory days (annual years FY29+) | B93: inv_days | C93: 60 | D93: days of HW COGS
A94: Retail receivable days | B94: ar_days | C94: 45 | D94: days | E94: Net-45 typical for big-box / Amazon vendor.
A96: Sales & marketing
A97: Retail co-op / MDF / displays (% of retail HW revenue) | B97: retail_coop | C97: 0.06 | D97: %
A100: TIME-SERIES INPUTS (blue) -- monthly Nov-26..Dec-28, then FY2029-FY2031
A101: Period | C101: =Timeline!C2 -> Nov-26 | D101: =Timeline!D2 -> Dec-26 | E101: =Timeline!E2 -> Jan-27 | F101: =Timeline!F2 -> Feb-27 | G101: =Timeline!G2 -> Mar-27 | H101: =Timeline!H2 -> Apr-27 | I101: =Timeline!I2 -> May-27 | J101: =Timeline!J2 -> Jun-27 | ... AE101: =Timeline!AE2 -> FY2031
A102: Regular unit sales, all SKUs (DTC + retail), base | B102: reg_units | C102: 0 | D102: 0 | E102: 0 | F102: 0 | G102: 0 | H102: 0 | I102: 0 | J102: 0 | K102: 0 | L102: 0 | M102: 0 | N102: 0 | O102: 0 | P102: 0 | Q102: 1250 | R102: 1350 | S102: 1650 | T102: 2050 | U102: 2450 | V102: 2850 | W102: 3350 | X102: 3450 | Y102: 3250 | Z102: 3650 | AA102: 5250 | AB102: 7400 | AC102: 120000 | AD102: 250000 | AE102: 400000 | AG102: Research final units: 5k 2027 (all pre-orders), 40k 2028, 120k 2029, 250k 2030; 400k 2031 (Research SOM table).
A103: Pre-order units shipped (% of total pre-orders) | B103: pre_ship_pct | C103: 0 | D103: 0 | E103: 0 | F103: 0 | G103: 0 | H103: 0 | I103: 0 | J103: 0 | K103: 0 | L103: 0 | M103: 0 | N103: 0 | O103: 0.5 | P103: 0.37 | Q103: 0.13 | R103: 0 | S103: 0 | T103: 0 | U103: 0 | V103: 0 | W103: 0 | X103: 0 | Y103: 0 | Z103: 0 | AA103: 0 | AB103: 0 | AC103: 0 | AD103: 0 | AE103: 0 | AG103: Q4-2027 first shipments (COMPANY.md).
A104: Pre-order cash collected (% of total pre-orders) | B104: pre_collect_pct | C104: 0 | D104: 0 | E104: 0 | F104: 0 | G104: 0 | H104: 0 | I104: 0 | J104: 0.8 | K104: 0.05 | L104: 0.05 | M104: 0.05 | N104: 0.05 | O104: 0 | P104: 0 | Q104: 0 | R104: 0 | S104: 0 | T104: 0 | U104: 0 | V104: 0 | W104: 0 | X104: 0 | Y104: 0 | Z104: 0 | AA104: 0 | AB104: 0 | AC104: 0 | AD104: 0 | AE104: 0 | AG104: KS campaign May-2027, payout ~14 days after close = Jun-2027; late pledges Jul-Oct.
A105: Atlas pre-order units shipped (% of Atlas pre-orders) | B105: pre_ship_atl | C105: 0 | D105: 0 | E105: 0 | F105: 0 | G105: 0 | H105: 0 | I105: 0 | J105: 0 | K105: 0 | L105: 0 | M105: 0 | N105: 0 | O105: 0 | P105: 0 | Q105: 0 | R105: 0.5 | S105: 0.5 | T105: 0 | U105: 0 | V105: 0 | W105: 0 | X105: 0 | Y105: 0 | Z105: 0 | AA105: 0 | AB105: 0 | AC105: 0 | AD105: 0 | AE105: 0 | AG105: Atlas ships ~3 months after Pebble/Square.
A106: Retail / wholesale share of regular units | B106: retail_share | C106: 0 | D106: 0 | E106: 0 | F106: 0 | G106: 0 | H106: 0 | I106: 0 | J106: 0 | K106: 0 | L106: 0 | M106: 0 | N106: 0 | O106: 0 | P106: 0 | Q106: 0.1 | R106: 0.1 | S106: 0.1 | T106: 0.1 | U106: 0.1 | V106: 0.1 | W106: 0.25 | X106: 0.25 | Y106: 0.25 | Z106: 0.25 | AA106: 0.25 | AB106: 0.25 | AC106: 0.3 | AD106: 0.35 | AE106: 0.35 | AG106: Retail from 2028 (COMPANY.md). DTC-led (Oura/Whoop-style) because retail margin on Square is thin at BOM-reconciled COGS.
A107: SKU mix of regular units -- Pebble | B107: mix_peb | C107: 0.53 | D107: 0.53 | E107: 0.53 | F107: 0.53 | G107: 0.53 | H107: 0.53 | I107: 0.53 | J107: 0.53 | K107: 0.53 | L107: 0.53 | M107: 0.53 | N107: 0.53 | O107: 0.53 | P107: 0.53 | Q107: 0.53 | R107: 0.53 | S107: 0.53 | T107: 0.45 | U107: 0.45 | V107: 0.45 | W107: 0.45 | X107: 0.45 | Y107: 0.45 | Z107: 0.45 | AA107: 0.45 | AB107: 0.45 | AC107: 0.45 | AD107: 0.45 | AE107: 0.45
A108: SKU mix of regular units -- Square | B108: mix_sq | C108: 0.47 | D108: 0.47 | E108: 0.47 | F108: 0.47 | G108: 0.47 | H108: 0.47 | I108: 0.47 | J108: 0.47 | K108: 0.47 | L108: 0.47 | M108: 0.47 | N108: 0.47 | O108: 0.47 | P108: 0.47 | Q108: 0.47 | R108: 0.47 | S108: 0.47 | T108: 0.4 | U108: 0.4 | V108: 0.4 | W108: 0.4 | X108: 0.4 | Y108: 0.4 | Z108: 0.4 | AA108: 0.4 | AB108: 0.4 | AC108: 0.4 | AD108: 0.4 | AE108: 0.4
A109: SKU mix of regular units -- Atlas (regular sales from Apr-2028) | B109: mix_atl | C109: 0 | D109: 0 | E109: 0 | F109: 0 | G109: 0 | H109: 0 | I109: 0 | J109: 0 | K109: 0 | L109: 0 | M109: 0 | N109: 0 | O109: 0 | P109: 0 | Q109: 0 | R109: 0 | S109: 0 | T109: 0.15 | U109: 0.15 | V109: 0.15 | W109: 0.15 | X109: 0.15 | Y109: 0.15 | Z109: 0.15 | AA109: 0.15 | AB109: 0.15 | AC109: 0.15 | AD109: 0.15 | AE109: 0.15
A110: B2B fleet devices deployed (end of period) | B110: fleet_end | C110: 0 | D110: 0 | E110: 0 | F110: 0 | G110: 0 | H110: 0 | I110: 0 | J110: 0 | K110: 0 | L110: 0 | M110: 0 | N110: 0 | O110: 0 | P110: 0 | Q110: 0 | R110: 0 | S110: 0 | T110: 50 | U110: 100 | V110: 150 | W110: 200 | X110: 250 | Y110: 300 | Z110: 400 | AA110: 500 | AB110: 600 | AC110: 2500 | AD110: 6000 | AE110: 11000 | AG110: Hostels & tour operators.
A111: Landed-COGS index (learning curve / volume) | B111: cogs_index | C111: 1 | D111: 1 | E111: 1 | F111: 1 | G111: 1 | H111: 1 | I111: 1 | J111: 1 | K111: 1 | L111: 1 | M111: 1 | N111: 1 | O111: 1 | P111: 1 | Q111: 1 | R111: 1 | S111: 1 | T111: 1 | U111: 1 | V111: 1 | W111: 0.95 | X111: 0.95 | Y111: 0.95 | Z111: 0.95 | AA111: 0.95 | AB111: 0.95 | AC111: 0.89 | AD111: 0.82 | AE111: 0.79 | AG111: hardware/bom: 10k->100k tier ratio ~0.79-0.81 for all SKUs; H2-2028 0.95 = DRAM normalisation (Square normalised $206 vs $227).
...

Sheet Scenarios
A1: Scenarios -- set the selector (1 = Bear, 2 = Base, 3 = Bull). Every sheet recalculates.
A3: ACTIVE SCENARIO (1/2/3) | C3: 2 | D3: =CHOOSE(Scenario,"Bear","Base","Bull") -> Base
A5: Driver | B5: Name | C5: Bear | D5: Base | E5: Bull | F5: LIVE | G5: What it does / rationale
A6: Unit volume multiplier (KS + regular sales) | B6: sc_vol | C6: 0.55 | D6: 1 | E6: 1.45 | F6: =CHOOSE(Scenario,C6,D6,E6) -> 1 | G6: Bear ~ a mid-sized KS ($0.55M) and slow retail; bull ~ breakout KS + strong retail sell-through.
A7: Hardware & subscription price multiplier | B7: sc_price | C7: 0.93 | D7: 1 | E7: 1 | F7: =CHOOSE(Scenario,C7,D7,E7) -> 1 | G7: Bear assumes ~7% deeper promotions / price cuts.
A8: Subscription attach multiplier | B8: sc_attach | C8: 0.7 | D8: 1 | E8: 1.25 | F8: =CHOOSE(Scenario,C8,D8,E8) -> 1 | G8: Applied to post-trial paid conversion per SKU.
A9: Subscription churn multiplier | B9: sc_churn | C9: 1.3 | D9: 1 | E9: 0.8 | F9: =CHOOSE(Scenario,C9,D9,E9) -> 1 | G9: Bear 7.8%/mo, base 6.0%/mo, bull 4.8%/mo.
A10: Landed COGS multiplier | B10: sc_cogs | C10: 1.1 | D10: 1 | E10: 0.95 | F10: =CHOOSE(Scenario,C10,D10,E10) -> 1 | G10: Bear: memory price spike / tariffs; bull: better ODM quote.
A11: CAC / paid-acquisition multiplier | B11: sc_cac | C11: 1.35 | D11: 1 | E11: 0.85 | F11: =CHOOSE(Scenario,C11,D11,E11) -> 1 | G11: Applied to paid CAC per DTC unit.
A15: SCENARIO SNAPSHOT (static values written by scripts/run_all.py after LibreOffice recalc of each scenario; re-run the script after changing inputs)
A16: Metric | B16: Scenario | C16: FY2026 | D16: FY2027 | E16: FY2028 | F16: FY2029 | G16: FY2030 | H16: FY2031
A17: Units shipped | B17: Bear | C17: 0 | D17: 2033.625 | E17: 21588.875 | F17: 66000 | G17: 137500 | H17: 220000
A18: Units shipped | B18: Base | C18: 0 | D18: 3697.5 | E18: 39252.5 | F18: 120000 | G18: 250000 | H18: 400000
A19: Units shipped | B19: Bull | C19: 0 | D19: 5361.375 | E19: 56916.125 | F19: 174000 | G19: 362500 | H19: 580000
A20: Revenue | B20: Bear | C20: 0 | D20: 335843.72 | E20: 5099835.3 | F20: 16034941 | G20: 33901014 | H20: 56150489
A21: Revenue | B21: Base | C21: 0 | D21: 656496.72 | E21: 10020674 | F21: 31635040 | G21: 67070783 | H21: 1.1133476e+08
A22: Revenue | B22: Bull | C22: 0 | D22: 951920.24 | E22: 14637557 | F22: 46643891 | G22: 99502275 | H22: 1.6612553e+08
A23: Gross margin % | B23: Bear | C23: 0 | D23: -0.035751427 | E23: 0.11661911 | F23: 0.1916271 | G23: 0.25713058 | H23: 0.30179441
A24: Gross margin % | B24: Base | C24: 0 | D24: 0.11214054 | E24: 0.23855058 | F24: 0.30235134 | G24: 0.35876946 | H24: 0.39734116
A25: Gross margin % | B25: Bull | C25: 0 | D25: 0.15158436 | E25: 0.27288933 | F25: 0.33654443 | G25: 0.39209644 | H25: 0.4305719
A26: EBITDA | B26: Bear | C26: -198666.67 | D26: -4159019.2 | E26: -5904312.4 | F26: -13066128 | G26: -18895179 | H26: -23192540
A27: EBITDA | B27: Base | C27: -198666.67 | D27: -4115400 | E27: -4613729.6 | F27: -8160796.7 | G27: -6583183.9 | H27: -621008.36
A28: EBITDA | B28: Bull | C28: -198666.67 | D28: -4083451.4 | E28: -3466513.7 | F28: -3464032 | G28: 5620914.4 | H28: 22395093
... A34: Subscription ARR (end) | B34: Bull | C34: 0 | D34: 0 | E34: 1492299.1 | F34: 6492515 | G34: 15190172 | H34: 27738297
A35: Min cash (with planned rounds) / peak cumulative burn / first EBITDA+ FY | B35: Bear | C35: -3617882.7 | D35: 74117883 | E35: after FY31
A36: Min cash (with planned rounds) / peak cumulative burn / first EBITDA+ FY | B36: Base | C36: 420194.5 | D36: 37073502 | E36: after FY31
A37: Min cash (with planned rounds) / peak cumulative burn / first EBITDA+ FY | B37: Bull | C37: 420194.5 | D37: 16791529 | E37: 2030

Sheet Pricing & Mix
A1: Pricing & SKU mix -- units by SKU and channel
A2: Period | C2: =Timeline!C2 -> Nov-26 | D2: =Timeline!D2 -> Dec-26 | E2: =Timeline!E2 -> Jan-27 | F2: =Timeline!F2 -> Feb-27 | G2: =Timeline!G2 -> Mar-27 | H2: =Timeline!H2 -> Apr-27 | I2: =Timeline!I2 -> May-27 | J2: =Timeline!J2 -> Jun-27 | ... AE2: =Timeline!AE2 -> FY2031 | AG2: FY2026 (Nov-Dec) | AH2: FY2027 | AI2: FY2028 | AJ2: FY2029 | AK2: FY2030 | AL2: FY2031
A3: Year | C3: =Timeline!C3 -> 2026 | D3: =Timeline!D3 -> 2026 | E3: =Timeline!E3 -> 2027 | F3: =Timeline!F3 -> 2027 | G3: =Timeline!G3 -> 2027 | H3: =Timeline!H3 -> 2027 | I3: =Timeline!I3 -> 2027 | J3: =Timeline!J3 -> 2027 | ... AE3: =Timeline!AE3 -> 2031 | AG3: 2026 | AH3: 2027 | AI3: 2028 | AJ3: 2029 | AK3: 2030 | AL3: 2031
A4: Months in period | C4: =Timeline!C4 -> 1 | D4: =Timeline!D4 -> 1 | E4: =Timeline!E4 -> 1 | F4: =Timeline!F4 -> 1 | G4: =Timeline!G4 -> 1 | H4: =Timeline!H4 -> 1 | I4: =Timeline!I4 -> 1 | J4: =Timeline!J4 -> 1 | ... AE4: =Timeline!AE4 -> 12
A5: Period start | C5: =Timeline!C5 -> 46327 | D5: =Timeline!D5 -> 46357 | E5: =Timeline!E5 -> 46388 | F5: =Timeline!F5 -> 46419 | G5: =Timeline!G5 -> 46447 | H5: =Timeline!H5 -> 46478 | I5: =Timeline!I5 -> 46508 | J5: =Timeline!J5 -> 46539 | ... AE5: =Timeline!AE5 -> 47849
A6: Period key | C6: =Timeline!C6 -> 202611 | D6: =Timeline!D6 -> 202612 | E6: =Timeline!E6 -> 202701 | F6: =Timeline!F6 -> 202702 | G6: =Timeline!G6 -> 202703 | H6: =Timeline!H6 -> 202704 | I6: =Timeline!I6 -> 202705 | J6: =Timeline!J6 -> 202706 | ... AE6: =Timeline!AE6 -> 2031
A9: Prices ($/unit)
A10: MSRP -- Pebble | B10: $ | C10: =msrp_peb*sc_price -> 149 | D10: =msrp_peb*sc_price -> 149 | E10: =msrp_peb*sc_price -> 149 | F10: =msrp_peb*sc_price -> 149 | G10: =msrp_peb*sc_price -> 149 | H10: =msrp_peb*sc_price -> 149 | I10: =msrp_peb*sc_price -> 149 | J10: =msrp_peb*sc_price -> 149 | ... AE10: =msrp_peb*sc_price -> 149
A11: MSRP -- Square | B11: $ | C11: =msrp_sq*sc_price -> 299 | D11: =msrp_sq*sc_price -> 299 | E11: =msrp_sq*sc_price -> 299 | F11: =msrp_sq*sc_price -> 299 | G11: =msrp_sq*sc_price -> 299 | H11: =msrp_sq*sc_price -> 299 | I11: =msrp_sq*sc_price -> 299 | J11: =msrp_sq*sc_price -> 299 | ... AE11: =msrp_sq*sc_price -> 299
A12: MSRP -- Atlas | B12: $ | C12: =msrp_atl*sc_price -> 599 | D12: =msrp_atl*sc_price -> 599 | E12: =msrp_atl*sc_price -> 599 | F12: =msrp_atl*sc_price -> 599 | G12: =msrp_atl*sc_price -> 599 | H12: =msrp_atl*sc_price -> 599 | I12: =msrp_atl*sc_price -> 599 | J12: =msrp_atl*sc_price -> 599 | ... AE12: =msrp_atl*sc_price -> 599
A13: DTC net price -- Pebble | B13: $ | C13: ='Pricing & Mix'!C10*(1-dtc_disc) -> 140.06 | D13: ='Pricing & Mix'!D10*(1-dtc_disc) -> 140.06 | E13: ='Pricing & Mix'!E10*(1-dtc_disc) -> 140.06 | F13: ='Pricing & Mix'!F10*(1-dtc_disc) -> 140.06 | G13: ='Pricing & Mix'!G10*(1-dtc_disc) -> 140.06 | H13: ='Pricing & Mix'!H10*(1-dtc_disc) -> 140.06 | I13: ='Pricing & Mix'!I10*(1-dtc_disc) -> 140.06 | J13: ='Pricing & Mix'!J10*(1-dtc_disc) -> 140.06 | ... AE13: ='Pricing & Mix'!AE10*(1-dtc_disc) -> 140.06
A14: DTC net price -- Square | B14: $ | C14: ='Pricing & Mix'!C11*(1-dtc_disc) -> 281.06 | D14: ='Pricing & Mix'!D11*(1-dtc_disc) -> 281.06 | E14: ='Pricing & Mix'!E11*(1-dtc_disc) -> 281.06 | F14: ='Pricing & Mix'!F11*(1-dtc_disc) -> 281.06 | G14: ='Pricing & Mix'!G11*(1-dtc_disc) -> 281.06 | H14: ='Pricing & Mix'!H11*(1-dtc_disc) -> 281.06 | I14: ='Pricing & Mix'!I11*(1-dtc_disc) -> 281.06 | J14: ='Pricing & Mix'!J11*(1-dtc_disc) -> 281.06 | ... AE14: ='Pricing & Mix'!AE11*(1-dtc_disc) -> 281.06
A15: DTC net price -- Atlas | B15: $ | C15: ='Pricing & Mix'!C12*(1-dtc_disc) -> 563.06 | D15: ='Pricing & Mix'!D12*(1-dtc_disc) -> 563.06 | E15: ='Pricing & Mix'!E12*(1-dtc_disc) -> 563.06 | F15: ='Pricing & Mix'!F12*(1-dtc_disc) -> 563.06 | G15: ='Pricing & Mix'!G12*(1-dtc_disc) -> 563.06 | H15: ='Pricing & Mix'!H12*(1-dtc_disc) -> 563.06 | I15: ='Pricing & Mix'!I12*(1-dtc_disc) -> 563.06 | J15: ='Pricing & Mix'!J12*(1-dtc_disc) -> 563.06 | ... AE15: ='Pricing & Mix'!AE12*(1-dtc_disc) -> 563.06
A16: Retail sell-in price -- Pebble | B16: $ | C16: ='Pricing & Mix'!C10*(1-retail_margin) -> 92.38 | D16: ='Pricing & Mix'!D10*(1-retail_margin) -> 92.38 | E16: ='Pricing & Mix'!E10*(1-retail_margin) -> 92.38 | F16: ='Pricing & Mix'!F10*(1-retail_margin) -> 92.38 | G16: ='Pricing & Mix'!G10*(1-retail_margin) -> 92.38 | H16: ='Pricing & Mix'!H10*(1-retail_margin) -> 92.38 | I16: ='Pricing & Mix'!I10*(1-retail_margin) -> 92.38 | J16: ='Pricing & Mix'!J10*(1-retail_margin) -> 92.38 | ... AE16: ='Pricing & Mix'!AE10*(1-retail_margin) -> 92.38
A17: Retail sell-in price -- Square | B17: $ | C17: ='Pricing & Mix'!C11*(1-retail_margin) -> 185.38 | D17: ='Pricing & Mix'!D11*(1-retail_margin) -> 185.38 | E17: ='Pricing & Mix'!E11*(1-retail_margin) -> 185.38 | F17: ='Pricing & Mix'!F11*(1-retail_margin) -> 185.38 | G17: ='Pricing & Mix'!G11*(1-retail_margin) -> 185.38 | H17: ='Pricing & Mix'!H11*(1-retail_margin) -> 185.38 | I17: ='Pricing & Mix'!I11*(1-retail_margin) -> 185.38 | J17: ='Pricing & Mix'!J11*(1-retail_margin) -> 185.38 | ... AE17: ='Pricing & Mix'!AE11*(1-retail_margin) -> 185.38
A18: Retail sell-in price -- Atlas | B18: $ | C18: ='Pricing & Mix'!C12*(1-retail_margin) -> 371.38 | D18: ='Pricing & Mix'!D12*(1-retail_margin) -> 371.38 | E18: ='Pricing & Mix'!E12*(1-retail_margin) -> 371.38 | F18: ='Pricing & Mix'!F12*(1-retail_margin) -> 371.38 | G18: ='Pricing & Mix'!G12*(1-retail_margin) -> 371.38 | H18: ='Pricing & Mix'!H12*(1-retail_margin) -> 371.38 | I18: ='Pricing & Mix'!I12*(1-retail_margin) -> 371.38 | J18: ='Pricing & Mix'!J12*(1-retail_margin) -> 371.38 | ... AE18: ='Pricing & Mix'!AE12*(1-retail_margin) -> 371.38
A19: Pre-order blended price -- Pebble | B19: $ | C19: =(ks_units*ks_peb+pre_units*pre_peb)/(ks_units+pre_units)*sc_price -> 115.4 | D19: =(ks_units*ks_peb+pre_units*pre_peb)/(ks_units+pre_units)*sc_price -> 115.4 | E19: =(ks_units*ks_peb+pre_units*pre_peb)/(ks_units+pre_units)*sc_price -> 115.4 | F19: =(ks_units*ks_peb+pre_units*pre_peb)/(ks_units+pre_units)*sc_price -> 115.4 | G19: =(ks_units*ks_peb+pre_units*pre_peb)/(ks_units+pre_units)*sc_price -> 115.4 | H19: =(ks_units*ks_peb+pre_units*pre_peb)/(ks_units+pre_units)*sc_price -> 115.4 | I19: =(ks_units*ks_peb+pre_units*pre_peb)/(ks_units+pre_units)*sc_price -> 115.4 | J19: =(ks_units*ks_peb+pre_units*pre_peb)/(ks_units+pre_units)*sc_price -> 115.4 | ... AE19: =(ks_units*ks_peb+pre_units*pre_peb)/(ks_units+pre_units)*sc_price -> 115.4
A20: Pre-order blended price -- Square | B20: $ | C20: =(ks_units*ks_sq+pre_units*pre_sq)/(ks_units+pre_units)*sc_price -> 232.6 | D20: =(ks_units*ks_sq+pre_units*pre_sq)/(ks_units+pre_units)*sc_price -> 232.6 | E20: =(ks_units*ks_sq+pre_units*pre_sq)/(ks_units+pre_units)*sc_price -> 232.6 | F20: =(ks_units*ks_sq+pre_units*pre_sq)/(ks_units+pre_units)*sc_price -> 232.6 | G20: =(ks_units*ks_sq+pre_units*pre_sq)/(ks_units+pre_units)*sc_price -> 232.6 | H20: =(ks_units*ks_sq+pre_units*pre_sq)/(ks_units+pre_units)*sc_price -> 232.6 | I20: =(ks_units*ks_sq+pre_units*pre_sq)/(ks_units+pre_units)*sc_price -> 232.6 | J20: =(ks_units*ks_sq+pre_units*pre_sq)/(ks_units+pre_units)*sc_price -> 232.6 | ... AE20: =(ks_units*ks_sq+pre_units*pre_sq)/(ks_units+pre_units)*sc_price -> 232.6
A21: Pre-order blended price -- Atlas | B21: $ | C21: =(ks_units*ks_atl+pre_units*pre_atl)/(ks_units+pre_units)*sc_price -> 453.4 | D21: =(ks_units*ks_atl+pre_units*pre_atl)/(ks_units+pre_units)*sc_price -> 453.4 | E21: =(ks_units*ks_atl+pre_units*pre_atl)/(ks_units+pre_units)*sc_price -> 453.4 | F21: =(ks_units*ks_atl+pre_units*pre_atl)/(ks_units+pre_units)*sc_price -> 453.4 | G21: =(ks_units*ks_atl+pre_units*pre_atl)/(ks_units+pre_units)*sc_price -> 453.4 | H21: =(ks_units*ks_atl+pre_units*pre_atl)/(ks_units+pre_units)*sc_price -> 453.4 | I21: =(ks_units*ks_atl+pre_units*pre_atl)/(ks_units+pre_units)*sc_price -> 453.4 | J21: =(ks_units*ks_atl+pre_units*pre_atl)/(ks_units+pre_units)*sc_price -> 453.4 | ... AE21: =(ks_units*ks_atl+pre_units*pre_atl)/(ks_units+pre_units)*sc_price -> 453.4
A23: Units
A24: Regular units sold (after scenario) | B24: units | C24: =Assumptions!C102*sc_vol -> 0 | D24: =Assumptions!D102*sc_vol -> 0 | E24: =Assumptions!E102*sc_vol -> 0 | F24: =Assumptions!F102*sc_vol -> 0 | G24: =Assumptions!G102*sc_vol -> 0 | H24: =Assumptions!H102*sc_vol -> 0 | I24: =Assumptions!I102*sc_vol -> 0 | J24: =Assumptions!J102*sc_vol -> 0 | ... AE24: =Assumptions!AE102*sc_vol -> 400000 | AG24: =SUMIF($C$3:$AE$3,AG$3,$C24:$AE24) -> 0 | AH24: =SUMIF($C$3:$AE$3,AH$3,$C24:$AE24) -> 0 | AI24: =SUMIF($C$3:$AE$3,AI$3,$C24:$AE24) -> 37950 | AJ24: =SUMIF($C$3:$AE$3,AJ$3,$C24:$AE24) -> 120000 | AK24: =SUMIF($C$3:$AE$3,AK$3,$C24:$AE24) -> 250000 | AL24: =SUMIF($C$3:$AE$3,AL$3,$C24:$AE24) -> 400000
A25: Mix -- Pebble | B25: % | C25: =Assumptions!C107 -> 0.53 | D25: =Assumptions!D107 -> 0.53 | E25: =Assumptions!E107 -> 0.53 | F25: =Assumptions!F107 -> 0.53 | G25: =Assumptions!G107 -> 0.53 | H25: =Assumptions!H107 -> 0.53 | I25: =Assumptions!I107 -> 0.53 | J25: =Assumptions!J107 -> 0.53 | ... AE25: =Assumptions!AE107 -> 0.45
A26: Mix -- Square | B26: % | C26: =Assumptions!C108 -> 0.47 | D26: =Assumptions!D108 -> 0.47 | E26: =Assumptions!E108 -> 0.47 | F26: =Assumptions!F108 -> 0.47 | G26: =Assumptions!G108 -> 0.47 | H26: =Assumptions!H108 -> 0.47 | I26: =Assumptions!I108 -> 0.47 | J26: =Assumptions!J108 -> 0.47 | ... AE26: =Assumptions!AE108 -> 0.4
A27: Mix -- Atlas | B27: % | C27: =Assumptions!C109 -> 0 | D27: =Assumptions!D109 -> 0 | E27: =Assumptions!E109 -> 0 | F27: =Assumptions!F109 -> 0 | G27: =Assumptions!G109 -> 0 | H27: =Assumptions!H109 -> 0 | I27: =Assumptions!I109 -> 0 | J27: =Assumptions!J109 -> 0 | ... AE27: =Assumptions!AE109 -> 0.15
A28: Retail share | B28: % | C28: =Assumptions!C106 -> 0 | D28: =Assumptions!D106 -> 0 | E28: =Assumptions!E106 -> 0 | F28: =Assumptions!F106 -> 0 | G28: =Assumptions!G106 -> 0 | H28: =Assumptions!H106 -> 0 | I28: =Assumptions!I106 -> 0 | J28: =Assumptions!J106 -> 0 | ... AE28: =Assumptions!AE106 -> 0.35
A29: DTC units -- Pebble | B29: units | C29: ='Pricing & Mix'!C24*'Pricing & Mix'!C25*(1-'Pricing & Mix'!C28) -> 0 | D29: ='Pricing & Mix'!D24*'Pricing & Mix'!D25*(1-'Pricing & Mix'!D28) -> 0 | E29: ='Pricing & Mix'!E24*'Pricing & Mix'!E25*(1-'Pricing & Mix'!E28) -> 0 | F29: ='Pricing & Mix'!F24*'Pricing & Mix'!F25*(1-'Pricing & Mix'!F28) -> 0 | G29: ='Pricing & Mix'!G24*'Pricing & Mix'!G25*(1-'Pricing & Mix'!G28) -> 0 | H29: ='Pricing & Mix'!H24*'Pricing & Mix'!H25*(1-'Pricing & Mix'!H28) -> 0 | I29: ='Pricing & Mix'!I24*'Pricing & Mix'!I25*(1-'Pricing & Mix'!I28) -> 0 | J29: ='Pricing & Mix'!J24*'Pricing & Mix'!J25*(1-'Pricing & Mix'!J28) -> 0 | ... AE29: ='Pricing & Mix'!AE24*'Pricing & Mix'!AE25*(1-'Pricing & Mix'!AE28) -> 117000 | AG29: =SUMIF($C$3:$AE$3,AG$3,$C29:$AE29) -> 0 | AH29: =SUMIF($C$3:$AE$3,AH$3,$C29:$AE29) -> 0 | AI29: =SUMIF($C$3:$AE$3,AI$3,$C29:$AE29) -> 13897.125 | AJ29: =SUMIF($C$3:$AE$3,AJ$3,$C29:$AE29) -> 37800 | AK29: =SUMIF($C$3:$AE$3,AK$3,$C29:$AE29) -> 73125 | AL29: =SUMIF($C$3:$AE$3,AL$3,$C29:$AE29) -> 117000
A30: DTC units -- Square | B30: units | C30: ='Pricing & Mix'!C24*'Pricing & Mix'!C26*(1-'Pricing & Mix'!C28) -> 0 | D30: ='Pricing & Mix'!D24*'Pricing & Mix'!D26*(1-'Pricing & Mix'!D28) -> 0 | E30: ='Pricing & Mix'!E24*'Pricing & Mix'!E26*(1-'Pricing & Mix'!E28) -> 0 | F30: ='Pricing & Mix'!F24*'Pricing & Mix'!F26*(1-'Pricing & Mix'!F28) -> 0 | G30: ='Pricing & Mix'!G24*'Pricing & Mix'!G26*(1-'Pricing & Mix'!G28) -> 0 | H30: ='Pricing & Mix'!H24*'Pricing & Mix'!H26*(1-'Pricing & Mix'!H28) -> 0 | I30: ='Pricing & Mix'!I24*'Pricing & Mix'!I26*(1-'Pricing & Mix'!I28) -> 0 | J30: ='Pricing & Mix'!J24*'Pricing & Mix'!J26*(1-'Pricing & Mix'!J28) -> 0 | ... AE30: ='Pricing & Mix'!AE24*'Pricing & Mix'!AE26*(1-'Pricing & Mix'!AE28) -> 104000 | AG30: =SUMIF($C$3:$AE$3,AG$3,$C30:$AE30) -> 0 | AH30: =SUMIF($C$3:$AE$3,AH$3,$C30:$AE30) -> 0 | AI30: =SUMIF($C$3:$AE$3,AI$3,$C30:$AE30) -> 12348.75 | AJ30: =SUMIF($C$3:$AE$3,AJ$3,$C30:$AE30) -> 33600 | AK30: =SUMIF($C$3:$AE$3,AK$3,$C30:$AE30) -> 65000 | AL30: =SUMIF($C$3:$AE$3,AL$3,$C30:$AE30) -> 104000
A31: DTC units -- Atlas | B31: units | C31: ='Pricing & Mix'!C24*'Pricing & Mix'!C27*(1-'Pricing & Mix'!C28) -> 0 | D31: ='Pricing & Mix'!D24*'Pricing & Mix'!D27*(1-'Pricing & Mix'!D28) -> 0 | E31: ='Pricing & Mix'!E24*'Pricing & Mix'!E27*(1-'Pricing & Mix'!E28) -> 0 | F31: ='Pricing & Mix'!F24*'Pricing & Mix'!F27*(1-'Pricing & Mix'!F28) -> 0 | G31: ='Pricing & Mix'!G24*'Pricing & Mix'!G27*(1-'Pricing & Mix'!G28) -> 0 | H31: ='Pricing & Mix'!H24*'Pricing & Mix'!H27*(1-'Pricing & Mix'!H28) -> 0 | I31: ='Pricing & Mix'!I24*'Pricing & Mix'!I27*(1-'Pricing & Mix'!I28) -> 0 | J31: ='Pricing & Mix'!J24*'Pricing & Mix'!J27*(1-'Pricing & Mix'!J28) -> 0 | ... AE31: ='Pricing & Mix'!AE24*'Pricing & Mix'!AE27*(1-'Pricing & Mix'!AE28) -> 39000 | AG31: =SUMIF($C$3:$AE$3,AG$3,$C31:$AE31) -> 0 | AH31: =SUMIF($C$3:$AE$3,AH$3,$C31:$AE31) -> 0 | AI31: =SUMIF($C$3:$AE$3,AI$3,$C31:$AE31) -> 3956.625 | AJ31: =SUMIF($C$3:$AE$3,AJ$3,$C31:$AE31) -> 12600 | AK31: =SUMIF($C$3:$AE$3,AK$3,$C31:$AE31) -> 24375 | AL31: =SUMIF($C$3:$AE$3,AL$3,$C31:$AE31) -> 39000
A32: Retail units -- Pebble | B32: units | C32: ='Pricing & Mix'!C24*'Pricing & Mix'!C25*'Pricing & Mix'!C28 -> 0 | D32: ='Pricing & Mix'!D24*'Pricing & Mix'!D25*'Pricing & Mix'!D28 -> 0 | E32: ='Pricing & Mix'!E24*'Pricing & Mix'!E25*'Pricing & Mix'!E28 -> 0 | F32: ='Pricing & Mix'!F24*'Pricing & Mix'!F25*'Pricing & Mix'!F28 -> 0 | G32: ='Pricing & Mix'!G24*'Pricing & Mix'!G25*'Pricing & Mix'!G28 -> 0 | H32: ='Pricing & Mix'!H24*'Pricing & Mix'!H25*'Pricing & Mix'!H28 -> 0 | I32: ='Pricing & Mix'!I24*'Pricing & Mix'!I25*'Pricing & Mix'!I28 -> 0 | J32: ='Pricing & Mix'!J24*'Pricing & Mix'!J25*'Pricing & Mix'!J28 -> 0 | ... AE32: ='Pricing & Mix'!AE24*'Pricing & Mix'!AE25*'Pricing & Mix'!AE28 -> 63000 | AG32: =SUMIF($C$3:$AE$3,AG$3,$C32:$AE32) -> 0 | AH32: =SUMIF($C$3:$AE$3,AH$3,$C32:$AE32) -> 0 | AI32: =SUMIF($C$3:$AE$3,AI$3,$C32:$AE32) -> 3520.375 | AJ32: =SUMIF($C$3:$AE$3,AJ$3,$C32:$AE32) -> 16200 | AK32: =SUMIF($C$3:$AE$3,AK$3,$C32:$AE32) -> 39375 | AL32: =SUMIF($C$3:$AE$3,AL$3,$C32:$AE32) -> 63000
A33: Retail units -- Square | B33: units | C33: ='Pricing & Mix'!C24*'Pricing & Mix'!C26*'Pricing & Mix'!C28 -> 0 | D33: ='Pricing & Mix'!D24*'Pricing & Mix'!D26*'Pricing & Mix'!D28 -> 0 | E33: ='Pricing & Mix'!E24*'Pricing & Mix'!E26*'Pricing & Mix'!E28 -> 0 | F33: ='Pricing & Mix'!F24*'Pricing & Mix'!F26*'Pricing & Mix'!F28 -> 0 | G33: ='Pricing & Mix'!G24*'Pricing & Mix'!G26*'Pricing & Mix'!G28 -> 0 | H33: ='Pricing & Mix'!H24*'Pricing & Mix'!H26*'Pricing & Mix'!H28 -> 0 | I33: ='Pricing & Mix'!I24*'Pricing & Mix'!I26*'Pricing & Mix'!I28 -> 0 | J33: ='Pricing & Mix'!J24*'Pricing & Mix'!J26*'Pricing & Mix'!J28 -> 0 | ... AE33: ='Pricing & Mix'!AE24*'Pricing & Mix'!AE26*'Pricing & Mix'!AE28 -> 56000 | AG33: =SUMIF($C$3:$AE$3,AG$3,$C33:$AE33) -> 0 | AH33: =SUMIF($C$3:$AE$3,AH$3,$C33:$AE33) -> 0 | AI33: =SUMIF($C$3:$AE$3,AI$3,$C33:$AE33) -> 3128.75 | AJ33: =SUMIF($C$3:$AE$3,AJ$3,$C33:$AE33) -> 14400 | AK33: =SUMIF($C$3:$AE$3,AK$3,$C33:$AE33) -> 35000 | AL33: =SUMIF($C$3:$AE$3,AL$3,$C33:$AE33) -> 56000
A34: Retail units -- Atlas | B34: units | C34: ='Pricing & Mix'!C24*'Pricing & Mix'!C27*'Pricing & Mix'!C28 -> 0 | D34: ='Pricing & Mix'!D24*'Pricing & Mix'!D27*'Pricing & Mix'!D28 -> 0 | E34: ='Pricing & Mix'!E24*'Pricing & Mix'!E27*'Pricing & Mix'!E28 -> 0 | F34: ='Pricing & Mix'!F24*'Pricing & Mix'!F27*'Pricing & Mix'!F28 -> 0 | G34: ='Pricing & Mix'!G24*'Pricing & Mix'!G27*'Pricing & Mix'!G28 -> 0 | H34: ='Pricing & Mix'!H24*'Pricing & Mix'!H27*'Pricing & Mix'!H28 -> 0 | I34: ='Pricing & Mix'!I24*'Pricing & Mix'!I27*'Pricing & Mix'!I28 -> 0 | J34: ='Pricing & Mix'!J24*'Pricing & Mix'!J27*'Pricing & Mix'!J28 -> 0 | ... AE34: ='Pricing & Mix'!AE24*'Pricing & Mix'!AE27*'Pricing & Mix'!AE28 -> 21000 | AG34: =SUMIF($C$3:$AE$3,AG$3,$C34:$AE34) -> 0 | AH34: =SUMIF($C$3:$AE$3,AH$3,$C34:$AE34) -> 0 | AI34: =SUMIF($C$3:$AE$3,AI$3,$C34:$AE34) -> 1098.375 | AJ34: =SUMIF($C$3:$AE$3,AJ$3,$C34:$AE34) -> 5400 | AK34: =SUMIF($C$3:$AE$3,AK$3,$C34:$AE34) -> 13125 | AL34: =SUMIF($C$3:$AE$3,AL$3,$C34:$AE34) -> 21000
A35: Pre-order units shipped -- Pebble | B35: units | C35: =(ks_units+pre_units)*sc_vol*Assumptions!C103*pre_mix_peb -> 0 | D35: =(ks_units+pre_units)*sc_vol*Assumptions!D103*pre_mix_peb -> 0 | E35: =(ks_units+pre_units)*sc_vol*Assumptions!E103*pre_mix_peb -> 0 | F35: =(ks_units+pre_units)*sc_vol*Assumptions!F103*pre_mix_peb -> 0 | G35: =(ks_units+pre_units)*sc_vol*Assumptions!G103*pre_mix_peb -> 0 | H35: =(ks_units+pre_units)*sc_vol*Assumptions!H103*pre_mix_peb -> 0 | I35: =(ks_units+pre_units)*sc_vol*Assumptions!I103*pre_mix_peb -> 0 | J35: =(ks_units+pre_units)*sc_vol*Assumptions!J103*pre_mix_peb -> 0 | ... AE35: =(ks_units+pre_units)*sc_vol*Assumptions!AE103*pre_mix_peb -> 0 | AG35: =SUMIF($C$3:$AE$3,AG$3,$C35:$AE35) -> 0 | AH35: =SUMIF($C$3:$AE$3,AH$3,$C35:$AE35) -> 1957.5 | AI35: =SUMIF($C$3:$AE$3,AI$3,$C35:$AE35) -> 292.5 | AJ35: =SUMIF($C$3:$AE$3,AJ$3,$C35:$AE35) -> 0 | AK35: =SUMIF($C$3:$AE$3,AK$3,$C35:$AE35) -> 0 | AL35: =SUMIF($C$3:$AE$3,AL$3,$C35:$AE35) -> 0
A36: Pre-order units shipped -- Square | B36: units | C36: =(ks_units+pre_units)*sc_vol*Assumptions!C103*(1-pre_mix_peb-pre_mix_atl) -> 0 | D36: =(ks_units+pre_units)*sc_vol*Assumptions!D103*(1-pre_mix_peb-pre_mix_atl) -> 0 | E36: =(ks_units+pre_units)*sc_vol*Assumptions!E103*(1-pre_mix_peb-pre_mix_atl) -> 0 | F36: =(ks_units+pre_units)*sc_vol*Assumptions!F103*(1-pre_mix_peb-pre_mix_atl) -> 0 | G36: =(ks_units+pre_units)*sc_vol*Assumptions!G103*(1-pre_mix_peb-pre_mix_atl) -> 0 | H36: =(ks_units+pre_units)*sc_vol*Assumptions!H103*(1-pre_mix_peb-pre_mix_atl) -> 0 | I36: =(ks_units+pre_units)*sc_vol*Assumptions!I103*(1-pre_mix_peb-pre_mix_atl) -> 0 | J36: =(ks_units+pre_units)*sc_vol*Assumptions!J103*(1-pre_mix_peb-pre_mix_atl) -> 0 | ... AE36: =(ks_units+pre_units)*sc_vol*Assumptions!AE103*(1-pre_mix_peb-pre_mix_atl) -> 0 | AG36: =SUMIF($C$3:$AE$3,AG$3,$C36:$AE36) -> 0 | AH36: =SUMIF($C$3:$AE$3,AH$3,$C36:$AE36) -> 1740 | AI36: =SUMIF($C$3:$AE$3,AI$3,$C36:$AE36) -> 260 | AJ36: =SUMIF($C$3:$AE$3,AJ$3,$C36:$AE36) -> 0 | AK36: =SUMIF($C$3:$AE$3,AK$3,$C36:$AE36) -> 0 | AL36: =SUMIF($C$3:$AE$3,AL$3,$C36:$AE36) -> 0
A37: Pre-order units shipped -- Atlas | B37: units | C37: =(ks_units+pre_units)*sc_vol*Assumptions!C105*pre_mix_atl -> 0 | D37: =(ks_units+pre_units)*sc_vol*Assumptions!D105*pre_mix_atl -> 0 | E37: =(ks_units+pre_units)*sc_vol*Assumptions!E105*pre_mix_atl -> 0 | F37: =(ks_units+pre_units)*sc_vol*Assumptions!F105*pre_mix_atl -> 0 | G37: =(ks_units+pre_units)*sc_vol*Assumptions!G105*pre_mix_atl -> 0 | H37: =(ks_units+pre_units)*sc_vol*Assumptions!H105*pre_mix_atl -> 0 | I37: =(ks_units+pre_units)*sc_vol*Assumptions!I105*pre_mix_atl -> 0 | J37: =(ks_units+pre_units)*sc_vol*Assumptions!J105*pre_mix_atl -> 0 | ... AE37: =(ks_units+pre_units)*sc_vol*Assumptions!AE105*pre_mix_atl -> 0 | AG37: =SUMIF($C$3:$AE$3,AG$3,$C37:$AE37) -> 0 | AH37: =SUMIF($C$3:$AE$3,AH$3,$C37:$AE37) -> 0 | AI37: =SUMIF($C$3:$AE$3,AI$3,$C37:$AE37) -> 750 | AJ37: =SUMIF($C$3:$AE$3,AJ$3,$C37:$AE37) -> 0 | AK37: =SUMIF($C$3:$AE$3,AK$3,$C37:$AE37) -> 0 | AL37: =SUMIF($C$3:$AE$3,AL$3,$C37:$AE37) -> 0
A38: Pre-order (KS + late pledge) units shipped | B38: units | C38: ='Pricing & Mix'!C35+'Pricing & Mix'!C36+'Pricing & Mix'!C37 -> 0 | D38: ='Pricing & Mix'!D35+'Pricing & Mix'!D36+'Pricing & Mix'!D37 -> 0 | E38: ='Pricing & Mix'!E35+'Pricing & Mix'!E36+'Pricing & Mix'!E37 -> 0 | F38: ='Pricing & Mix'!F35+'Pricing & Mix'!F36+'Pricing & Mix'!F37 -> 0 | G38: ='Pricing & Mix'!G35+'Pricing & Mix'!G36+'Pricing & Mix'!G37 -> 0 | H38: ='Pricing & Mix'!H35+'Pricing & Mix'!H36+'Pricing & Mix'!H37 -> 0 | I38: ='Pricing & Mix'!I35+'Pricing & Mix'!I36+'Pricing & Mix'!I37 -> 0 | J38: ='Pricing & Mix'!J35+'Pricing & Mix'!J36+'Pricing & Mix'!J37 -> 0 | ... AE38: ='Pricing & Mix'!AE35+'Pricing & Mix'!AE36+'Pricing & Mix'!AE37 -> 0 | AG38: =SUMIF($C$3:$AE$3,AG$3,$C38:$AE38) -> 0 | AH38: =SUMIF($C$3:$AE$3,AH$3,$C38:$AE38) -> 3697.5 | AI38: =SUMIF($C$3:$AE$3,AI$3,$C38:$AE38) -> 1302.5 | AJ38: =SUMIF($C$3:$AE$3,AJ$3,$C38:$AE38) -> 0 | AK38: =SUMIF($C$3:$AE$3,AK$3,$C38:$AE38) -> 0 | AL38: =SUMIF($C$3:$AE$3,AL$3,$C38:$AE38) -> 0
A39: Total units shipped -- Pebble | B39: units | C39: ='Pricing & Mix'!C29+'Pricing & Mix'!C32+'Pricing & Mix'!C35 -> 0 | D39: ='Pricing & Mix'!D29+'Pricing & Mix'!D32+'Pricing & Mix'!D35 -> 0 | E39: ='Pricing & Mix'!E29+'Pricing & Mix'!E32+'Pricing & Mix'!E35 -> 0 | F39: ='Pricing & Mix'!F29+'Pricing & Mix'!F32+'Pricing & Mix'!F35 -> 0 | G39: ='Pricing & Mix'!G29+'Pricing & Mix'!G32+'Pricing & Mix'!G35 -> 0 | H39: ='Pricing & Mix'!H29+'Pricing & Mix'!H32+'Pricing & Mix'!H35 -> 0 | I39: ='Pricing & Mix'!I29+'Pricing & Mix'!I32+'Pricing & Mix'!I35 -> 0 | J39: ='Pricing & Mix'!J29+'Pricing & Mix'!J32+'Pricing & Mix'!J35 -> 0 | ... AE39: ='Pricing & Mix'!AE29+'Pricing & Mix'!AE32+'Pricing & Mix'!AE35 -> 180000 | AG39: =SUMIF($C$3:$AE$3,AG$3,$C39:$AE39) -> 0 | AH39: =SUMIF($C$3:$AE$3,AH$3,$C39:$AE39) -> 1957.5 | AI39: =SUMIF($C$3:$AE$3,AI$3,$C39:$AE39) -> 17710 | AJ39: =SUMIF($C$3:$AE$3,AJ$3,$C39:$AE39) -> 54000 | AK39: =SUMIF($C$3:$AE$3,AK$3,$C39:$AE39) -> 112500 | AL39: =SUMIF($C$3:$AE$3,AL$3,$C39:$AE39) -> 180000
A40: Total units shipped -- Square | B40: units | C40: ='Pricing & Mix'!C30+'Pricing & Mix'!C33+'Pricing & Mix'!C36 -> 0 | D40: ='Pricing & Mix'!D30+'Pricing & Mix'!D33+'Pricing & Mix'!D36 -> 0 | E40: ='Pricing & Mix'!E30+'Pricing & Mix'!E33+'Pricing & Mix'!E36 -> 0 | F40: ='Pricing & Mix'!F30+'Pricing & Mix'!F33+'Pricing & Mix'!F36 -> 0 | G40: ='Pricing & Mix'!G30+'Pricing & Mix'!G33+'Pricing & Mix'!G36 -> 0 | H40: ='Pricing & Mix'!H30+'Pricing & Mix'!H33+'Pricing & Mix'!H36 -> 0 | I40: ='Pricing & Mix'!I30+'Pricing & Mix'!I33+'Pricing & Mix'!I36 -> 0 | J40: ='Pricing & Mix'!J30+'Pricing & Mix'!J33+'Pricing & Mix'!J36 -> 0 | ... AE40: ='Pricing & Mix'!AE30+'Pricing & Mix'!AE33+'Pricing & Mix'!AE36 -> 160000 | AG40: =SUMIF($C$3:$AE$3,AG$3,$C40:$AE40) -> 0 | AH40: =SUMIF($C$3:$AE$3,AH$3,$C40:$AE40) -> 1740 | AI40: =SUMIF($C$3:$AE$3,AI$3,$C40:$AE40) -> 15737.5 | AJ40: =SUMIF($C$3:$AE$3,AJ$3,$C40:$AE40) -> 48000 | AK40: =SUMIF($C$3:$AE$3,AK$3,$C40:$AE40) -> 100000 | AL40: =SUMIF($C$3:$AE$3,AL$3,$C40:$AE40) -> 160000
A41: Total units shipped -- Atlas | B41: units | C41: ='Pricing & Mix'!C31+'Pricing & Mix'!C34+'Pricing & Mix'!C37 -> 0 | D41: ='Pricing & Mix'!D31+'Pricing & Mix'!D34+'Pricing & Mix'!D37 -> 0 | E41: ='Pricing & Mix'!E31+'Pricing & Mix'!E34+'Pricing & Mix'!E37 -> 0 | F41: ='Pricing & Mix'!F31+'Pricing & Mix'!F34+'Pricing & Mix'!F37 -> 0 | G41: ='Pricing & Mix'!G31+'Pricing & Mix'!G34+'Pricing & Mix'!G37 -> 0 | H41: ='Pricing & Mix'!H31+'Pricing & Mix'!H34+'Pricing & Mix'!H37 -> 0 | I41: ='Pricing & Mix'!I31+'Pricing & Mix'!I34+'Pricing & Mix'!I37 -> 0 | J41: ='Pricing & Mix'!J31+'Pricing & Mix'!J34+'Pricing & Mix'!J37 -> 0 | ... AE41: ='Pricing & Mix'!AE31+'Pricing & Mix'!AE34+'Pricing & Mix'!AE37 -> 60000 | AG41: =SUMIF($C$3:$AE$3,AG$3,$C41:$AE41) -> 0 | AH41: =SUMIF($C$3:$AE$3,AH$3,$C41:$AE41) -> 0 | AI41: =SUMIF($C$3:$AE$3,AI$3,$C41:$AE41) -> 5805 | AJ41: =SUMIF($C$3:$AE$3,AJ$3,$C41:$AE41) -> 18000 | AK41: =SUMIF($C$3:$AE$3,AK$3,$C41:$AE41) -> 37500 | AL41: =SUMIF($C$3:$AE$3,AL$3,$C41:$AE41) -> 60000
A42: TOTAL UNITS SHIPPED | B42: units | C42: ='Pricing & Mix'!C39+'Pricing & Mix'!C40+'Pricing & Mix'!C41 -> 0 | D42: ='Pricing & Mix'!D39+'Pricing & Mix'!D40+'Pricing & Mix'!D41 -> 0 | E42: ='Pricing & Mix'!E39+'Pricing & Mix'!E40+'Pricing & Mix'!E41 -> 0 | F42: ='Pricing & Mix'!F39+'Pricing & Mix'!F40+'Pricing & Mix'!F41 -> 0 | G42: ='Pricing & Mix'!G39+'Pricing & Mix'!G40+'Pricing & Mix'!G41 -> 0 | H42: ='Pricing & Mix'!H39+'Pricing & Mix'!H40+'Pricing & Mix'!H41 -> 0 | I42: ='Pricing & Mix'!I39+'Pricing & Mix'!I40+'Pricing & Mix'!I41 -> 0 | J42: ='Pricing & Mix'!J39+'Pricing & Mix'!J40+'Pricing & Mix'!J41 -> 0 | ... AE42: ='Pricing & Mix'!AE39+'Pricing & Mix'!AE40+'Pricing & Mix'!AE41 -> 400000 | AG42: =SUMIF($C$3:$AE$3,AG$3,$C42:$AE42) -> 0 | AH42: =SUMIF($C$3:$AE$3,AH$3,$C42:$AE42) -> 3697.5 | AI42: =SUMIF($C$3:$AE$3,AI$3,$C42:$AE42) -> 39252.5 | AJ42: =SUMIF($C$3:$AE$3,AJ$3,$C42:$AE42) -> 120000 | AK42: =SUMIF($C$3:$AE$3,AK$3,$C42:$AE42) -> 250000 | AL42: =SUMIF($C$3:$AE$3,AL$3,$C42:$AE42) -> 400000
A43: DTC regular units | B43: units | C43: ='Pricing & Mix'!C29+'Pricing & Mix'!C30+'Pricing & Mix'!C31 -> 0 | D43: ='Pricing & Mix'!D29+'Pricing & Mix'!D30+'Pricing & Mix'!D31 -> 0 | E43: ='Pricing & Mix'!E29+'Pricing & Mix'!E30+'Pricing & Mix'!E31 -> 0 | F43: ='Pricing & Mix'!F29+'Pricing & Mix'!F30+'Pricing & Mix'!F31 -> 0 | G43: ='Pricing & Mix'!G29+'Pricing & Mix'!G30+'Pricing & Mix'!G31 -> 0 | H43: ='Pricing & Mix'!H29+'Pricing & Mix'!H30+'Pricing & Mix'!H31 -> 0 | I43: ='Pricing & Mix'!I29+'Pricing & Mix'!I30+'Pricing & Mix'!I31 -> 0 | J43: ='Pricing & Mix'!J29+'Pricing & Mix'!J30+'Pricing & Mix'!J31 -> 0 | ... AE43: ='Pricing & Mix'!AE29+'Pricing & Mix'!AE30+'Pricing & Mix'!AE31 -> 260000 | AG43: =SUMIF($C$3:$AE$3,AG$3,$C43:$AE43) -> 0 | AH43: =SUMIF($C$3:$AE$3,AH$3,$C43:$AE43) -> 0 | AI43: =SUMIF($C$3:$AE$3,AI$3,$C43:$AE43) -> 30202.5 | AJ43: =SUMIF($C$3:$AE$3,AJ$3,$C43:$AE43) -> 84000 | AK43: =SUMIF($C$3:$AE$3,AK$3,$C43:$AE43) -> 162500 | AL43: =SUMIF($C$3:$AE$3,AL$3,$C43:$AE43) -> 260000
A44: Retail units | B44: units | C44: ='Pricing & Mix'!C32+'Pricing & Mix'!C33+'Pricing & Mix'!C34 -> 0 | D44: ='Pricing & Mix'!D32+'Pricing & Mix'!D33+'Pricing & Mix'!D34 -> 0 | E44: ='Pricing & Mix'!E32+'Pricing & Mix'!E33+'Pricing & Mix'!E34 -> 0 | F44: ='Pricing & Mix'!F32+'Pricing & Mix'!F33+'Pricing & Mix'!F34 -> 0 | G44: ='Pricing & Mix'!G32+'Pricing & Mix'!G33+'Pricing & Mix'!G34 -> 0 | H44: ='Pricing & Mix'!H32+'Pricing & Mix'!H33+'Pricing & Mix'!H34 -> 0 | I44: ='Pricing & Mix'!I32+'Pricing & Mix'!I33+'Pricing & Mix'!I34 -> 0 | J44: ='Pricing & Mix'!J32+'Pricing & Mix'!J33+'Pricing & Mix'!J34 -> 0 | ... AE44: ='Pricing & Mix'!AE32+'Pricing & Mix'!AE33+'Pricing & Mix'!AE34 -> 140000 | AG44: =SUMIF($C$3:$AE$3,AG$3,$C44:$AE44) -> 0 | AH44: =SUMIF($C$3:$AE$3,AH$3,$C44:$AE44) -> 0 | AI44: =SUMIF($C$3:$AE$3,AI$3,$C44:$AE44) -> 7747.5 | AJ44: =SUMIF($C$3:$AE$3,AJ$3,$C44:$AE44) -> 36000 | AK44: =SUMIF($C$3:$AE$3,AK$3,$C44:$AE44) -> 87500 | AL44: =SUMIF($C$3:$AE$3,AL$3,$C44:$AE44) -> 140000
A45: Cumulative units shipped | B45: units | C45: =SUM('Pricing & Mix'!$C42:C42) -> 0 | D45: =SUM('Pricing & Mix'!$C42:D42) -> 0 | E45: =SUM('Pricing & Mix'!$C42:E42) -> 0 | F45: =SUM('Pricing & Mix'!$C42:F42) -> 0 | G45: =SUM('Pricing & Mix'!$C42:G42) -> 0 | H45: =SUM('Pricing & Mix'!$C42:H42) -> 0 | I45: =SUM('Pricing & Mix'!$C42:I42) -> 0 | J45: =SUM('Pricing & Mix'!$C42:J42) -> 0 | ... AE45: =SUM('Pricing & Mix'!$C42:AE42) -> 812950 | AG45: =D45 -> 0 | AH45: =P45 -> 3697.5 | AI45: =AB45 -> 42950 | AJ45: =AC45 -> 162950 | AK45: =AD45 -> 412950 | AL45: =AE45 -> 812950

Sheet Unit Economics
A1: Unit economics per SKU -- FY2028 basis (live). DTC = direct web/app sale; Retail = sell-in to retailer.
B3: Pebble DTC | C3: Square DTC | D3: Atlas DTC | E3: Pebble Retail | F3: Square Retail | G3: Atlas Retail | I3: Notes
A4: MSRP | B4: =msrp_peb*sc_price -> 149 | C4: =msrp_sq*sc_price -> 299 | D4: =msrp_atl*sc_price -> 599 | E4: =msrp_peb*sc_price -> 149 | F4: =msrp_sq*sc_price -> 299 | G4: =msrp_atl*sc_price -> 599
A5: Discount / retailer margin | B5: =-B4*dtc_disc -> -8.94 | C5: =-C4*dtc_disc -> -17.94 | D5: =-D4*dtc_disc -> -35.94 | E5: =-E4*retail_margin -> -56.62 | F5: =-F4*retail_margin -> -113.62 | G5: =-G4*retail_margin -> -227.62 | I5: DTC promo vs retailer margin.
A6: Returns allowance | B6: =-(B4+B5)*returns_pct -> -5.6024 | C6: =-(C4+C5)*returns_pct -> -11.2424 | D6: =-(D4+D5)*returns_pct -> -22.5224 | E6: =-(E4+E5)*returns_pct -> -3.6952 | F6: =-(F4+F5)*returns_pct -> -7.4152 | G6: =-(G4+G5)*returns_pct -> -14.8552
A7: Net revenue per unit | B7: =B4+B5+B6 -> 134.4576 | C7: =C4+C5+C6 -> 269.8176 | D7: =D4+D5+D6 -> 540.5376 | E7: =E4+E5+E6 -> 88.6848 | F7: =F4+F5+F6 -> 177.9648 | G7: =G4+G5+G6 -> 356.5248
A8: Landed COGS (BOM + assembly + pack + freight/duty) | B8: =-(bom_peb+asm_peb+pkg_peb)*(1+freight_duty)*sc_cogs -> -62.6503 | C8: =-(bom_sq+asm_sq+pkg_sq)*(1+freight_duty)*sc_cogs -> -227.1591 | D8: =-(bom_atl+asm_atl+pkg_atl)*(1+freight_duty)*sc_cogs -> -317.3925 | E8: =-(bom_peb+asm_peb+pkg_peb)*(1+freight_duty)*sc_cogs -> -62.6503 | F8: =-(bom_sq+asm_sq+pkg_sq)*(1+freight_duty)*sc_cogs -> -227.1591 | G8: =-(bom_atl+asm_atl+pkg_atl)*(1+freight_duty)*sc_cogs -> -317.3925 | I8: 2027-28 cost basis (index 1.00).
A9: Fulfilment / distribution | B9: =-dtc_ship -> -11 | C9: =-dtc_ship -> -11 | D9: =-dtc_ship -> -11 | E9: =-retail_dist -> -4 | F9: =-retail_dist -> -4 | G9: =-retail_dist -> -4
A10: Payment processing | B10: =-((B4+B5)*pay_pct+pay_fixed) -> -4.36174 | C10: =-((C4+C5)*pay_pct+pay_fixed) -> -8.45074 | D10: =-((D4+D5)*pay_pct+pay_fixed) -> -16.62874 | E10: =0 -> 0 | F10: =0 -> 0 | G10: =0 -> 0
A11: Warranty reserve | B11: =-(B4+B5)*warranty_pct -> -2.8012 | C11: =-(C4+C5)*warranty_pct -> -5.6212 | D11: =-(D4+D5)*warranty_pct -> -11.2612 | E11: =-(E4+E5)*warranty_pct -> -1.8476 | F11: =-(F4+F5)*warranty_pct -> -3.7076 | G11: =-(G4+G5)*warranty_pct -> -7.4276
A12: Hardware gross profit per unit | B12: =B7+B8+B9+B10+B11 -> 53.64436 | C12: =C7+C8+C9+C10+C11 -> 17.58656 | D12: =D7+D8+D9+D10+D11 -> 184.25516 | E12: =E7+E8+E9+E10+E11 -> 20.1869 | F12: =F7+F8+F9+F10+F11 -> -56.9019 | G12: =G7+G8+G9+G10+G11 -> 27.7047
A13: Hardware gross margin % | B13: =IF(B7>0,B12/B7,0) -> 0.3989686 | C13: =IF(C7>0,C12/C7,0) -> 0.06517944 | D13: =IF(D7>0,D12/D7,0) -> 0.3408739 | E13: =IF(E7>0,E12/E7,0) -> 0.22762525 | F13: =IF(F7>0,F12/F7,0) -> -0.31973682 | G13: =IF(G7>0,G12/G7,0) -> 0.077707638
A14: Acquisition cost (paid CAC DTC; co-op for retail) | B14: =-Assumptions!V113*sc_cac -> -60 | C14: =-Assumptions!V113*sc_cac -> -60 | D14: =-Assumptions!V113*sc_cac -> -60 | E14: =-(E4+E5)*retail_coop -> -5.5428 | F14: =-(F4+F5)*retail_coop -> -11.1228 | G14: =-(G4+G5)*retail_coop -> -22.2828 | I14: FY2028 CAC.
A15: Hardware contribution after acquisition | B15: =B12+B14 -> -6.35564 | C15: =C12+C14 -> -42.41344 | D15: =D12+D14 -> 124.25516 | E15: =E12+E14 -> 14.6441 | F15: =F12+F14 -> -68.0247 | G15: =G12+G14 -> 5.4219
A16: Accessories gross profit per device | B16: =acc_attach*acc_aov*sc_price*(1-acc_cogs_pct) -> 8.37 | C16: =acc_attach*acc_aov*sc_price*(1-acc_cogs_pct) -> 8.37 | D16: =acc_attach*acc_aov*sc_price*(1-acc_cogs_pct) -> 8.37 | E16: =acc_attach*acc_aov*sc_price*(1-acc_cogs_pct) -> 8.37 | F16: =acc_attach*acc_aov*sc_price*(1-acc_cogs_pct) -> 8.37 | G16: =acc_attach*acc_aov*sc_price*(1-acc_cogs_pct) -> 8.37
A17: Free 3-month trial cost (cloud) | B17: =-trial_months*'Cloud & AI COGS'!V10 -> -6.048 | C17: =-trial_months*'Cloud & AI COGS'!V10 -> -6.048 | D17: =-trial_months*'Cloud & AI COGS'!V10 -> -6.048 | E17: =-trial_months*'Cloud & AI COGS'!V10 -> -6.048 | F17: =-trial_months*'Cloud & AI COGS'!V10 -> -6.048 | G17: =-trial_months*'Cloud & AI COGS'!V10 -> -6.048 | I17: Every device gets 3 months of Explorer.
A18: Paid attach after trial | B18: =MIN(1,attach_peb*sc_attach) -> 0.28 | C18: =MIN(1,attach_sq*sc_attach) -> 0.4 | D18: =MIN(1,attach_atl*sc_attach) -> 0.55 | E18: =MIN(1,attach_peb*sc_attach) -> 0.28 | F18: =MIN(1,attach_sq*sc_attach) -> 0.4 | G18: =MIN(1,attach_atl*sc_attach) -> 0.55
A19: Subscription gross profit per paid month | B19: =sub_price*arpu_real*sc_price*(1-sub_pay_fee)-'Cloud & AI COGS'!V10 -> 5.888088 | C19: =sub_price*arpu_real*sc_price*(1-sub_pay_fee)-'Cloud & AI COGS'!V10 -> 5.888088 | D19: =sub_price*arpu_real*sc_price*(1-sub_pay_fee)-'Cloud & AI COGS'!V10 -> 5.888088 | E19: =sub_price*arpu_real*sc_price*(1-sub_pay_fee)-'Cloud & AI COGS'!V10 -> 5.888088 | F19: =sub_price*arpu_real*sc_price*(1-sub_pay_fee)-'Cloud & AI COGS'!V10 -> 5.888088 | G19: =sub_price*arpu_real*sc_price*(1-sub_pay_fee)-'Cloud & AI COGS'!V10 -> 5.888088
A20: Expected paid lifetime (months) = 1/churn | B20: =1/MIN(0.5,churn*sc_churn) -> 16.666667 | C20: =1/MIN(0.5,churn*sc_churn) -> 16.666667 | D20: =1/MIN(0.5,churn*sc_churn) -> 16.666667 | E20: =1/MIN(0.5,churn*sc_churn) -> 16.666667 | F20: =1/MIN(0.5,churn*sc_churn) -> 16.666667 | G20: =1/MIN(0.5,churn*sc_churn) -> 16.666667
A21: Subscription LTV (gross profit, undiscounted) | B21: =B18*B19*B20 -> 27.477744 | C21: =C18*C19*C20 -> 39.25392 | D21: =D18*D19*D20 -> 53.97414 | E21: =E18*E19*E20 -> 27.477744 | F21: =F18*F19*F20 -> 39.25392 | G21: =G18*G19*G20 -> 53.97414
A22: Affiliate gross profit over device life | B22: =Assumptions!V112/device_inactive -> 15 | C22: =Assumptions!V112/device_inactive -> 15 | D22: =Assumptions!V112/device_inactive -> 15 | E22: =Assumptions!V112/device_inactive -> 15 | F22: =Assumptions!V112/device_inactive -> 15 | G22: =Assumptions!V112/device_inactive -> 15 | I22: Rate x expected active life (1/inactivity).
A23: TOTAL LIFETIME CONTRIBUTION PER DEVICE | B23: =B15+B16+B17+B21+B22 -> 38.444104 | C23: =C15+C16+C17+C21+C22 -> 14.16248 | D23: =D15+D16+D17+D21+D22 -> 195.5513 | E23: =E15+E16+E17+E21+E22 -> 59.443844 | F23: =F15+F16+F17+F21+F22 -> -11.44878 | G23: =G15+G16+G17+G21+G22 -> 76.71804
A24: Lifetime contribution / acquisition cost (LTV:CAC) | B24: =IF(B14<0,(B23-B14)/-B14,0) -> 1.6407351 | C24: =IF(C14<0,(C23-C14)/-C14,0) -> 1.2360413 | D24: =IF(D14<0,(D23-D14)/-D14,0) -> 4.2591883 | E24: =IF(E14<0,(E23-E14)/-E14,0) -> 11.724515 | F24: =IF(F14<0,(F23-F14)/-F14,0) -> -0.029307369 | G24: =IF(G14<0,(G23-G14)/-G14,0) -> 4.4429264 | I24: Contribution before CAC divided by CAC.
A25: Payback on CAC (months after purchase) | B25: =IF(B12+B16>=-B14,0,(-B14-B12-B16)/MAX(0.01,B18*B19)) -> 0 | C25: =IF(C12+C16>=-C14,0,(-C14-C12-C16)/MAX(0.01,C18*C19)) -> 14.45437 | D25: =IF(D12+D16>=-D14,0,(-D14-D12-D16)/MAX(0.01,D18*D19)) -> 0 | E25: =IF(E12+E16>=-E14,0,(-E14-E12-E16)/MAX(0.01,E18*E19)) -> 0 | F25: =IF(F12+F16>=-F14,0,(-F14-F12-F16)/MAX(0.01,F18*F19)) -> 25.328553 | G25: =IF(G12+G16>=-G14,0,(-G14-G12-G16)/MAX(0.01,G18*G19)) -> 0 | I25: 0 = paid back at sale by hardware margin.
A29: Sensitivity: DTC hardware gross margin % by price (rows) and landed-COGS change (cols)
A30: Pebble: price \ COGS delta | B30: -0.15 | C30: -0.1 | D30: -0.05 | E30: 0 | F30: 0.05 | G30: 0.1 | H30: 0.2
A31: 119 | B31: =1-((bom_peb+asm_peb+pkg_peb)*(1+freight_duty)*(1+B$30)+dtc_ship+$A31*(1-dtc_disc)*(pay_pct+warranty_pct)+pay_fixed)/($A31*(1-dtc_disc)*(1-returns_pct)) -> 0.34782787 | C31: =1-((bom_peb+asm_peb+pkg_peb)*(1+freight_duty)*(1+C$30)+dtc_ship+$A31*(1-dtc_disc)*(pay_pct+warranty_pct)+pay_fixed)/($A31*(1-dtc_disc)*(1-returns_pct)) -> 0.31865716 | D31: =1-((bom_peb+asm_peb+pkg_peb)*(1+freight_duty)*(1+D$30)+dtc_ship+$A31*(1-dtc_disc)*(pay_pct+warranty_pct)+pay_fixed)/($A31*(1-dtc_disc)*(1-returns_pct)) -> 0.28948644 | E31: =1-((bom_peb+asm_peb+pkg_peb)*(1+freight_duty)*(1+E$30)+dtc_ship+$A31*(1-dtc_disc)*(pay_pct+warranty_pct)+pay_fixed)/($A31*(1-dtc_disc)*(1-returns_pct)) -> 0.26031572 | F31: =1-((bom_peb+asm_peb+pkg_peb)*(1+freight_duty)*(1+F$30)+dtc_ship+$A31*(1-dtc_disc)*(pay_pct+warranty_pct)+pay_fixed)/($A31*(1-dtc_disc)*(1-returns_pct)) -> 0.231145 | G31: =1-((bom_peb+asm_peb+pkg_peb)*(1+freight_duty)*(1+G$30)+dtc_ship+$A31*(1-dtc_disc)*(pay_pct+warranty_pct)+pay_fixed)/($A31*(1-dtc_disc)*(1-returns_pct)) -> 0.20197429 | H31: =1-((bom_peb+asm_peb+pkg_peb)*(1+freight_duty)*(1+H$30)+dtc_ship+$A31*(1-dtc_disc)*(pay_pct+warranty_pct)+pay_fixed)/($A31*(1-dtc_disc)*(1-returns_pct)) -> 0.14363285
A32: 129 | B32: =1-((bom_peb+asm_peb+pkg_peb)*(1+freight_duty)*(1+B$30)+dtc_ship+$A32*(1-dtc_disc)*(pay_pct+warranty_pct)+pay_fixed)/($A32*(1-dtc_disc)*(1-returns_pct)) -> 0.39442713 | C32: =1-((bom_peb+asm_peb+pkg_peb)*(1+freight_duty)*(1+C$30)+dtc_ship+$A32*(1-dtc_disc)*(pay_pct+warranty_pct)+pay_fixed)/($A32*(1-dtc_disc)*(1-returns_pct)) -> 0.36751771 | D32: =1-((bom_peb+asm_peb+pkg_peb)*(1+freight_duty)*(1+D$30)+dtc_ship+$A32*(1-dtc_disc)*(pay_pct+warranty_pct)+pay_fixed)/($A32*(1-dtc_disc)*(1-returns_pct)) -> 0.34060829 | E32: =1-((bom_peb+asm_peb+pkg_peb)*(1+freight_duty)*(1+E$30)+dtc_ship+$A32*(1-dtc_disc)*(pay_pct+warranty_pct)+pay_fixed)/($A32*(1-dtc_disc)*(1-returns_pct)) -> 0.31369887 | F32: =1-((bom_peb+asm_peb+pkg_peb)*(1+freight_duty)*(1+F$30)+dtc_ship+$A32*(1-dtc_disc)*(pay_pct+warranty_pct)+pay_fixed)/($A32*(1-dtc_disc)*(1-returns_pct)) -> 0.28678945 | G32: =1-((bom_peb+asm_peb+pkg_peb)*(1+freight_duty)*(1+G$30)+dtc_ship+$A32*(1-dtc_disc)*(pay_pct+warranty_pct)+pay_fixed)/($A32*(1-dtc_disc)*(1-returns_pct)) -> 0.25988003 | H32: =1-((bom_peb+asm_peb+pkg_peb)*(1+freight_duty)*(1+H$30)+dtc_ship+$A32*(1-dtc_disc)*(pay_pct+warranty_pct)+pay_fixed)/($A32*(1-dtc_disc)*(1-returns_pct)) -> 0.20606118
A33: 139 | B33: =1-((bom_peb+asm_peb+pkg_peb)*(1+freight_duty)*(1+B$30)+dtc_ship+$A33*(1-dtc_disc)*(pay_pct+warranty_pct)+pay_fixed)/($A33*(1-dtc_disc)*(1-returns_pct)) -> 0.43432147 | C33: =1-((bom_peb+asm_peb+pkg_peb)*(1+freight_duty)*(1+C$30)+dtc_ship+$A33*(1-dtc_disc)*(pay_pct+warranty_pct)+pay_fixed)/($A33*(1-dtc_disc)*(1-returns_pct)) -> 0.40934797 | D33: =1-((bom_peb+asm_peb+pkg_peb)*(1+freight_duty)*(1+D$30)+dtc_ship+$A33*(1-dtc_disc)*(pay_pct+warranty_pct)+pay_fixed)/($A33*(1-dtc_disc)*(1-returns_pct)) -> 0.38437448 | E33: =1-((bom_peb+asm_peb+pkg_peb)*(1+freight_duty)*(1+E$30)+dtc_ship+$A33*(1-dtc_disc)*(pay_pct+warranty_pct)+pay_fixed)/($A33*(1-dtc_disc)*(1-returns_pct)) -> 0.35940099 | F33: =1-((bom_peb+asm_peb+pkg_peb)*(1+freight_duty)*(1+F$30)+dtc_ship+$A33*(1-dtc_disc)*(pay_pct+warranty_pct)+pay_fixed)/($A33*(1-dtc_disc)*(1-returns_pct)) -> 0.3344275 | G33: =1-((bom_peb+asm_peb+pkg_peb)*(1+freight_duty)*(1+G$30)+dtc_ship+$A33*(1-dtc_disc)*(pay_pct+warranty_pct)+pay_fixed)/($A33*(1-dtc_disc)*(1-returns_pct)) -> 0.30945401 | H33: =1-((bom_peb+asm_peb+pkg_peb)*(1+freight_duty)*(1+H$30)+dtc_ship+$A33*(1-dtc_disc)*(pay_pct+warranty_pct)+pay_fixed)/($A33*(1-dtc_disc)*(1-returns_pct)) -> 0.25950702
A34: 149 | B34: =1-((bom_peb+asm_peb+pkg_peb)*(1+freight_duty)*(1+B$30)+dtc_ship+$A34*(1-dtc_disc)*(pay_pct+warranty_pct)+pay_fixed)/($A34*(1-dtc_disc)*(1-returns_pct)) -> 0.46886085 | C34: =1-((bom_peb+asm_peb+pkg_peb)*(1+freight_duty)*(1+C$30)+dtc_ship+$A34*(1-dtc_disc)*(pay_pct+warranty_pct)+pay_fixed)/($A34*(1-dtc_disc)*(1-returns_pct)) -> 0.44556343 | D34: =1-((bom_peb+asm_peb+pkg_peb)*(1+freight_duty)*(1+D$30)+dtc_ship+$A34*(1-dtc_disc)*(pay_pct+warranty_pct)+pay_fixed)/($A34*(1-dtc_disc)*(1-returns_pct)) -> 0.42226602 | E34: =1-((bom_peb+asm_peb+pkg_peb)*(1+freight_duty)*(1+E$30)+dtc_ship+$A34*(1-dtc_disc)*(pay_pct+warranty_pct)+pay_fixed)/($A34*(1-dtc_disc)*(1-returns_pct)) -> 0.3989686 | F34: =1-((bom_peb+asm_peb+pkg_peb)*(1+freight_duty)*(1+F$30)+dtc_ship+$A34*(1-dtc_disc)*(pay_pct+warranty_pct)+pay_fixed)/($A34*(1-dtc_disc)*(1-returns_pct)) -> 0.37567118 | G34: =1-((bom_peb+asm_peb+pkg_peb)*(1+freight_duty)*(1+G$30)+dtc_ship+$A34*(1-dtc_disc)*(pay_pct+warranty_pct)+pay_fixed)/($A34*(1-dtc_disc)*(1-returns_pct)) -> 0.35237376 | H34: =1-((bom_peb+asm_peb+pkg_peb)*(1+freight_duty)*(1+H$30)+dtc_ship+$A34*(1-dtc_disc)*(pay_pct+warranty_pct)+pay_fixed)/($A34*(1-dtc_disc)*(1-returns_pct)) -> 0.30577892
A35: 169 | B35: =1-((bom_peb+asm_peb+pkg_peb)*(1+freight_duty)*(1+B$30)+dtc_ship+$A35*(1-dtc_disc)*(pay_pct+warranty_pct)+pay_fixed)/($A35*(1-dtc_disc)*(1-returns_pct)) -> 0.52567712 | C35: =1-((bom_peb+asm_peb+pkg_peb)*(1+freight_duty)*(1+C$30)+dtc_ship+$A35*(1-dtc_disc)*(pay_pct+warranty_pct)+pay_fixed)/($A35*(1-dtc_disc)*(1-returns_pct)) -> 0.50513679 | D35: =1-((bom_peb+asm_peb+pkg_peb)*(1+freight_duty)*(1+D$30)+dtc_ship+$A35*(1-dtc_disc)*(pay_pct+warranty_pct)+pay_fixed)/($A35*(1-dtc_disc)*(1-returns_pct)) -> 0.48459647 | E35: =1-((bom_peb+asm_peb+pkg_peb)*(1+freight_duty)*(1+E$30)+dtc_ship+$A35*(1-dtc_disc)*(pay_pct+warranty_pct)+pay_fixed)/($A35*(1-dtc_disc)*(1-returns_pct)) -> 0.46405614 | F35: =1-((bom_peb+asm_peb+pkg_peb)*(1+freight_duty)*(1+F$30)+dtc_ship+$A35*(1-dtc_disc)*(pay_pct+warranty_pct)+pay_fixed)/($A35*(1-dtc_disc)*(1-returns_pct)) -> 0.44351581 | G35: =1-((bom_peb+asm_peb+pkg_peb)*(1+freight_duty)*(1+G$30)+dtc_ship+$A35*(1-dtc_disc)*(pay_pct+warranty_pct)+pay_fixed)/($A35*(1-dtc_disc)*(1-returns_pct)) -> 0.42297548 | H35: =1-((bom_peb+asm_peb+pkg_peb)*(1+freight_duty)*(1+H$30)+dtc_ship+$A35*(1-dtc_disc)*(pay_pct+warranty_pct)+pay_fixed)/($A35*(1-dtc_disc)*(1-returns_pct)) -> 0.38189483
A36: 179 | B36: =1-((bom_peb+asm_peb+pkg_peb)*(1+freight_duty)*(1+B$30)+dtc_ship+$A36*(1-dtc_disc)*(pay_pct+warranty_pct)+pay_fixed)/($A36*(1-dtc_disc)*(1-returns_pct)) -> 0.54932412 | C36: =1-((bom_peb+asm_peb+pkg_peb)*(1+freight_duty)*(1+C$30)+dtc_ship+$A36*(1-dtc_disc)*(pay_pct+warranty_pct)+pay_fixed)/($A36*(1-dtc_disc)*(1-returns_pct)) -> 0.52993129 | D36: =1-((bom_peb+asm_peb+pkg_peb)*(1+freight_duty)*(1+D$30)+dtc_ship+$A36*(1-dtc_disc)*(pay_pct+warranty_pct)+pay_fixed)/($A36*(1-dtc_disc)*(1-returns_pct)) -> 0.51053847 | E36: =1-((bom_peb+asm_peb+pkg_peb)*(1+freight_duty)*(1+E$30)+dtc_ship+$A36*(1-dtc_disc)*(pay_pct+warranty_pct)+pay_fixed)/($A36*(1-dtc_disc)*(1-returns_pct)) -> 0.49114565 | F36: =1-((bom_peb+asm_peb+pkg_peb)*(1+freight_duty)*(1+F$30)+dtc_ship+$A36*(1-dtc_disc)*(pay_pct+warranty_pct)+pay_fixed)/($A36*(1-dtc_disc)*(1-returns_pct)) -> 0.47175282 | G36: =1-((bom_peb+asm_peb+pkg_peb)*(1+freight_duty)*(1+G$30)+dtc_ship+$A36*(1-dtc_disc)*(pay_pct+warranty_pct)+pay_fixed)/($A36*(1-dtc_disc)*(1-returns_pct)) -> 0.45236 | H36: =1-((bom_peb+asm_peb+pkg_peb)*(1+freight_duty)*(1+H$30)+dtc_ship+$A36*(1-dtc_disc)*(pay_pct+warranty_pct)+pay_fixed)/($A36*(1-dtc_disc)*(1-returns_pct)) -> 0.41357435
A38: Square: price \ COGS delta | B38: -0.15 | C38: -0.1 | D38: -0.05 | E38: 0 | F38: 0.05 | G38: 0.1 | H38: 0.2
A39: 249 | B39: =1-((bom_sq+asm_sq+pkg_sq)*(1+freight_duty)*(1+B$38)+dtc_ship+$A39*(1-dtc_disc)*(pay_pct+warranty_pct)+pay_fixed)/($A39*(1-dtc_disc)*(1-returns_pct)) -> 0.039357007 | C39: =1-((bom_sq+asm_sq+pkg_sq)*(1+freight_duty)*(1+C$38)+dtc_ship+$A39*(1-dtc_disc)*(pay_pct+warranty_pct)+pay_fixed)/($A39*(1-dtc_disc)*(1-returns_pct)) -> -0.011190729 | D39: =1-((bom_sq+asm_sq+pkg_sq)*(1+freight_duty)*(1+D$38)+dtc_ship+$A39*(1-dtc_disc)*(pay_pct+warranty_pct)+pay_fixed)/($A39*(1-dtc_disc)*(1-returns_pct)) -> -0.061738465 | E39: =1-((bom_sq+asm_sq+pkg_sq)*(1+freight_duty)*(1+E$38)+dtc_ship+$A39*(1-dtc_disc)*(pay_pct+warranty_pct)+pay_fixed)/($A39*(1-dtc_disc)*(1-returns_pct)) -> -0.1122862 | F39: =1-((bom_sq+asm_sq+pkg_sq)*(1+freight_duty)*(1+F$38)+dtc_ship+$A39*(1-dtc_disc)*(pay_pct+warranty_pct)+pay_fixed)/($A39*(1-dtc_disc)*(1-returns_pct)) -> -0.16283394 | G39: =1-((bom_sq+asm_sq+pkg_sq)*(1+freight_duty)*(1+G$38)+dtc_ship+$A39*(1-dtc_disc)*(pay_pct+warranty_pct)+pay_fixed)/($A39*(1-dtc_disc)*(1-returns_pct)) -> -0.21338167 | H39: =1-((bom_sq+asm_sq+pkg_sq)*(1+freight_duty)*(1+H$38)+dtc_ship+$A39*(1-dtc_disc)*(pay_pct+warranty_pct)+pay_fixed)/($A39*(1-dtc_disc)*(1-returns_pct)) -> -0.31447715
A40: 269 | B40: =1-((bom_sq+asm_sq+pkg_sq)*(1+freight_duty)*(1+B$38)+dtc_ship+$A40*(1-dtc_disc)*(pay_pct+warranty_pct)+pay_fixed)/($A40*(1-dtc_disc)*(1-returns_pct)) -> 0.10698536 | C40: =1-((bom_sq+asm_sq+pkg_sq)*(1+freight_duty)*(1+C$38)+dtc_ship+$A40*(1-dtc_disc)*(pay_pct+warranty_pct)+pay_fixed)/($A40*(1-dtc_disc)*(1-returns_pct)) -> 0.060195818 | D40: =1-((bom_sq+asm_sq+pkg_sq)*(1+freight_duty)*(1+D$38)+dtc_ship+$A40*(1-dtc_disc)*(pay_pct+warranty_pct)+pay_fixed)/($A40*(1-dtc_disc)*(1-returns_pct)) -> 0.013406278 | E40: =1-((bom_sq+asm_sq+pkg_sq)*(1+freight_duty)*(1+E$38)+dtc_ship+$A40*(1-dtc_disc)*(pay_pct+warranty_pct)+pay_fixed)/($A40*(1-dtc_disc)*(1-returns_pct)) -> -0.033383262 | F40: =1-((bom_sq+asm_sq+pkg_sq)*(1+freight_duty)*(1+F$38)+dtc_ship+$A40*(1-dtc_disc)*(pay_pct+warranty_pct)+pay_fixed)/($A40*(1-dtc_disc)*(1-returns_pct)) -> -0.080172802 | G40: =1-((bom_sq+asm_sq+pkg_sq)*(1+freight_duty)*(1+G$38)+dtc_ship+$A40*(1-dtc_disc)*(pay_pct+warranty_pct)+pay_fixed)/($A40*(1-dtc_disc)*(1-returns_pct)) -> -0.12696234 | H40: =1-((bom_sq+asm_sq+pkg_sq)*(1+freight_duty)*(1+H$38)+dtc_ship+$A40*(1-dtc_disc)*(pay_pct+warranty_pct)+pay_fixed)/($A40*(1-dtc_disc)*(1-returns_pct)) -> -0.22054142
A41: 279 | B41: =1-((bom_sq+asm_sq+pkg_sq)*(1+freight_duty)*(1+B$38)+dtc_ship+$A41*(1-dtc_disc)*(pay_pct+warranty_pct)+pay_fixed)/($A41*(1-dtc_disc)*(1-returns_pct)) -> 0.1371636 | C41: =1-((bom_sq+asm_sq+pkg_sq)*(1+freight_duty)*(1+C$38)+dtc_ship+$A41*(1-dtc_disc)*(pay_pct+warranty_pct)+pay_fixed)/($A41*(1-dtc_disc)*(1-returns_pct)) -> 0.092051105 | D41: =1-((bom_sq+asm_sq+pkg_sq)*(1+freight_duty)*(1+D$38)+dtc_ship+$A41*(1-dtc_disc)*(pay_pct+warranty_pct)+pay_fixed)/($A41*(1-dtc_disc)*(1-returns_pct)) -> 0.04693861 | E41: =1-((bom_sq+asm_sq+pkg_sq)*(1+freight_duty)*(1+E$38)+dtc_ship+$A41*(1-dtc_disc)*(pay_pct+warranty_pct)+pay_fixed)/($A41*(1-dtc_disc)*(1-returns_pct)) -> 0.001826114 | F41: =1-((bom_sq+asm_sq+pkg_sq)*(1+freight_duty)*(1+F$38)+dtc_ship+$A41*(1-dtc_disc)*(pay_pct+warranty_pct)+pay_fixed)/($A41*(1-dtc_disc)*(1-returns_pct)) -> -0.043286382 | G41: =1-((bom_sq+asm_sq+pkg_sq)*(1+freight_duty)*(1+G$38)+dtc_ship+$A41*(1-dtc_disc)*(pay_pct+warranty_pct)+pay_fixed)/($A41*(1-dtc_disc)*(1-returns_pct)) -> -0.088398877 | H41: =1-((bom_sq+asm_sq+pkg_sq)*(1+freight_duty)*(1+H$38)+dtc_ship+$A41*(1-dtc_disc)*(pay_pct+warranty_pct)+pay_fixed)/($A41*(1-dtc_disc)*(1-returns_pct)) -> -0.17862387
A42: 299 | B42: =1-((bom_sq+asm_sq+pkg_sq)*(1+freight_duty)*(1+B$38)+dtc_ship+$A42*(1-dtc_disc)*(pay_pct+warranty_pct)+pay_fixed)/($A42*(1-dtc_disc)*(1-returns_pct)) -> 0.19146425 | C42: =1-((bom_sq+asm_sq+pkg_sq)*(1+freight_duty)*(1+C$38)+dtc_ship+$A42*(1-dtc_disc)*(pay_pct+warranty_pct)+pay_fixed)/($A42*(1-dtc_disc)*(1-returns_pct)) -> 0.14936931 | D42: =1-((bom_sq+asm_sq+pkg_sq)*(1+freight_duty)*(1+D$38)+dtc_ship+$A42*(1-dtc_disc)*(pay_pct+warranty_pct)+pay_fixed)/($A42*(1-dtc_disc)*(1-returns_pct)) -> 0.10727438 | E42: =1-((bom_sq+asm_sq+pkg_sq)*(1+freight_duty)*(1+E$38)+dtc_ship+$A42*(1-dtc_disc)*(pay_pct+warranty_pct)+pay_fixed)/($A42*(1-dtc_disc)*(1-returns_pct)) -> 0.06517944 | F42: =1-((bom_sq+asm_sq+pkg_sq)*(1+freight_duty)*(1+F$38)+dtc_ship+$A42*(1-dtc_disc)*(pay_pct+warranty_pct)+pay_fixed)/($A42*(1-dtc_disc)*(1-returns_pct)) -> 0.023084502 | G42: =1-((bom_sq+asm_sq+pkg_sq)*(1+freight_duty)*(1+G$38)+dtc_ship+$A42*(1-dtc_disc)*(pay_pct+warranty_pct)+pay_fixed)/($A42*(1-dtc_disc)*(1-returns_pct)) -> -0.019010435 | H42: =1-((bom_sq+asm_sq+pkg_sq)*(1+freight_duty)*(1+H$38)+dtc_ship+$A42*(1-dtc_disc)*(pay_pct+warranty_pct)+pay_fixed)/($A42*(1-dtc_disc)*(1-returns_pct)) -> -0.10320031
A43: 329 | B43: =1-((bom_sq+asm_sq+pkg_sq)*(1+freight_duty)*(1+B$38)+dtc_ship+$A43*(1-dtc_disc)*(pay_pct+warranty_pct)+pay_fixed)/($A43*(1-dtc_disc)*(1-returns_pct)) -> 0.26053666 | C43: =1-((bom_sq+asm_sq+pkg_sq)*(1+freight_duty)*(1+C$38)+dtc_ship+$A43*(1-dtc_disc)*(pay_pct+warranty_pct)+pay_fixed)/($A43*(1-dtc_disc)*(1-returns_pct)) -> 0.22228017 | D43: =1-((bom_sq+asm_sq+pkg_sq)*(1+freight_duty)*(1+D$38)+dtc_ship+$A43*(1-dtc_disc)*(pay_pct+warranty_pct)+pay_fixed)/($A43*(1-dtc_disc)*(1-returns_pct)) -> 0.18402367 | E43: =1-((bom_sq+asm_sq+pkg_sq)*(1+freight_duty)*(1+E$38)+dtc_ship+$A43*(1-dtc_disc)*(pay_pct+warranty_pct)+pay_fixed)/($A43*(1-dtc_disc)*(1-returns_pct)) -> 0.14576718 | F43: =1-((bom_sq+asm_sq+pkg_sq)*(1+freight_duty)*(1+F$38)+dtc_ship+$A43*(1-dtc_disc)*(pay_pct+warranty_pct)+pay_fixed)/($A43*(1-dtc_disc)*(1-returns_pct)) -> 0.10751069 | G43: =1-((bom_sq+asm_sq+pkg_sq)*(1+freight_duty)*(1+G$38)+dtc_ship+$A43*(1-dtc_disc)*(pay_pct+warranty_pct)+pay_fixed)/($A43*(1-dtc_disc)*(1-returns_pct)) -> 0.069254194 | H43: =1-((bom_sq+asm_sq+pkg_sq)*(1+freight_duty)*(1+H$38)+dtc_ship+$A43*(1-dtc_disc)*(pay_pct+warranty_pct)+pay_fixed)/($A43*(1-dtc_disc)*(1-returns_pct)) -> -0.0072587925
A44: 349 | B44: =1-((bom_sq+asm_sq+pkg_sq)*(1+freight_duty)*(1+B$38)+dtc_ship+$A44*(1-dtc_disc)*(pay_pct+warranty_pct)+pay_fixed)/($A44*(1-dtc_disc)*(1-returns_pct)) -> 0.29998776 | C44: =1-((bom_sq+asm_sq+pkg_sq)*(1+freight_duty)*(1+C$38)+dtc_ship+$A44*(1-dtc_disc)*(pay_pct+warranty_pct)+pay_fixed)/($A44*(1-dtc_disc)*(1-returns_pct)) -> 0.26392362 | D44: =1-((bom_sq+asm_sq+pkg_sq)*(1+freight_duty)*(1+D$38)+dtc_ship+$A44*(1-dtc_disc)*(pay_pct+warranty_pct)+pay_fixed)/($A44*(1-dtc_disc)*(1-returns_pct)) -> 0.22785947 | E44: =1-((bom_sq+asm_sq+pkg_sq)*(1+freight_duty)*(1+E$38)+dtc_ship+$A44*(1-dtc_disc)*(pay_pct+warranty_pct)+pay_fixed)/($A44*(1-dtc_disc)*(1-returns_pct)) -> 0.19179533 | F44: =1-((bom_sq+asm_sq+pkg_sq)*(1+freight_duty)*(1+F$38)+dtc_ship+$A44*(1-dtc_disc)*(pay_pct+warranty_pct)+pay_fixed)/($A44*(1-dtc_disc)*(1-returns_pct)) -> 0.15573118 | G44: =1-((bom_sq+asm_sq+pkg_sq)*(1+freight_duty)*(1+G$38)+dtc_ship+$A44*(1-dtc_disc)*(pay_pct+warranty_pct)+pay_fixed)/($A44*(1-dtc_disc)*(1-returns_pct)) -> 0.11966704 | H44: =1-((bom_sq+asm_sq+pkg_sq)*(1+freight_duty)*(1+H$38)+dtc_ship+$A44*(1-dtc_disc)*(pay_pct+warranty_pct)+pay_fixed)/($A44*(1-dtc_disc)*(1-returns_pct)) -> 0.047538751
A46: Atlas: price \ COGS delta | B46: -0.15 | C46: -0.1 | D46: -0.05 | E46: 0 | F46: 0.05 | G46: 0.1 | H46: 0.2
A47: 449 | B47: =1-((bom_atl+asm_atl+pkg_atl)*(1+freight_duty)*(1+B$46)+dtc_ship+$A47*(1-dtc_disc)*(pay_pct+warranty_pct)+pay_fixed)/($A47*(1-dtc_disc)*(1-returns_pct)) -> 0.2552289 | C47: =1-((bom_atl+asm_atl+pkg_atl)*(1+freight_duty)*(1+C$46)+dtc_ship+$A47*(1-dtc_disc)*(pay_pct+warranty_pct)+pay_fixed)/($A47*(1-dtc_disc)*(1-returns_pct)) -> 0.21606182 | D47: =1-((bom_atl+asm_atl+pkg_atl)*(1+freight_duty)*(1+D$46)+dtc_ship+$A47*(1-dtc_disc)*(pay_pct+warranty_pct)+pay_fixed)/($A47*(1-dtc_disc)*(1-returns_pct)) -> 0.17689474 | E47: =1-((bom_atl+asm_atl+pkg_atl)*(1+freight_duty)*(1+E$46)+dtc_ship+$A47*(1-dtc_disc)*(pay_pct+warranty_pct)+pay_fixed)/($A47*(1-dtc_disc)*(1-returns_pct)) -> 0.13772765 | F47: =1-((bom_atl+asm_atl+pkg_atl)*(1+freight_duty)*(1+F$46)+dtc_ship+$A47*(1-dtc_disc)*(pay_pct+warranty_pct)+pay_fixed)/($A47*(1-dtc_disc)*(1-returns_pct)) -> 0.098560569 | G47: =1-((bom_atl+asm_atl+pkg_atl)*(1+freight_duty)*(1+G$46)+dtc_ship+$A47*(1-dtc_disc)*(pay_pct+warranty_pct)+pay_fixed)/($A47*(1-dtc_disc)*(1-returns_pct)) -> 0.059393486 | H47: =1-((bom_atl+asm_atl+pkg_atl)*(1+freight_duty)*(1+H$46)+dtc_ship+$A47*(1-dtc_disc)*(pay_pct+warranty_pct)+pay_fixed)/($A47*(1-dtc_disc)*(1-returns_pct)) -> -0.018940682
A48: 499 | B48: =1-((bom_atl+asm_atl+pkg_atl)*(1+freight_duty)*(1+B$46)+dtc_ship+$A48*(1-dtc_disc)*(pay_pct+warranty_pct)+pay_fixed)/($A48*(1-dtc_disc)*(1-returns_pct)) -> 0.32474087 | C48: =1-((bom_atl+asm_atl+pkg_atl)*(1+freight_duty)*(1+C$46)+dtc_ship+$A48*(1-dtc_disc)*(pay_pct+warranty_pct)+pay_fixed)/($A48*(1-dtc_disc)*(1-returns_pct)) -> 0.28949835 | D48: =1-((bom_atl+asm_atl+pkg_atl)*(1+freight_duty)*(1+D$46)+dtc_ship+$A48*(1-dtc_disc)*(pay_pct+warranty_pct)+pay_fixed)/($A48*(1-dtc_disc)*(1-returns_pct)) -> 0.25425582 | E48: =1-((bom_atl+asm_atl+pkg_atl)*(1+freight_duty)*(1+E$46)+dtc_ship+$A48*(1-dtc_disc)*(pay_pct+warranty_pct)+pay_fixed)/($A48*(1-dtc_disc)*(1-returns_pct)) -> 0.21901329 | F48: =1-((bom_atl+asm_atl+pkg_atl)*(1+freight_duty)*(1+F$46)+dtc_ship+$A48*(1-dtc_disc)*(pay_pct+warranty_pct)+pay_fixed)/($A48*(1-dtc_disc)*(1-returns_pct)) -> 0.18377077 | G48: =1-((bom_atl+asm_atl+pkg_atl)*(1+freight_duty)*(1+G$46)+dtc_ship+$A48*(1-dtc_disc)*(pay_pct+warranty_pct)+pay_fixed)/($A48*(1-dtc_disc)*(1-returns_pct)) -> 0.14852824 | H48: =1-((bom_atl+asm_atl+pkg_atl)*(1+freight_duty)*(1+H$46)+dtc_ship+$A48*(1-dtc_disc)*(pay_pct+warranty_pct)+pay_fixed)/($A48*(1-dtc_disc)*(1-returns_pct)) -> 0.078043187
A49: 529 | B49: =1-((bom_atl+asm_atl+pkg_atl)*(1+freight_duty)*(1+B$46)+dtc_ship+$A49*(1-dtc_disc)*(pay_pct+warranty_pct)+pay_fixed)/($A49*(1-dtc_disc)*(1-returns_pct)) -> 0.36014073 | C49: =1-((bom_atl+asm_atl+pkg_atl)*(1+freight_duty)*(1+C$46)+dtc_ship+$A49*(1-dtc_disc)*(pay_pct+warranty_pct)+pay_fixed)/($A49*(1-dtc_disc)*(1-returns_pct)) -> 0.32689683 | D49: =1-((bom_atl+asm_atl+pkg_atl)*(1+freight_duty)*(1+D$46)+dtc_ship+$A49*(1-dtc_disc)*(pay_pct+warranty_pct)+pay_fixed)/($A49*(1-dtc_disc)*(1-returns_pct)) -> 0.29365294 | E49: =1-((bom_atl+asm_atl+pkg_atl)*(1+freight_duty)*(1+E$46)+dtc_ship+$A49*(1-dtc_disc)*(pay_pct+warranty_pct)+pay_fixed)/($A49*(1-dtc_disc)*(1-returns_pct)) -> 0.26040904 | F49: =1-((bom_atl+asm_atl+pkg_atl)*(1+freight_duty)*(1+F$46)+dtc_ship+$A49*(1-dtc_disc)*(pay_pct+warranty_pct)+pay_fixed)/($A49*(1-dtc_disc)*(1-returns_pct)) -> 0.22716515 | G49: =1-((bom_atl+asm_atl+pkg_atl)*(1+freight_duty)*(1+G$46)+dtc_ship+$A49*(1-dtc_disc)*(pay_pct+warranty_pct)+pay_fixed)/($A49*(1-dtc_disc)*(1-returns_pct)) -> 0.19392125 | H49: =1-((bom_atl+asm_atl+pkg_atl)*(1+freight_duty)*(1+H$46)+dtc_ship+$A49*(1-dtc_disc)*(pay_pct+warranty_pct)+pay_fixed)/($A49*(1-dtc_disc)*(1-returns_pct)) -> 0.12743346
A50: 549 | B50: =1-((bom_atl+asm_atl+pkg_atl)*(1+freight_duty)*(1+B$46)+dtc_ship+$A50*(1-dtc_disc)*(pay_pct+warranty_pct)+pay_fixed)/($A50*(1-dtc_disc)*(1-returns_pct)) -> 0.38159128 | C50: =1-((bom_atl+asm_atl+pkg_atl)*(1+freight_duty)*(1+C$46)+dtc_ship+$A50*(1-dtc_disc)*(pay_pct+warranty_pct)+pay_fixed)/($A50*(1-dtc_disc)*(1-returns_pct)) -> 0.34955845 | D50: =1-((bom_atl+asm_atl+pkg_atl)*(1+freight_duty)*(1+D$46)+dtc_ship+$A50*(1-dtc_disc)*(pay_pct+warranty_pct)+pay_fixed)/($A50*(1-dtc_disc)*(1-returns_pct)) -> 0.31752563 | E50: =1-((bom_atl+asm_atl+pkg_atl)*(1+freight_duty)*(1+E$46)+dtc_ship+$A50*(1-dtc_disc)*(pay_pct+warranty_pct)+pay_fixed)/($A50*(1-dtc_disc)*(1-returns_pct)) -> 0.2854928 | F50: =1-((bom_atl+asm_atl+pkg_atl)*(1+freight_duty)*(1+F$46)+dtc_ship+$A50*(1-dtc_disc)*(pay_pct+warranty_pct)+pay_fixed)/($A50*(1-dtc_disc)*(1-returns_pct)) -> 0.25345998 | G50: =1-((bom_atl+asm_atl+pkg_atl)*(1+freight_duty)*(1+G$46)+dtc_ship+$A50*(1-dtc_disc)*(pay_pct+warranty_pct)+pay_fixed)/($A50*(1-dtc_disc)*(1-returns_pct)) -> 0.22142716 | H50: =1-((bom_atl+asm_atl+pkg_atl)*(1+freight_duty)*(1+H$46)+dtc_ship+$A50*(1-dtc_disc)*(pay_pct+warranty_pct)+pay_fixed)/($A50*(1-dtc_disc)*(1-returns_pct)) -> 0.15736151
A51: 599 | B51: =1-((bom_atl+asm_atl+pkg_atl)*(1+freight_duty)*(1+B$46)+dtc_ship+$A51*(1-dtc_disc)*(pay_pct+warranty_pct)+pay_fixed)/($A51*(1-dtc_disc)*(1-returns_pct)) -> 0.4289508 | C51: =1-((bom_atl+asm_atl+pkg_atl)*(1+freight_duty)*(1+C$46)+dtc_ship+$A51*(1-dtc_disc)*(pay_pct+warranty_pct)+pay_fixed)/($A51*(1-dtc_disc)*(1-returns_pct)) -> 0.39959183 | D51: =1-((bom_atl+asm_atl+pkg_atl)*(1+freight_duty)*(1+D$46)+dtc_ship+$A51*(1-dtc_disc)*(pay_pct+warranty_pct)+pay_fixed)/($A51*(1-dtc_disc)*(1-returns_pct)) -> 0.37023287 | E51: =1-((bom_atl+asm_atl+pkg_atl)*(1+freight_duty)*(1+E$46)+dtc_ship+$A51*(1-dtc_disc)*(pay_pct+warranty_pct)+pay_fixed)/($A51*(1-dtc_disc)*(1-returns_pct)) -> 0.3408739 | F51: =1-((bom_atl+asm_atl+pkg_atl)*(1+freight_duty)*(1+F$46)+dtc_ship+$A51*(1-dtc_disc)*(pay_pct+warranty_pct)+pay_fixed)/($A51*(1-dtc_disc)*(1-returns_pct)) -> 0.31151493 | G51: =1-((bom_atl+asm_atl+pkg_atl)*(1+freight_duty)*(1+G$46)+dtc_ship+$A51*(1-dtc_disc)*(pay_pct+warranty_pct)+pay_fixed)/($A51*(1-dtc_disc)*(1-returns_pct)) -> 0.28215597 | H51: =1-((bom_atl+asm_atl+pkg_atl)*(1+freight_duty)*(1+H$46)+dtc_ship+$A51*(1-dtc_disc)*(pay_pct+warranty_pct)+pay_fixed)/($A51*(1-dtc_disc)*(1-returns_pct)) -> 0.22343804
A52: 649 | B52: =1-((bom_atl+asm_atl+pkg_atl)*(1+freight_duty)*(1+B$46)+dtc_ship+$A52*(1-dtc_disc)*(pay_pct+warranty_pct)+pay_fixed)/($A52*(1-dtc_disc)*(1-returns_pct)) -> 0.46901301 | C52: =1-((bom_atl+asm_atl+pkg_atl)*(1+freight_duty)*(1+C$46)+dtc_ship+$A52*(1-dtc_disc)*(pay_pct+warranty_pct)+pay_fixed)/($A52*(1-dtc_disc)*(1-returns_pct)) -> 0.44191591 | D52: =1-((bom_atl+asm_atl+pkg_atl)*(1+freight_duty)*(1+D$46)+dtc_ship+$A52*(1-dtc_disc)*(pay_pct+warranty_pct)+pay_fixed)/($A52*(1-dtc_disc)*(1-returns_pct)) -> 0.4148188 | E52: =1-((bom_atl+asm_atl+pkg_atl)*(1+freight_duty)*(1+E$46)+dtc_ship+$A52*(1-dtc_disc)*(pay_pct+warranty_pct)+pay_fixed)/($A52*(1-dtc_disc)*(1-returns_pct)) -> 0.3877217 | F52: =1-((bom_atl+asm_atl+pkg_atl)*(1+freight_duty)*(1+F$46)+dtc_ship+$A52*(1-dtc_disc)*(pay_pct+warranty_pct)+pay_fixed)/($A52*(1-dtc_disc)*(1-returns_pct)) -> 0.3606246 | G52: =1-((bom_atl+asm_atl+pkg_atl)*(1+freight_duty)*(1+G$46)+dtc_ship+$A52*(1-dtc_disc)*(pay_pct+warranty_pct)+pay_fixed)/($A52*(1-dtc_disc)*(1-returns_pct)) -> 0.33352749 | H52: =1-((bom_atl+asm_atl+pkg_atl)*(1+freight_duty)*(1+H$46)+dtc_ship+$A52*(1-dtc_disc)*(pay_pct+warranty_pct)+pay_fixed)/($A52*(1-dtc_disc)*(1-returns_pct)) -> 0.27933328

Sheet Subscription Cohorts
A1: LORE Pass subscription model -- trial -> paid conversion, churn, ARPU, installed base
A2: Period | C2: =Timeline!C2 -> Nov-26 | D2: =Timeline!D2 -> Dec-26 | E2: =Timeline!E2 -> Jan-27 | F2: =Timeline!F2 -> Feb-27 | G2: =Timeline!G2 -> Mar-27 | H2: =Timeline!H2 -> Apr-27 | I2: =Timeline!I2 -> May-27 | J2: =Timeline!J2 -> Jun-27 | ... AE2: =Timeline!AE2 -> FY2031 | AG2: FY2026 (Nov-Dec) | AH2: FY2027 | AI2: FY2028 | AJ2: FY2029 | AK2: FY2030 | AL2: FY2031
A3: Year | C3: =Timeline!C3 -> 2026 | D3: =Timeline!D3 -> 2026 | E3: =Timeline!E3 -> 2027 | F3: =Timeline!F3 -> 2027 | G3: =Timeline!G3 -> 2027 | H3: =Timeline!H3 -> 2027 | I3: =Timeline!I3 -> 2027 | J3: =Timeline!J3 -> 2027 | ... AE3: =Timeline!AE3 -> 2031 | AG3: 2026 | AH3: 2027 | AI3: 2028 | AJ3: 2029 | AK3: 2030 | AL3: 2031
A4: Months in period | C4: =Timeline!C4 -> 1 | D4: =Timeline!D4 -> 1 | E4: =Timeline!E4 -> 1 | F4: =Timeline!F4 -> 1 | G4: =Timeline!G4 -> 1 | H4: =Timeline!H4 -> 1 | I4: =Timeline!I4 -> 1 | J4: =Timeline!J4 -> 1 | ... AE4: =Timeline!AE4 -> 12
A5: Period start | C5: =Timeline!C5 -> 46327 | D5: =Timeline!D5 -> 46357 | E5: =Timeline!E5 -> 46388 | F5: =Timeline!F5 -> 46419 | G5: =Timeline!G5 -> 46447 | H5: =Timeline!H5 -> 46478 | I5: =Timeline!I5 -> 46508 | J5: =Timeline!J5 -> 46539 | ... AE5: =Timeline!AE5 -> 47849
A6: Period key | C6: =Timeline!C6 -> 202611 | D6: =Timeline!D6 -> 202612 | E6: =Timeline!E6 -> 202701 | F6: =Timeline!F6 -> 202702 | G6: =Timeline!G6 -> 202703 | H6: =Timeline!H6 -> 202704 | I6: =Timeline!I6 -> 202705 | J6: =Timeline!J6 -> 202706 | ... AE6: =Timeline!AE6 -> 2031
A9: Conversion pipeline
A10: Devices shipped (each gets a 3-month Explorer trial) | B10: units | C10: ='Pricing & Mix'!C42 -> 0 | D10: ='Pricing & Mix'!D42 -> 0 | E10: ='Pricing & Mix'!E42 -> 0 | F10: ='Pricing & Mix'!F42 -> 0 | G10: ='Pricing & Mix'!G42 -> 0 | H10: ='Pricing & Mix'!H42 -> 0 | I10: ='Pricing & Mix'!I42 -> 0 | J10: ='Pricing & Mix'!J42 -> 0 | ... AE10: ='Pricing & Mix'!AE42 -> 400000 | AG10: =SUMIF($C$3:$AE$3,AG$3,$C10:$AE10) -> 0 | AH10: =SUMIF($C$3:$AE$3,AH$3,$C10:$AE10) -> 3697.5 | AI10: =SUMIF($C$3:$AE$3,AI$3,$C10:$AE10) -> 39252.5 | AJ10: =SUMIF($C$3:$AE$3,AJ$3,$C10:$AE10) -> 120000 | AK10: =SUMIF($C$3:$AE$3,AK$3,$C10:$AE10) -> 250000 | AL10: =SUMIF($C$3:$AE$3,AL$3,$C10:$AE10) -> 400000
A11: Expected paid conversions from this period's devices | B11: subs | C11: =MIN(1,sc_attach)*0+('Pricing & Mix'!C39*MIN(1,attach_peb*sc_attach)+'Pricing & Mix'!C40*MIN(1,attach_sq*sc_attach)+'Pricing & Mix'!C41*MIN(1,attach_atl*sc_attach)) -> 0 | D11: =MIN(1,sc_attach)*0+('Pricing & Mix'!D39*MIN(1,attach_peb*sc_attach)+'Pricing & Mix'!D40*MIN(1,attach_sq*sc_attach)+'Pricing & Mix'!D41*MIN(1,attach_atl*sc_attach)) -> 0 | E11: =MIN(1,sc_attach)*0+('Pricing & Mix'!E39*MIN(1,attach_peb*sc_attach)+'Pricing & Mix'!E40*MIN(1,attach_sq*sc_attach)+'Pricing & Mix'!E41*MIN(1,attach_atl*sc_attach)) -> 0 | F11: =MIN(1,sc_attach)*0+('Pricing & Mix'!F39*MIN(1,attach_peb*sc_attach)+'Pricing & Mix'!F40*MIN(1,attach_sq*sc_attach)+'Pricing & Mix'!F41*MIN(1,attach_atl*sc_attach)) -> 0 | G11: =MIN(1,sc_attach)*0+('Pricing & Mix'!G39*MIN(1,attach_peb*sc_attach)+'Pricing & Mix'!G40*MIN(1,attach_sq*sc_attach)+'Pricing & Mix'!G41*MIN(1,attach_atl*sc_attach)) -> 0 | H11: =MIN(1,sc_attach)*0+('Pricing & Mix'!H39*MIN(1,attach_peb*sc_attach)+'Pricing & Mix'!H40*MIN(1,attach_sq*sc_attach)+'Pricing & Mix'!H41*MIN(1,attach_atl*sc_attach)) -> 0 | I11: =MIN(1,sc_attach)*0+('Pricing & Mix'!I39*MIN(1,attach_peb*sc_attach)+'Pricing & Mix'!I40*MIN(1,attach_sq*sc_attach)+'Pricing & Mix'!I41*MIN(1,attach_atl*sc_attach)) -> 0 | J11: =MIN(1,sc_attach)*0+('Pricing & Mix'!J39*MIN(1,attach_peb*sc_attach)+'Pricing & Mix'!J40*MIN(1,attach_sq*sc_attach)+'Pricing & Mix'!J41*MIN(1,attach_atl*sc_attach)) -> 0 | ... AE11: =MIN(1,sc_attach)*0+('Pricing & Mix'!AE39*MIN(1,attach_peb*sc_attach)+'Pricing & Mix'!AE40*MIN(1,attach_sq*sc_attach)+'Pricing & Mix'!AE41*MIN(1,attach_atl*sc_attach)) -> 147400 | AG11: =SUMIF($C$3:$AE$3,AG$3,$C11:$AE11) -> 0 | AH11: =SUMIF($C$3:$AE$3,AH$3,$C11:$AE11) -> 1244.1 | AI11: =SUMIF($C$3:$AE$3,AI$3,$C11:$AE11) -> 14446.55 | AJ11: =SUMIF($C$3:$AE$3,AJ$3,$C11:$AE11) -> 44220 | AK11: =SUMIF($C$3:$AE$3,AK$3,$C11:$AE11) -> 92125 | AL11: =SUMIF($C$3:$AE$3,AL$3,$C11:$AE11) -> 147400
A12: Weighted attach rate (after scenario) | B12: % | C12: =IF('Subscription Cohorts'!C10>0,'Subscription Cohorts'!C11/'Subscription Cohorts'!C10,0) -> 0 | D12: =IF('Subscription Cohorts'!D10>0,'Subscription Cohorts'!D11/'Subscription Cohorts'!D10,0) -> 0 | E12: =IF('Subscription Cohorts'!E10>0,'Subscription Cohorts'!E11/'Subscription Cohorts'!E10,0) -> 0 | F12: =IF('Subscription Cohorts'!F10>0,'Subscription Cohorts'!F11/'Subscription Cohorts'!F10,0) -> 0 | G12: =IF('Subscription Cohorts'!G10>0,'Subscription Cohorts'!G11/'Subscription Cohorts'!G10,0) -> 0 | H12: =IF('Subscription Cohorts'!H10>0,'Subscription Cohorts'!H11/'Subscription Cohorts'!H10,0) -> 0 | I12: =IF('Subscription Cohorts'!I10>0,'Subscription Cohorts'!I11/'Subscription Cohorts'!I10,0) -> 0 | J12: =IF('Subscription Cohorts'!J10>0,'Subscription Cohorts'!J11/'Subscription Cohorts'!J10,0) -> 0 | ... AE12: =IF('Subscription Cohorts'!AE10>0,'Subscription Cohorts'!AE11/'Subscription Cohorts'!AE10,0) -> 0.3685
A13: New paid Explorer subscribers (trial ends) | B13: subs | C13: =0 -> 0 | D13: =0 -> 0 | E13: =0 -> 0 | F13: ='Subscription Cohorts'!C11 -> 0 | G13: ='Subscription Cohorts'!D11 -> 0 | H13: ='Subscription Cohorts'!E11 -> 0 | I13: ='Subscription Cohorts'!F11 -> 0 | J13: ='Subscription Cohorts'!G11 -> 0 | K13: ='Subscription Cohorts'!H11 -> 0 | L13: ='Subscription Cohorts'!I11 -> 0 | M13: ='Subscription Cohorts'!J11 -> 0 | ... AB13: ='Subscription Cohorts'!Y11 -> 1197.625 | AC13: ='Subscription Cohorts'!AC11*0.75+'Subscription Cohorts'!Z11+'Subscription Cohorts'!AA11+'Subscription Cohorts'!AB11 -> 39171.55 | AD13: ='Subscription Cohorts'!AD11*0.75+'Subscription Cohorts'!AC11*0.25 -> 80148.75 | AE13: ='Subscription Cohorts'!AE11*0.75+'Subscription Cohorts'!AD11*0.25 -> 133581.25 | AG13: =SUMIF($C$3:$AE$3,AG$3,$C13:$AE13) -> 0 | AH13: =SUMIF($C$3:$AE$3,AH$3,$C13:$AE13) -> 0 | AI13: =SUMIF($C$3:$AE$3,AI$3,$C13:$AE13) -> 9684.1 | AJ13: =SUMIF($C$3:$AE$3,AJ$3,$C13:$AE13) -> 39171.55 | AK13: =SUMIF($C$3:$AE$3,AK$3,$C13:$AE13) -> 80148.75 | AL13: =SUMIF($C$3:$AE$3,AL$3,$C13:$AE13) -> 133581.25
A14: Monthly churn (after scenario) | B14: %/mo | C14: =MIN(0.5,churn*sc_churn) -> 0.06 | D14: =MIN(0.5,churn*sc_churn) -> 0.06 | E14: =MIN(0.5,churn*sc_churn) -> 0.06 | F14: =MIN(0.5,churn*sc_churn) -> 0.06 | G14: =MIN(0.5,churn*sc_churn) -> 0.06 | H14: =MIN(0.5,churn*sc_churn) -> 0.06 | I14: =MIN(0.5,churn*sc_churn) -> 0.06 | J14: =MIN(0.5,churn*sc_churn) -> 0.06 | ... AE14: =MIN(0.5,churn*sc_churn) -> 0.06
A16: Paid subscriber roll-forward
A17: Beginning paid subs | B17: subs | C17: =0 -> 0 | D17: =C19 -> 0 | E17: =D19 -> 0 | F17: =E19 -> 0 | G17: =F19 -> 0 | H17: =G19 -> 0 | I17: =H19 -> 0 | J17: =I19 -> 0 | K17: =J19 -> 0 | ... AE17: =AD19 -> 73636.421
A18: Churned subs | B18: subs | C18: =C17+C13-C19 -> 0 | D18: =D17+D13-D19 -> 0 | E18: =E17+E13-E19 -> 0 | F18: =F17+F13-F19 -> 0 | G18: =G17+G13-G19 -> 0 | H18: =H17+H13-H19 -> 0 | I18: =I17+I13-I19 -> 0 | J18: =J17+J13-J19 -> 0 | ... AE18: =AE17+AE13-AE19 -> 74940.353 | AG18: =SUMIF($C$3:$AE$3,AG$3,$C18:$AE18) -> 0 | AH18: =SUMIF($C$3:$AE$3,AH$3,$C18:$AE18) -> 0 | AI18: =SUMIF($C$3:$AE$3,AI$3,$C18:$AE18) -> 2057.6813 | AJ18: =SUMIF($C$3:$AE$3,AJ$3,$C18:$AE18) -> 14655.882 | AK18: =SUMIF($C$3:$AE$3,AK$3,$C18:$AE18) -> 38654.415 | AL18: =SUMIF($C$3:$AE$3,AL$3,$C18:$AE18) -> 74940.353
A19: Ending paid subs | B19: subs | C19: ='Subscription Cohorts'!C17*(1-'Subscription Cohorts'!C14)+'Subscription Cohorts'!C13 -> 0 | D19: ='Subscription Cohorts'!D17*(1-'Subscription Cohorts'!D14)+'Subscription Cohorts'!D13 -> 0 | E19: ='Subscription Cohorts'!E17*(1-'Subscription Cohorts'!E14)+'Subscription Cohorts'!E13 -> 0 | F19: ='Subscription Cohorts'!F17*(1-'Subscription Cohorts'!F14)+'Subscription Cohorts'!F13 -> 0 | G19: ='Subscription Cohorts'!G17*(1-'Subscription Cohorts'!G14)+'Subscription Cohorts'!G13 -> 0 | H19: ='Subscription Cohorts'!H17*(1-'Subscription Cohorts'!H14)+'Subscription Cohorts'!H13 -> 0 | I19: ='Subscription Cohorts'!I17*(1-'Subscription Cohorts'!I14)+'Subscription Cohorts'!I13 -> 0 | J19: ='Subscription Cohorts'!J17*(1-'Subscription Cohorts'!J14)+'Subscription Cohorts'!J13 -> 0 | ... AB19: ='Subscription Cohorts'!AB17*(1-'Subscription Cohorts'!AB14)+'Subscription Cohorts'!AB13 -> 7626.4187 | AC19: ='Subscription Cohorts'!AC17*(1-'Subscription Cohorts'!AC14)^12+'Subscription Cohorts'!AC13*(1-(1-'Subscription Cohorts'!AC14)^12)/(12*'Subscription Cohorts'!AC14) -> 32142.086 | AD19: ='Subscription Cohorts'!AD17*(1-'Subscription Cohorts'!AD14)^12+'Subscription Cohorts'!AD13*(1-(1-'Subscription Cohorts'!AD14)^12)/(12*'Subscription Cohorts'!AD14) -> 73636.421 | AE19: ='Subscription Cohorts'!AE17*(1-'Subscription Cohorts'!AE14)^12+'Subscription Cohorts'!AE13*(1-(1-'Subscription Cohorts'!AE14)^12)/(12*'Subscription Cohorts'!AE14) -> 132277.32 | AG19: =D19 -> 0 | AH19: =P19 -> 0 | AI19: =AB19 -> 7626.4187 | AJ19: =AC19 -> 32142.086 | AK19: =AD19 -> 73636.421 | AL19: =AE19 -> 132277.32
A20: Average paid subs in period | B20: subs | C20: =('Subscription Cohorts'!C17+'Subscription Cohorts'!C19)/2 -> 0 | D20: =('Subscription Cohorts'!D17+'Subscription Cohorts'!D19)/2 -> 0 | E20: =('Subscription Cohorts'!E17+'Subscription Cohorts'!E19)/2 -> 0 | F20: =('Subscription Cohorts'!F17+'Subscription Cohorts'!F19)/2 -> 0 | G20: =('Subscription Cohorts'!G17+'Subscription Cohorts'!G19)/2 -> 0 | H20: =('Subscription Cohorts'!H17+'Subscription Cohorts'!H19)/2 -> 0 | I20: =('Subscription Cohorts'!I17+'Subscription Cohorts'!I19)/2 -> 0 | J20: =('Subscription Cohorts'!J17+'Subscription Cohorts'!J19)/2 -> 0 | ... AE20: =('Subscription Cohorts'!AE17+'Subscription Cohorts'!AE19)/2 -> 102956.87 | AG20: =SUMIF($C$3:$AE$3,AG$3,$C20:$AE20)/COUNTIF($C$3:$AE$3,AG$3) -> 0 | AH20: =SUMIF($C$3:$AE$3,AH$3,$C20:$AE20)/COUNTIF($C$3:$AE$3,AH$3) -> 0 | AI20: =SUMIF($C$3:$AE$3,AI$3,$C20:$AE20)/COUNTIF($C$3:$AE$3,AI$3) -> 3175.6582 | AJ20: =SUMIF($C$3:$AE$3,AJ$3,$C20:$AE20)/COUNTIF($C$3:$AE$3,AJ$3) -> 19884.253 | AK20: =SUMIF($C$3:$AE$3,AK$3,$C20:$AE20)/COUNTIF($C$3:$AE$3,AK$3) -> 52889.254 | AL20: =SUMIF($C$3:$AE$3,AL$3,$C20:$AE20)/COUNTIF($C$3:$AE$3,AL$3) -> 102956.87
A21: Paid subscriber-months | B21: sub-mo | C21: ='Subscription Cohorts'!C20*Timeline!C4 -> 0 | D21: ='Subscription Cohorts'!D20*Timeline!D4 -> 0 | E21: ='Subscription Cohorts'!E20*Timeline!E4 -> 0 | F21: ='Subscription Cohorts'!F20*Timeline!F4 -> 0 | G21: ='Subscription Cohorts'!G20*Timeline!G4 -> 0 | H21: ='Subscription Cohorts'!H20*Timeline!H4 -> 0 | I21: ='Subscription Cohorts'!I20*Timeline!I4 -> 0 | J21: ='Subscription Cohorts'!J20*Timeline!J4 -> 0 | ... AE21: ='Subscription Cohorts'!AE20*Timeline!AE4 -> 1235482.4 | AG21: =SUMIF($C$3:$AE$3,AG$3,$C21:$AE21) -> 0 | AH21: =SUMIF($C$3:$AE$3,AH$3,$C21:$AE21) -> 0 | AI21: =SUMIF($C$3:$AE$3,AI$3,$C21:$AE21) -> 38107.898 | AJ21: =SUMIF($C$3:$AE$3,AJ$3,$C21:$AE21) -> 238611.03 | AK21: =SUMIF($C$3:$AE$3,AK$3,$C21:$AE21) -> 634671.05 | AL21: =SUMIF($C$3:$AE$3,AL$3,$C21:$AE21) -> 1235482.4
A22: Realised ARPU per paid sub-month | B22: $ | C22: =sub_price*arpu_real*sc_price -> 8.5914 | D22: =sub_price*arpu_real*sc_price -> 8.5914 | E22: =sub_price*arpu_real*sc_price -> 8.5914 | F22: =sub_price*arpu_real*sc_price -> 8.5914 | G22: =sub_price*arpu_real*sc_price -> 8.5914 | H22: =sub_price*arpu_real*sc_price -> 8.5914 | I22: =sub_price*arpu_real*sc_price -> 8.5914 | J22: =sub_price*arpu_real*sc_price -> 8.5914 | ... AE22: =sub_price*arpu_real*sc_price -> 8.5914
A23: Subscription revenue (Explorer) | B23: $ | C23: ='Subscription Cohorts'!C21*'Subscription Cohorts'!C22 -> 0 | D23: ='Subscription Cohorts'!D21*'Subscription Cohorts'!D22 -> 0 | E23: ='Subscription Cohorts'!E21*'Subscription Cohorts'!E22 -> 0 | F23: ='Subscription Cohorts'!F21*'Subscription Cohorts'!F22 -> 0 | G23: ='Subscription Cohorts'!G21*'Subscription Cohorts'!G22 -> 0 | H23: ='Subscription Cohorts'!H21*'Subscription Cohorts'!H22 -> 0 | I23: ='Subscription Cohorts'!I21*'Subscription Cohorts'!I22 -> 0 | J23: ='Subscription Cohorts'!J21*'Subscription Cohorts'!J22 -> 0 | ... AE23: ='Subscription Cohorts'!AE21*'Subscription Cohorts'!AE22 -> 10614524 | AG23: =SUMIF($C$3:$AE$3,AG$3,$C23:$AE23) -> 0 | AH23: =SUMIF($C$3:$AE$3,AH$3,$C23:$AE23) -> 0 | AI23: =SUMIF($C$3:$AE$3,AI$3,$C23:$AE23) -> 327400.2 | AJ23: =SUMIF($C$3:$AE$3,AJ$3,$C23:$AE23) -> 2050002.8 | AK23: =SUMIF($C$3:$AE$3,AK$3,$C23:$AE23) -> 5452712.8 | AL23: =SUMIF($C$3:$AE$3,AL$3,$C23:$AE23) -> 10614524
A24: Subscription ARR at period end (ending subs x ARPU x 12) | B24: $ | C24: ='Subscription Cohorts'!C19*'Subscription Cohorts'!C22*12 -> 0 | D24: ='Subscription Cohorts'!D19*'Subscription Cohorts'!D22*12 -> 0 | E24: ='Subscription Cohorts'!E19*'Subscription Cohorts'!E22*12 -> 0 | F24: ='Subscription Cohorts'!F19*'Subscription Cohorts'!F22*12 -> 0 | G24: ='Subscription Cohorts'!G19*'Subscription Cohorts'!G22*12 -> 0 | H24: ='Subscription Cohorts'!H19*'Subscription Cohorts'!H22*12 -> 0 | I24: ='Subscription Cohorts'!I19*'Subscription Cohorts'!I22*12 -> 0 | J24: ='Subscription Cohorts'!J19*'Subscription Cohorts'!J22*12 -> 0 | ... AE24: ='Subscription Cohorts'!AE19*'Subscription Cohorts'!AE22*12 -> 13637368 | AG24: =D24 -> 0 | AH24: =P24 -> 0 | AI24: =AB24 -> 786259.36 | AJ24: =AC24 -> 3313746.3 | AK24: =AD24 -> 7591679.4 | AL24: =AE24 -> 13637368
A26: Trials & installed base
A27: Trial user-months (devices inside their free 3 months) | B27: user-mo | C27: ='Subscription Cohorts'!C10 -> 0 | D27: ='Subscription Cohorts'!C10+'Subscription Cohorts'!D10 -> 0 | E27: ='Subscription Cohorts'!C10+'Subscription Cohorts'!D10+'Subscription Cohorts'!E10 -> 0 | F27: ='Subscription Cohorts'!D10+'Subscription Cohorts'!E10+'Subscription Cohorts'!F10 -> 0 | G27: ='Subscription Cohorts'!E10+'Subscription Cohorts'!F10+'Subscription Cohorts'!G10 -> 0 | H27: ='Subscription Cohorts'!F10+'Subscription Cohorts'!G10+'Subscription Cohorts'!H10 -> 0 | I27: ='Subscription Cohorts'!G10+'Subscription Cohorts'!H10+'Subscription Cohorts'!I10 -> 0 | J27: ='Subscription Cohorts'!H10+'Subscription Cohorts'!I10+'Subscription Cohorts'!J10 -> 0 | K27: ='Subscription Cohorts'!I10+'Subscription Cohorts'!J10+'Subscription Cohorts'!K10 -> 0 | L27: ='Subscription Cohorts'!J10+'Subscription Cohorts'!K10+'Subscription Cohorts'!L10 -> 0 | ... AB27: ='Subscription Cohorts'!Z10+'Subscription Cohorts'!AA10+'Subscription Cohorts'!AB10 -> 16300 | AC27: ='Subscription Cohorts'!AC10*trial_months -> 360000 | AD27: ='Subscription Cohorts'!AD10*trial_months -> 750000 | AE27: ='Subscription Cohorts'!AE10*trial_months -> 1200000 | AG27: =SUMIF($C$3:$AE$3,AG$3,$C27:$AE27) -> 0 | AH27: =SUMIF($C$3:$AE$3,AH$3,$C27:$AE27) -> 5822.5 | AI27: =SUMIF($C$3:$AE$3,AI$3,$C27:$AE27) -> 102977.5 | AJ27: =SUMIF($C$3:$AE$3,AJ$3,$C27:$AE27) -> 360000 | AK27: =SUMIF($C$3:$AE$3,AK$3,$C27:$AE27) -> 750000 | AL27: =SUMIF($C$3:$AE$3,AL$3,$C27:$AE27) -> 1200000
A28: Active devices -- beginning | B28: devices | C28: =0 -> 0 | D28: =C29 -> 0 | E28: =D29 -> 0 | F28: =E29 -> 0 | G28: =F29 -> 0 | H28: =G29 -> 0 | I28: =H29 -> 0 | J28: =I29 -> 0 | K28: =J29 -> 0 | ... AE28: =AD29 -> 332813.71
A29: Active devices -- ending | B29: devices | C29: ='Subscription Cohorts'!C28*(1-device_inactive)+'Subscription Cohorts'!C10 -> 0 | D29: ='Subscription Cohorts'!D28*(1-device_inactive)+'Subscription Cohorts'!D10 -> 0 | E29: ='Subscription Cohorts'!E28*(1-device_inactive)+'Subscription Cohorts'!E10 -> 0 | F29: ='Subscription Cohorts'!F28*(1-device_inactive)+'Subscription Cohorts'!F10 -> 0 | G29: ='Subscription Cohorts'!G28*(1-device_inactive)+'Subscription Cohorts'!G10 -> 0 | H29: ='Subscription Cohorts'!H28*(1-device_inactive)+'Subscription Cohorts'!H10 -> 0 | I29: ='Subscription Cohorts'!I28*(1-device_inactive)+'Subscription Cohorts'!I10 -> 0 | J29: ='Subscription Cohorts'!J28*(1-device_inactive)+'Subscription Cohorts'!J10 -> 0 | ... AB29: ='Subscription Cohorts'!AB28*(1-device_inactive)+'Subscription Cohorts'!AB10 -> 39124.509 | AC29: ='Subscription Cohorts'!AC28*(1-device_inactive)^12+'Subscription Cohorts'!AC10*(1-(1-device_inactive)^12)/(12*device_inactive) -> 138343.29 | AD29: ='Subscription Cohorts'!AD28*(1-device_inactive)^12+'Subscription Cohorts'!AD10*(1-(1-device_inactive)^12)/(12*device_inactive) -> 332813.71 | AE29: ='Subscription Cohorts'!AE28*(1-device_inactive)^12+'Subscription Cohorts'!AE10*(1-(1-device_inactive)^12)/(12*device_inactive) -> 619969.94 | AG29: =D29 -> 0 | AH29: =P29 -> 3655 | AI29: =AB29 -> 39124.509 | AJ29: =AC29 -> 138343.29 | AK29: =AD29 -> 332813.71 | AL29: =AE29 -> 619969.94
A30: Active devices -- average | B30: devices | C30: =('Subscription Cohorts'!C28+'Subscription Cohorts'!C29)/2 -> 0 | D30: =('Subscription Cohorts'!D28+'Subscription Cohorts'!D29)/2 -> 0 | E30: =('Subscription Cohorts'!E28+'Subscription Cohorts'!E29)/2 -> 0 | F30: =('Subscription Cohorts'!F28+'Subscription Cohorts'!F29)/2 -> 0 | G30: =('Subscription Cohorts'!G28+'Subscription Cohorts'!G29)/2 -> 0 | H30: =('Subscription Cohorts'!H28+'Subscription Cohorts'!H29)/2 -> 0 | I30: =('Subscription Cohorts'!I28+'Subscription Cohorts'!I29)/2 -> 0 | J30: =('Subscription Cohorts'!J28+'Subscription Cohorts'!J29)/2 -> 0 | ... AE30: =('Subscription Cohorts'!AE28+'Subscription Cohorts'!AE29)/2 -> 476391.83 | AG30: =SUMIF($C$3:$AE$3,AG$3,$C30:$AE30)/COUNTIF($C$3:$AE$3,AG$3) -> 0 | AH30: =SUMIF($C$3:$AE$3,AH$3,$C30:$AE30)/COUNTIF($C$3:$AE$3,AH$3) -> 329.375 | AI30: =SUMIF($C$3:$AE$3,AI$3,$C30:$AE30)/COUNTIF($C$3:$AE$3,AI$3) -> 17240.358 | AJ30: =SUMIF($C$3:$AE$3,AJ$3,$C30:$AE30)/COUNTIF($C$3:$AE$3,AJ$3) -> 88733.902 | AK30: =SUMIF($C$3:$AE$3,AK$3,$C30:$AE30)/COUNTIF($C$3:$AE$3,AK$3) -> 235578.5 | AL30: =SUMIF($C$3:$AE$3,AL$3,$C30:$AE30)/COUNTIF($C$3:$AE$3,AL$3) -> 476391.83
A31: Active device-months | B31: dev-mo | C31: ='Subscription Cohorts'!C30*Timeline!C4 -> 0 | D31: ='Subscription Cohorts'!D30*Timeline!D4 -> 0 | E31: ='Subscription Cohorts'!E30*Timeline!E4 -> 0 | F31: ='Subscription Cohorts'!F30*Timeline!F4 -> 0 | G31: ='Subscription Cohorts'!G30*Timeline!G4 -> 0 | H31: ='Subscription Cohorts'!H30*Timeline!H4 -> 0 | I31: ='Subscription Cohorts'!I30*Timeline!I4 -> 0 | J31: ='Subscription Cohorts'!J30*Timeline!J4 -> 0 | ... AE31: ='Subscription Cohorts'!AE30*Timeline!AE4 -> 5716701.9 | AG31: =SUMIF($C$3:$AE$3,AG$3,$C31:$AE31) -> 0 | AH31: =SUMIF($C$3:$AE$3,AH$3,$C31:$AE31) -> 3952.5 | AI31: =SUMIF($C$3:$AE$3,AI$3,$C31:$AE31) -> 206884.3 | AJ31: =SUMIF($C$3:$AE$3,AJ$3,$C31:$AE31) -> 1064806.8 | AK31: =SUMIF($C$3:$AE$3,AK$3,$C31:$AE31) -> 2826942 | AL31: =SUMIF($C$3:$AE$3,AL$3,$C31:$AE31) -> 5716701.9
A32: eSIM device share (Square + Atlas, period mix) | B32: % | C32: =Assumptions!C108+Assumptions!C109 -> 0.47 | D32: =Assumptions!D108+Assumptions!D109 -> 0.47 | E32: =Assumptions!E108+Assumptions!E109 -> 0.47 | F32: =Assumptions!F108+Assumptions!F109 -> 0.47 | G32: =Assumptions!G108+Assumptions!G109 -> 0.47 | H32: =Assumptions!H108+Assumptions!H109 -> 0.47 | I32: =Assumptions!I108+Assumptions!I109 -> 0.47 | J32: =Assumptions!J108+Assumptions!J109 -> 0.47 | ... AE32: =Assumptions!AE108+Assumptions!AE109 -> 0.55
A33: Free-tier device-months (active, not paying, not in trial) | B33: dev-mo | C33: =MAX(0,'Subscription Cohorts'!C31-'Subscription Cohorts'!C21-'Subscription Cohorts'!C27) -> 0 | D33: =MAX(0,'Subscription Cohorts'!D31-'Subscription Cohorts'!D21-'Subscription Cohorts'!D27) -> 0 | E33: =MAX(0,'Subscription Cohorts'!E31-'Subscription Cohorts'!E21-'Subscription Cohorts'!E27) -> 0 | F33: =MAX(0,'Subscription Cohorts'!F31-'Subscription Cohorts'!F21-'Subscription Cohorts'!F27) -> 0 | G33: =MAX(0,'Subscription Cohorts'!G31-'Subscription Cohorts'!G21-'Subscription Cohorts'!G27) -> 0 | H33: =MAX(0,'Subscription Cohorts'!H31-'Subscription Cohorts'!H21-'Subscription Cohorts'!H27) -> 0 | I33: =MAX(0,'Subscription Cohorts'!I31-'Subscription Cohorts'!I21-'Subscription Cohorts'!I27) -> 0 | J33: =MAX(0,'Subscription Cohorts'!J31-'Subscription Cohorts'!J21-'Subscription Cohorts'!J27) -> 0 | ... AE33: =MAX(0,'Subscription Cohorts'!AE31-'Subscription Cohorts'!AE21-'Subscription Cohorts'!AE27) -> 3281219.5 | AG33: =SUMIF($C$3:$AE$3,AG$3,$C33:$AE33) -> 0 | AH33: =SUMIF($C$3:$AE$3,AH$3,$C33:$AE33) -> 0 | AI33: =SUMIF($C$3:$AE$3,AI$3,$C33:$AE33) -> 66779.203 | AJ33: =SUMIF($C$3:$AE$3,AJ$3,$C33:$AE33) -> 466195.79 | AK33: =SUMIF($C$3:$AE$3,AK$3,$C33:$AE33) -> 1442271 | AL33: =SUMIF($C$3:$AE$3,AL$3,$C33:$AE33) -> 3281219.5
A34: Trip Passes sold | B34: passes | C34: ='Subscription Cohorts'!C33*'Subscription Cohorts'!C32*trip_rate -> 0 | D34: ='Subscription Cohorts'!D33*'Subscription Cohorts'!D32*trip_rate -> 0 | E34: ='Subscription Cohorts'!E33*'Subscription Cohorts'!E32*trip_rate -> 0 | F34: ='Subscription Cohorts'!F33*'Subscription Cohorts'!F32*trip_rate -> 0 | G34: ='Subscription Cohorts'!G33*'Subscription Cohorts'!G32*trip_rate -> 0 | H34: ='Subscription Cohorts'!H33*'Subscription Cohorts'!H32*trip_rate -> 0 | I34: ='Subscription Cohorts'!I33*'Subscription Cohorts'!I32*trip_rate -> 0 | J34: ='Subscription Cohorts'!J33*'Subscription Cohorts'!J32*trip_rate -> 0 | ... AE34: ='Subscription Cohorts'!AE33*'Subscription Cohorts'!AE32*trip_rate -> 54140.122 | AG34: =SUMIF($C$3:$AE$3,AG$3,$C34:$AE34) -> 0 | AH34: =SUMIF($C$3:$AE$3,AH$3,$C34:$AE34) -> 0 | AI34: =SUMIF($C$3:$AE$3,AI$3,$C34:$AE34) -> 1096.6509 | AJ34: =SUMIF($C$3:$AE$3,AJ$3,$C34:$AE34) -> 7692.2306 | AK34: =SUMIF($C$3:$AE$3,AK$3,$C34:$AE34) -> 23797.471 | AL34: =SUMIF($C$3:$AE$3,AL$3,$C34:$AE34) -> 54140.122
A35: Trip Pass revenue | B35: $ | C35: ='Subscription Cohorts'!C34*trip_price*sc_price -> 0 | D35: ='Subscription Cohorts'!D34*trip_price*sc_price -> 0 | E35: ='Subscription Cohorts'!E34*trip_price*sc_price -> 0 | F35: ='Subscription Cohorts'!F34*trip_price*sc_price -> 0 | G35: ='Subscription Cohorts'!G34*trip_price*sc_price -> 0 | H35: ='Subscription Cohorts'!H34*trip_price*sc_price -> 0 | I35: ='Subscription Cohorts'!I34*trip_price*sc_price -> 0 | J35: ='Subscription Cohorts'!J34*trip_price*sc_price -> 0 | ... AE35: ='Subscription Cohorts'!AE34*trip_price*sc_price -> 1732483.9 | AG35: =SUMIF($C$3:$AE$3,AG$3,$C35:$AE35) -> 0 | AH35: =SUMIF($C$3:$AE$3,AH$3,$C35:$AE35) -> 0 | AI35: =SUMIF($C$3:$AE$3,AI$3,$C35:$AE35) -> 35092.829 | AJ35: =SUMIF($C$3:$AE$3,AJ$3,$C35:$AE35) -> 246151.38 | AK35: =SUMIF($C$3:$AE$3,AK$3,$C35:$AE35) -> 761519.08 | AL35: =SUMIF($C$3:$AE$3,AL$3,$C35:$AE35) -> 1732483.9
A36: Paid subs as % of active devices (end) | B36: % | C36: =IF('Subscription Cohorts'!C29>0,'Subscription Cohorts'!C19/'Subscription Cohorts'!C29,0) -> 0 | D36: =IF('Subscription Cohorts'!D29>0,'Subscription Cohorts'!D19/'Subscription Cohorts'!D29,0) -> 0 | E36: =IF('Subscription Cohorts'!E29>0,'Subscription Cohorts'!E19/'Subscription Cohorts'!E29,0) -> 0 | F36: =IF('Subscription Cohorts'!F29>0,'Subscription Cohorts'!F19/'Subscription Cohorts'!F29,0) -> 0 | G36: =IF('Subscription Cohorts'!G29>0,'Subscription Cohorts'!G19/'Subscription Cohorts'!G29,0) -> 0 | H36: =IF('Subscription Cohorts'!H29>0,'Subscription Cohorts'!H19/'Subscription Cohorts'!H29,0) -> 0 | I36: =IF('Subscription Cohorts'!I29>0,'Subscription Cohorts'!I19/'Subscription Cohorts'!I29,0) -> 0 | J36: =IF('Subscription Cohorts'!J29>0,'Subscription Cohorts'!J19/'Subscription Cohorts'!J29,0) -> 0 | ... AE36: =IF('Subscription Cohorts'!AE29>0,'Subscription Cohorts'!AE19/'Subscription Cohorts'!AE29,0) -> 0.21336086

Sheet Revenue Build
A1: Revenue build by stream
A2: Period | C2: =Timeline!C2 -> Nov-26 | D2: =Timeline!D2 -> Dec-26 | E2: =Timeline!E2 -> Jan-27 | F2: =Timeline!F2 -> Feb-27 | G2: =Timeline!G2 -> Mar-27 | H2: =Timeline!H2 -> Apr-27 | I2: =Timeline!I2 -> May-27 | J2: =Timeline!J2 -> Jun-27 | ... AE2: =Timeline!AE2 -> FY2031 | AG2: FY2026 (Nov-Dec) | AH2: FY2027 | AI2: FY2028 | AJ2: FY2029 | AK2: FY2030 | AL2: FY2031
A3: Year | C3: =Timeline!C3 -> 2026 | D3: =Timeline!D3 -> 2026 | E3: =Timeline!E3 -> 2027 | F3: =Timeline!F3 -> 2027 | G3: =Timeline!G3 -> 2027 | H3: =Timeline!H3 -> 2027 | I3: =Timeline!I3 -> 2027 | J3: =Timeline!J3 -> 2027 | ... AE3: =Timeline!AE3 -> 2031 | AG3: 2026 | AH3: 2027 | AI3: 2028 | AJ3: 2029 | AK3: 2030 | AL3: 2031
A4: Months in period | C4: =Timeline!C4 -> 1 | D4: =Timeline!D4 -> 1 | E4: =Timeline!E4 -> 1 | F4: =Timeline!F4 -> 1 | G4: =Timeline!G4 -> 1 | H4: =Timeline!H4 -> 1 | I4: =Timeline!I4 -> 1 | J4: =Timeline!J4 -> 1 | ... AE4: =Timeline!AE4 -> 12
A5: Period start | C5: =Timeline!C5 -> 46327 | D5: =Timeline!D5 -> 46357 | E5: =Timeline!E5 -> 46388 | F5: =Timeline!F5 -> 46419 | G5: =Timeline!G5 -> 46447 | H5: =Timeline!H5 -> 46478 | I5: =Timeline!I5 -> 46508 | J5: =Timeline!J5 -> 46539 | ... AE5: =Timeline!AE5 -> 47849
A6: Period key | C6: =Timeline!C6 -> 202611 | D6: =Timeline!D6 -> 202612 | E6: =Timeline!E6 -> 202701 | F6: =Timeline!F6 -> 202702 | G6: =Timeline!G6 -> 202703 | H6: =Timeline!H6 -> 202704 | I6: =Timeline!I6 -> 202705 | J6: =Timeline!J6 -> 202706 | ... AE6: =Timeline!AE6 -> 2031
A9: Hardware
A10: Hardware -- DTC (web/app) | C10: ='Pricing & Mix'!C29*'Pricing & Mix'!C13+'Pricing & Mix'!C30*'Pricing & Mix'!C14+'Pricing & Mix'!C31*'Pricing & Mix'!C15 -> 0 | D10: ='Pricing & Mix'!D29*'Pricing & Mix'!D13+'Pricing & Mix'!D30*'Pricing & Mix'!D14+'Pricing & Mix'!D31*'Pricing & Mix'!D15 -> 0 | E10: ='Pricing & Mix'!E29*'Pricing & Mix'!E13+'Pricing & Mix'!E30*'Pricing & Mix'!E14+'Pricing & Mix'!E31*'Pricing & Mix'!E15 -> 0 | F10: ='Pricing & Mix'!F29*'Pricing & Mix'!F13+'Pricing & Mix'!F30*'Pricing & Mix'!F14+'Pricing & Mix'!F31*'Pricing & Mix'!F15 -> 0 | G10: ='Pricing & Mix'!G29*'Pricing & Mix'!G13+'Pricing & Mix'!G30*'Pricing & Mix'!G14+'Pricing & Mix'!G31*'Pricing & Mix'!G15 -> 0 | H10: ='Pricing & Mix'!H29*'Pricing & Mix'!H13+'Pricing & Mix'!H30*'Pricing & Mix'!H14+'Pricing & Mix'!H31*'Pricing & Mix'!H15 -> 0 | I10: ='Pricing & Mix'!I29*'Pricing & Mix'!I13+'Pricing & Mix'!I30*'Pricing & Mix'!I14+'Pricing & Mix'!I31*'Pricing & Mix'!I15 -> 0 | J10: ='Pricing & Mix'!J29*'Pricing & Mix'!J13+'Pricing & Mix'!J30*'Pricing & Mix'!J14+'Pricing & Mix'!J31*'Pricing & Mix'!J15 -> 0 | ... AE10: ='Pricing & Mix'!AE29*'Pricing & Mix'!AE13+'Pricing & Mix'!AE30*'Pricing & Mix'!AE14+'Pricing & Mix'!AE31*'Pricing & Mix'!AE15 -> 67576600 | AG10: =SUMIF($C$3:$AE$3,AG$3,$C10:$AE10) -> 0 | AH10: =SUMIF($C$3:$AE$3,AH$3,$C10:$AE10) -> 0 | AI10: =SUMIF($C$3:$AE$3,AI$3,$C10:$AE10) -> 7644988.3 | AJ10: =SUMIF($C$3:$AE$3,AJ$3,$C10:$AE10) -> 21832440 | AK10: =SUMIF($C$3:$AE$3,AK$3,$C10:$AE10) -> 42235375 | AL10: =SUMIF($C$3:$AE$3,AL$3,$C10:$AE10) -> 67576600
A11: Hardware -- retail / wholesale (sell-in) | C11: ='Pricing & Mix'!C32*'Pricing & Mix'!C16+'Pricing & Mix'!C33*'Pricing & Mix'!C17+'Pricing & Mix'!C34*'Pricing & Mix'!C18 -> 0 | D11: ='Pricing & Mix'!D32*'Pricing & Mix'!D16+'Pricing & Mix'!D33*'Pricing & Mix'!D17+'Pricing & Mix'!D34*'Pricing & Mix'!D18 -> 0 | E11: ='Pricing & Mix'!E32*'Pricing & Mix'!E16+'Pricing & Mix'!E33*'Pricing & Mix'!E17+'Pricing & Mix'!E34*'Pricing & Mix'!E18 -> 0 | F11: ='Pricing & Mix'!F32*'Pricing & Mix'!F16+'Pricing & Mix'!F33*'Pricing & Mix'!F17+'Pricing & Mix'!F34*'Pricing & Mix'!F18 -> 0 | G11: ='Pricing & Mix'!G32*'Pricing & Mix'!G16+'Pricing & Mix'!G33*'Pricing & Mix'!G17+'Pricing & Mix'!G34*'Pricing & Mix'!G18 -> 0 | H11: ='Pricing & Mix'!H32*'Pricing & Mix'!H16+'Pricing & Mix'!H33*'Pricing & Mix'!H17+'Pricing & Mix'!H34*'Pricing & Mix'!H18 -> 0 | I11: ='Pricing & Mix'!I32*'Pricing & Mix'!I16+'Pricing & Mix'!I33*'Pricing & Mix'!I17+'Pricing & Mix'!I34*'Pricing & Mix'!I18 -> 0 | J11: ='Pricing & Mix'!J32*'Pricing & Mix'!J16+'Pricing & Mix'!J33*'Pricing & Mix'!J17+'Pricing & Mix'!J34*'Pricing & Mix'!J18 -> 0 | ... AE11: ='Pricing & Mix'!AE32*'Pricing & Mix'!AE16+'Pricing & Mix'!AE33*'Pricing & Mix'!AE17+'Pricing & Mix'!AE34*'Pricing & Mix'!AE18 -> 24000200 | AG11: =SUMIF($C$3:$AE$3,AG$3,$C11:$AE11) -> 0 | AH11: =SUMIF($C$3:$AE$3,AH$3,$C11:$AE11) -> 0 | AI11: =SUMIF($C$3:$AE$3,AI$3,$C11:$AE11) -> 1313134.4 | AJ11: =SUMIF($C$3:$AE$3,AJ$3,$C11:$AE11) -> 6171480 | AK11: =SUMIF($C$3:$AE$3,AK$3,$C11:$AE11) -> 15000125 | AL11: =SUMIF($C$3:$AE$3,AL$3,$C11:$AE11) -> 24000200
A12: Hardware -- Kickstarter / pre-orders (recognised on shipment) | C12: ='Pricing & Mix'!C35*'Pricing & Mix'!C19+'Pricing & Mix'!C36*'Pricing & Mix'!C20+'Pricing & Mix'!C37*'Pricing & Mix'!C21 -> 0 | D12: ='Pricing & Mix'!D35*'Pricing & Mix'!D19+'Pricing & Mix'!D36*'Pricing & Mix'!D20+'Pricing & Mix'!D37*'Pricing & Mix'!D21 -> 0 | E12: ='Pricing & Mix'!E35*'Pricing & Mix'!E19+'Pricing & Mix'!E36*'Pricing & Mix'!E20+'Pricing & Mix'!E37*'Pricing & Mix'!E21 -> 0 | F12: ='Pricing & Mix'!F35*'Pricing & Mix'!F19+'Pricing & Mix'!F36*'Pricing & Mix'!F20+'Pricing & Mix'!F37*'Pricing & Mix'!F21 -> 0 | G12: ='Pricing & Mix'!G35*'Pricing & Mix'!G19+'Pricing & Mix'!G36*'Pricing & Mix'!G20+'Pricing & Mix'!G37*'Pricing & Mix'!G21 -> 0 | H12: ='Pricing & Mix'!H35*'Pricing & Mix'!H19+'Pricing & Mix'!H36*'Pricing & Mix'!H20+'Pricing & Mix'!H37*'Pricing & Mix'!H21 -> 0 | I12: ='Pricing & Mix'!I35*'Pricing & Mix'!I19+'Pricing & Mix'!I36*'Pricing & Mix'!I20+'Pricing & Mix'!I37*'Pricing & Mix'!I21 -> 0 | J12: ='Pricing & Mix'!J35*'Pricing & Mix'!J19+'Pricing & Mix'!J36*'Pricing & Mix'!J20+'Pricing & Mix'!J37*'Pricing & Mix'!J21 -> 0 | ... AE12: ='Pricing & Mix'!AE35*'Pricing & Mix'!AE19+'Pricing & Mix'!AE36*'Pricing & Mix'!AE20+'Pricing & Mix'!AE37*'Pricing & Mix'!AE21 -> 0 | AG12: =SUMIF($C$3:$AE$3,AG$3,$C12:$AE12) -> 0 | AH12: =SUMIF($C$3:$AE$3,AH$3,$C12:$AE12) -> 630619.5 | AI12: =SUMIF($C$3:$AE$3,AI$3,$C12:$AE12) -> 434280.5 | AJ12: =SUMIF($C$3:$AE$3,AJ$3,$C12:$AE12) -> 0 | AK12: =SUMIF($C$3:$AE$3,AK$3,$C12:$AE12) -> 0 | AL12: =SUMIF($C$3:$AE$3,AL$3,$C12:$AE12) -> 0
A13: Gross hardware revenue | C13: ='Revenue Build'!C10+'Revenue Build'!C11+'Revenue Build'!C12 -> 0 | D13: ='Revenue Build'!D10+'Revenue Build'!D11+'Revenue Build'!D12 -> 0 | E13: ='Revenue Build'!E10+'Revenue Build'!E11+'Revenue Build'!E12 -> 0 | F13: ='Revenue Build'!F10+'Revenue Build'!F11+'Revenue Build'!F12 -> 0 | G13: ='Revenue Build'!G10+'Revenue Build'!G11+'Revenue Build'!G12 -> 0 | H13: ='Revenue Build'!H10+'Revenue Build'!H11+'Revenue Build'!H12 -> 0 | I13: ='Revenue Build'!I10+'Revenue Build'!I11+'Revenue Build'!I12 -> 0 | J13: ='Revenue Build'!J10+'Revenue Build'!J11+'Revenue Build'!J12 -> 0 | ... AE13: ='Revenue Build'!AE10+'Revenue Build'!AE11+'Revenue Build'!AE12 -> 91576800 | AG13: =SUMIF($C$3:$AE$3,AG$3,$C13:$AE13) -> 0 | AH13: =SUMIF($C$3:$AE$3,AH$3,$C13:$AE13) -> 630619.5 | AI13: =SUMIF($C$3:$AE$3,AI$3,$C13:$AE13) -> 9392403.2 | AJ13: =SUMIF($C$3:$AE$3,AJ$3,$C13:$AE13) -> 28003920 | AK13: =SUMIF($C$3:$AE$3,AK$3,$C13:$AE13) -> 57235500 | AL13: =SUMIF($C$3:$AE$3,AL$3,$C13:$AE13) -> 91576800
A14: Less: returns & refunds allowance | C14: =-'Revenue Build'!C13*returns_pct -> 0 | D14: =-'Revenue Build'!D13*returns_pct -> 0 | E14: =-'Revenue Build'!E13*returns_pct -> 0 | F14: =-'Revenue Build'!F13*returns_pct -> 0 | G14: =-'Revenue Build'!G13*returns_pct -> 0 | H14: =-'Revenue Build'!H13*returns_pct -> 0 | I14: =-'Revenue Build'!I13*returns_pct -> 0 | J14: =-'Revenue Build'!J13*returns_pct -> 0 | ... AE14: =-'Revenue Build'!AE13*returns_pct -> -3663072 | AG14: =SUMIF($C$3:$AE$3,AG$3,$C14:$AE14) -> 0 | AH14: =SUMIF($C$3:$AE$3,AH$3,$C14:$AE14) -> -25224.78 | AI14: =SUMIF($C$3:$AE$3,AI$3,$C14:$AE14) -> -375696.13 | AJ14: =SUMIF($C$3:$AE$3,AJ$3,$C14:$AE14) -> -1120156.8 | AK14: =SUMIF($C$3:$AE$3,AK$3,$C14:$AE14) -> -2289420 | AL14: =SUMIF($C$3:$AE$3,AL$3,$C14:$AE14) -> -3663072
A15: Net hardware revenue | C15: ='Revenue Build'!C13+'Revenue Build'!C14 -> 0 | D15: ='Revenue Build'!D13+'Revenue Build'!D14 -> 0 | E15: ='Revenue Build'!E13+'Revenue Build'!E14 -> 0 | F15: ='Revenue Build'!F13+'Revenue Build'!F14 -> 0 | G15: ='Revenue Build'!G13+'Revenue Build'!G14 -> 0 | H15: ='Revenue Build'!H13+'Revenue Build'!H14 -> 0 | I15: ='Revenue Build'!I13+'Revenue Build'!I14 -> 0 | J15: ='Revenue Build'!J13+'Revenue Build'!J14 -> 0 | ... AE15: ='Revenue Build'!AE13+'Revenue Build'!AE14 -> 87913728 | AG15: =SUMIF($C$3:$AE$3,AG$3,$C15:$AE15) -> 0 | AH15: =SUMIF($C$3:$AE$3,AH$3,$C15:$AE15) -> 605394.72 | AI15: =SUMIF($C$3:$AE$3,AI$3,$C15:$AE15) -> 9016707.1 | AJ15: =SUMIF($C$3:$AE$3,AJ$3,$C15:$AE15) -> 26883763 | AK15: =SUMIF($C$3:$AE$3,AK$3,$C15:$AE15) -> 54946080 | AL15: =SUMIF($C$3:$AE$3,AL$3,$C15:$AE15) -> 87913728
A17: Recurring & other
A18: Subscriptions -- LORE Pass Explorer | C18: ='Subscription Cohorts'!C23 -> 0 | D18: ='Subscription Cohorts'!D23 -> 0 | E18: ='Subscription Cohorts'!E23 -> 0 | F18: ='Subscription Cohorts'!F23 -> 0 | G18: ='Subscription Cohorts'!G23 -> 0 | H18: ='Subscription Cohorts'!H23 -> 0 | I18: ='Subscription Cohorts'!I23 -> 0 | J18: ='Subscription Cohorts'!J23 -> 0 | ... AE18: ='Subscription Cohorts'!AE23 -> 10614524 | AG18: =SUMIF($C$3:$AE$3,AG$3,$C18:$AE18) -> 0 | AH18: =SUMIF($C$3:$AE$3,AH$3,$C18:$AE18) -> 0 | AI18: =SUMIF($C$3:$AE$3,AI$3,$C18:$AE18) -> 327400.2 | AJ18: =SUMIF($C$3:$AE$3,AJ$3,$C18:$AE18) -> 2050002.8 | AK18: =SUMIF($C$3:$AE$3,AK$3,$C18:$AE18) -> 5452712.8 | AL18: =SUMIF($C$3:$AE$3,AL$3,$C18:$AE18) -> 10614524
A19: Subscriptions -- Trip Pass | C19: ='Subscription Cohorts'!C35 -> 0 | D19: ='Subscription Cohorts'!D35 -> 0 | E19: ='Subscription Cohorts'!E35 -> 0 | F19: ='Subscription Cohorts'!F35 -> 0 | G19: ='Subscription Cohorts'!G35 -> 0 | H19: ='Subscription Cohorts'!H35 -> 0 | I19: ='Subscription Cohorts'!I35 -> 0 | J19: ='Subscription Cohorts'!J35 -> 0 | ... AE19: ='Subscription Cohorts'!AE35 -> 1732483.9 | AG19: =SUMIF($C$3:$AE$3,AG$3,$C19:$AE19) -> 0 | AH19: =SUMIF($C$3:$AE$3,AH$3,$C19:$AE19) -> 0 | AI19: =SUMIF($C$3:$AE$3,AI$3,$C19:$AE19) -> 35092.829 | AJ19: =SUMIF($C$3:$AE$3,AJ$3,$C19:$AE19) -> 246151.38 | AK19: =SUMIF($C$3:$AE$3,AK$3,$C19:$AE19) -> 761519.08 | AL19: =SUMIF($C$3:$AE$3,AL$3,$C19:$AE19) -> 1732483.9
A20: Accessories (LORE Kit) | C20: ='Pricing & Mix'!C42*acc_attach*acc_aov*sc_price -> 0 | D20: ='Pricing & Mix'!D42*acc_attach*acc_aov*sc_price -> 0 | E20: ='Pricing & Mix'!E42*acc_attach*acc_aov*sc_price -> 0 | F20: ='Pricing & Mix'!F42*acc_attach*acc_aov*sc_price -> 0 | G20: ='Pricing & Mix'!G42*acc_attach*acc_aov*sc_price -> 0 | H20: ='Pricing & Mix'!H42*acc_attach*acc_aov*sc_price -> 0 | I20: ='Pricing & Mix'!I42*acc_attach*acc_aov*sc_price -> 0 | J20: ='Pricing & Mix'!J42*acc_attach*acc_aov*sc_price -> 0 | ... AE20: ='Pricing & Mix'!AE42*acc_attach*acc_aov*sc_price -> 5400000 | AG20: =SUMIF($C$3:$AE$3,AG$3,$C20:$AE20) -> 0 | AH20: =SUMIF($C$3:$AE$3,AH$3,$C20:$AE20) -> 49916.25 | AI20: =SUMIF($C$3:$AE$3,AI$3,$C20:$AE20) -> 529908.75 | AJ20: =SUMIF($C$3:$AE$3,AJ$3,$C20:$AE20) -> 1620000 | AK20: =SUMIF($C$3:$AE$3,AK$3,$C20:$AE20) -> 3375000 | AL20: =SUMIF($C$3:$AE$3,AL$3,$C20:$AE20) -> 5400000
A21: Affiliate bookings (hotels, tours, restaurants) | C21: ='Subscription Cohorts'!C31*Assumptions!C112 -> 0 | D21: ='Subscription Cohorts'!D31*Assumptions!D112 -> 0 | E21: ='Subscription Cohorts'!E31*Assumptions!E112 -> 0 | F21: ='Subscription Cohorts'!F31*Assumptions!F112 -> 0 | G21: ='Subscription Cohorts'!G31*Assumptions!G112 -> 0 | H21: ='Subscription Cohorts'!H31*Assumptions!H112 -> 0 | I21: ='Subscription Cohorts'!I31*Assumptions!I112 -> 0 | J21: ='Subscription Cohorts'!J31*Assumptions!J112 -> 0 | ... AE21: ='Subscription Cohorts'!AE31*Assumptions!AE112 -> 3430021.2 | AG21: =SUMIF($C$3:$AE$3,AG$3,$C21:$AE21) -> 0 | AH21: =SUMIF($C$3:$AE$3,AH$3,$C21:$AE21) -> 1185.75 | AI21: =SUMIF($C$3:$AE$3,AI$3,$C21:$AE21) -> 62065.291 | AJ21: =SUMIF($C$3:$AE$3,AJ$3,$C21:$AE21) -> 425922.73 | AK21: =SUMIF($C$3:$AE$3,AK$3,$C21:$AE21) -> 1413471 | AL21: =SUMIF($C$3:$AE$3,AL$3,$C21:$AE21) -> 3430021.2
A22: B2B fleet devices -- average deployed | B22: devices | C22: =(Assumptions!C110+0)/2 -> 0 | D22: =(Assumptions!D110+Assumptions!C110)/2 -> 0 | E22: =(Assumptions!E110+Assumptions!D110)/2 -> 0 | F22: =(Assumptions!F110+Assumptions!E110)/2 -> 0 | G22: =(Assumptions!G110+Assumptions!F110)/2 -> 0 | H22: =(Assumptions!H110+Assumptions!G110)/2 -> 0 | I22: =(Assumptions!I110+Assumptions!H110)/2 -> 0 | J22: =(Assumptions!J110+Assumptions!I110)/2 -> 0 | K22: =(Assumptions!K110+Assumptions!J110)/2 -> 0 | ... AE22: =(Assumptions!AE110+Assumptions!AD110)/2 -> 8500 | AG22: =SUMIF($C$3:$AE$3,AG$3,$C22:$AE22)/COUNTIF($C$3:$AE$3,AG$3) -> 0 | AH22: =SUMIF($C$3:$AE$3,AH$3,$C22:$AE22)/COUNTIF($C$3:$AE$3,AH$3) -> 0 | AI22: =SUMIF($C$3:$AE$3,AI$3,$C22:$AE22)/COUNTIF($C$3:$AE$3,AI$3) -> 187.5 | AJ22: =SUMIF($C$3:$AE$3,AJ$3,$C22:$AE22)/COUNTIF($C$3:$AE$3,AJ$3) -> 1550 | AK22: =SUMIF($C$3:$AE$3,AK$3,$C22:$AE22)/COUNTIF($C$3:$AE$3,AK$3) -> 4250 | AL22: =SUMIF($C$3:$AE$3,AL$3,$C22:$AE22)/COUNTIF($C$3:$AE$3,AL$3) -> 8500
A23: B2B fleet rental | C23: ='Revenue Build'!C22*fleet_fee*Timeline!C4 -> 0 | D23: ='Revenue Build'!D22*fleet_fee*Timeline!D4 -> 0 | E23: ='Revenue Build'!E22*fleet_fee*Timeline!E4 -> 0 | F23: ='Revenue Build'!F22*fleet_fee*Timeline!F4 -> 0 | G23: ='Revenue Build'!G22*fleet_fee*Timeline!G4 -> 0 | H23: ='Revenue Build'!H22*fleet_fee*Timeline!H4 -> 0 | I23: ='Revenue Build'!I22*fleet_fee*Timeline!I4 -> 0 | J23: ='Revenue Build'!J22*fleet_fee*Timeline!J4 -> 0 | ... AE23: ='Revenue Build'!AE22*fleet_fee*Timeline!AE4 -> 2244000 | AG23: =SUMIF($C$3:$AE$3,AG$3,$C23:$AE23) -> 0 | AH23: =SUMIF($C$3:$AE$3,AH$3,$C23:$AE23) -> 0 | AI23: =SUMIF($C$3:$AE$3,AI$3,$C23:$AE23) -> 49500 | AJ23: =SUMIF($C$3:$AE$3,AJ$3,$C23:$AE23) -> 409200 | AK23: =SUMIF($C$3:$AE$3,AK$3,$C23:$AE23) -> 1122000 | AL23: =SUMIF($C$3:$AE$3,AL$3,$C23:$AE23) -> 2244000
A24: TOTAL REVENUE | C24: ='Revenue Build'!C15+'Revenue Build'!C18+'Revenue Build'!C19+'Revenue Build'!C20+'Revenue Build'!C21+'Revenue Build'!C23 -> 0 | D24: ='Revenue Build'!D15+'Revenue Build'!D18+'Revenue Build'!D19+'Revenue Build'!D20+'Revenue Build'!D21+'Revenue Build'!D23 -> 0 | E24: ='Revenue Build'!E15+'Revenue Build'!E18+'Revenue Build'!E19+'Revenue Build'!E20+'Revenue Build'!E21+'Revenue Build'!E23 -> 0 | F24: ='Revenue Build'!F15+'Revenue Build'!F18+'Revenue Build'!F19+'Revenue Build'!F20+'Revenue Build'!F21+'Revenue Build'!F23 -> 0 | G24: ='Revenue Build'!G15+'Revenue Build'!G18+'Revenue Build'!G19+'Revenue Build'!G20+'Revenue Build'!G21+'Revenue Build'!G23 -> 0 | H24: ='Revenue Build'!H15+'Revenue Build'!H18+'Revenue Build'!H19+'Revenue Build'!H20+'Revenue Build'!H21+'Revenue Build'!H23 -> 0 | I24: ='Revenue Build'!I15+'Revenue Build'!I18+'Revenue Build'!I19+'Revenue Build'!I20+'Revenue Build'!I21+'Revenue Build'!I23 -> 0 | J24: ='Revenue Build'!J15+'Revenue Build'!J18+'Revenue Build'!J19+'Revenue Build'!J20+'Revenue Build'!J21+'Revenue Build'!J23 -> 0 | ... AE24: ='Revenue Build'!AE15+'Revenue Build'!AE18+'Revenue Build'!AE19+'Revenue Build'!AE20+'Revenue Build'!AE21+'Revenue Build'!AE23 -> 1.1133476e+08 | AG24: =SUMIF($C$3:$AE$3,AG$3,$C24:$AE24) -> 0 | AH24: =SUMIF($C$3:$AE$3,AH$3,$C24:$AE24) -> 656496.72 | AI24: =SUMIF($C$3:$AE$3,AI$3,$C24:$AE24) -> 10020674 | AJ24: =SUMIF($C$3:$AE$3,AJ$3,$C24:$AE24) -> 31635040 | AK24: =SUMIF($C$3:$AE$3,AK$3,$C24:$AE24) -> 67070783 | AL24: =SUMIF($C$3:$AE$3,AL$3,$C24:$AE24) -> 1.1133476e+08
A25: Recurring revenue (subs + trip + fleet) | C25: ='Revenue Build'!C18+'Revenue Build'!C19+'Revenue Build'!C23 -> 0 | D25: ='Revenue Build'!D18+'Revenue Build'!D19+'Revenue Build'!D23 -> 0 | E25: ='Revenue Build'!E18+'Revenue Build'!E19+'Revenue Build'!E23 -> 0 | F25: ='Revenue Build'!F18+'Revenue Build'!F19+'Revenue Build'!F23 -> 0 | G25: ='Revenue Build'!G18+'Revenue Build'!G19+'Revenue Build'!G23 -> 0 | H25: ='Revenue Build'!H18+'Revenue Build'!H19+'Revenue Build'!H23 -> 0 | I25: ='Revenue Build'!I18+'Revenue Build'!I19+'Revenue Build'!I23 -> 0 | J25: ='Revenue Build'!J18+'Revenue Build'!J19+'Revenue Build'!J23 -> 0 | ... AE25: ='Revenue Build'!AE18+'Revenue Build'!AE19+'Revenue Build'!AE23 -> 14591008 | AG25: =SUMIF($C$3:$AE$3,AG$3,$C25:$AE25) -> 0 | AH25: =SUMIF($C$3:$AE$3,AH$3,$C25:$AE25) -> 0 | AI25: =SUMIF($C$3:$AE$3,AI$3,$C25:$AE25) -> 411993.03 | AJ25: =SUMIF($C$3:$AE$3,AJ$3,$C25:$AE25) -> 2705354.2 | AK25: =SUMIF($C$3:$AE$3,AK$3,$C25:$AE25) -> 7336231.9 | AL25: =SUMIF($C$3:$AE$3,AL$3,$C25:$AE25) -> 14591008
A26: Recurring share of revenue | B26: % | C26: =IF('Revenue Build'!C24>0,'Revenue Build'!C25/'Revenue Build'!C24,0) -> 0 | D26: =IF('Revenue Build'!D24>0,'Revenue Build'!D25/'Revenue Build'!D24,0) -> 0 | E26: =IF('Revenue Build'!E24>0,'Revenue Build'!E25/'Revenue Build'!E24,0) -> 0 | F26: =IF('Revenue Build'!F24>0,'Revenue Build'!F25/'Revenue Build'!F24,0) -> 0 | G26: =IF('Revenue Build'!G24>0,'Revenue Build'!G25/'Revenue Build'!G24,0) -> 0 | H26: =IF('Revenue Build'!H24>0,'Revenue Build'!H25/'Revenue Build'!H24,0) -> 0 | I26: =IF('Revenue Build'!I24>0,'Revenue Build'!I25/'Revenue Build'!I24,0) -> 0 | J26: =IF('Revenue Build'!J24>0,'Revenue Build'!J25/'Revenue Build'!J24,0) -> 0 | ... AE26: =IF('Revenue Build'!AE24>0,'Revenue Build'!AE25/'Revenue Build'!AE24,0) -> 0.13105528 | AG26: =IF(AG24>0,AG25/AG24,0) -> 0 | AH26: =IF(AH24>0,AH25/AH24,0) -> 0 | AI26: =IF(AI24>0,AI25/AI24,0) -> 0.041114302 | AJ26: =IF(AJ24>0,AJ25/AJ24,0) -> 0.085517647 | AK26: =IF(AK24>0,AK25/AK24,0) -> 0.10938044 | AL26: =IF(AL24>0,AL25/AL24,0) -> 0.13105528

Sheet Hardware COGS
A1: Hardware & accessory COGS (landed) + fulfilment
A2: Period | C2: =Timeline!C2 -> Nov-26 | D2: =Timeline!D2 -> Dec-26 | E2: =Timeline!E2 -> Jan-27 | F2: =Timeline!F2 -> Feb-27 | G2: =Timeline!G2 -> Mar-27 | H2: =Timeline!H2 -> Apr-27 | I2: =Timeline!I2 -> May-27 | J2: =Timeline!J2 -> Jun-27 | ... AE2: =Timeline!AE2 -> FY2031 | AG2: FY2026 (Nov-Dec) | AH2: FY2027 | AI2: FY2028 | AJ2: FY2029 | AK2: FY2030 | AL2: FY2031
A3: Year | C3: =Timeline!C3 -> 2026 | D3: =Timeline!D3 -> 2026 | E3: =Timeline!E3 -> 2027 | F3: =Timeline!F3 -> 2027 | G3: =Timeline!G3 -> 2027 | H3: =Timeline!H3 -> 2027 | I3: =Timeline!I3 -> 2027 | J3: =Timeline!J3 -> 2027 | ... AE3: =Timeline!AE3 -> 2031 | AG3: 2026 | AH3: 2027 | AI3: 2028 | AJ3: 2029 | AK3: 2030 | AL3: 2031
A4: Months in period | C4: =Timeline!C4 -> 1 | D4: =Timeline!D4 -> 1 | E4: =Timeline!E4 -> 1 | F4: =Timeline!F4 -> 1 | G4: =Timeline!G4 -> 1 | H4: =Timeline!H4 -> 1 | I4: =Timeline!I4 -> 1 | J4: =Timeline!J4 -> 1 | ... AE4: =Timeline!AE4 -> 12
A5: Period start | C5: =Timeline!C5 -> 46327 | D5: =Timeline!D5 -> 46357 | E5: =Timeline!E5 -> 46388 | F5: =Timeline!F5 -> 46419 | G5: =Timeline!G5 -> 46447 | H5: =Timeline!H5 -> 46478 | I5: =Timeline!I5 -> 46508 | J5: =Timeline!J5 -> 46539 | ... AE5: =Timeline!AE5 -> 47849
A6: Period key | C6: =Timeline!C6 -> 202611 | D6: =Timeline!D6 -> 202612 | E6: =Timeline!E6 -> 202701 | F6: =Timeline!F6 -> 202702 | G6: =Timeline!G6 -> 202703 | H6: =Timeline!H6 -> 202704 | I6: =Timeline!I6 -> 202705 | J6: =Timeline!J6 -> 202706 | ... AE6: =Timeline!AE6 -> 2031
A8: Landed cost per unit -- Pebble | B8: $ | C8: =(bom_peb+asm_peb+pkg_peb)*(1+freight_duty)*Assumptions!C111*sc_cogs -> 62.6503 | D8: =(bom_peb+asm_peb+pkg_peb)*(1+freight_duty)*Assumptions!D111*sc_cogs -> 62.6503 | E8: =(bom_peb+asm_peb+pkg_peb)*(1+freight_duty)*Assumptions!E111*sc_cogs -> 62.6503 | F8: =(bom_peb+asm_peb+pkg_peb)*(1+freight_duty)*Assumptions!F111*sc_cogs -> 62.6503 | G8: =(bom_peb+asm_peb+pkg_peb)*(1+freight_duty)*Assumptions!G111*sc_cogs -> 62.6503 | H8: =(bom_peb+asm_peb+pkg_peb)*(1+freight_duty)*Assumptions!H111*sc_cogs -> 62.6503 | I8: =(bom_peb+asm_peb+pkg_peb)*(1+freight_duty)*Assumptions!I111*sc_cogs -> 62.6503 | J8: =(bom_peb+asm_peb+pkg_peb)*(1+freight_duty)*Assumptions!J111*sc_cogs -> 62.6503 | ... AE8: =(bom_peb+asm_peb+pkg_peb)*(1+freight_duty)*Assumptions!AE111*sc_cogs -> 49.493737
A9: Landed cost per unit -- Square | B9: $ | C9: =(bom_sq+asm_sq+pkg_sq)*(1+freight_duty)*Assumptions!C111*sc_cogs -> 227.1591 | D9: =(bom_sq+asm_sq+pkg_sq)*(1+freight_duty)*Assumptions!D111*sc_cogs -> 227.1591 | E9: =(bom_sq+asm_sq+pkg_sq)*(1+freight_duty)*Assumptions!E111*sc_cogs -> 227.1591 | F9: =(bom_sq+asm_sq+pkg_sq)*(1+freight_duty)*Assumptions!F111*sc_cogs -> 227.1591 | G9: =(bom_sq+asm_sq+pkg_sq)*(1+freight_duty)*Assumptions!G111*sc_cogs -> 227.1591 | H9: =(bom_sq+asm_sq+pkg_sq)*(1+freight_duty)*Assumptions!H111*sc_cogs -> 227.1591 | I9: =(bom_sq+asm_sq+pkg_sq)*(1+freight_duty)*Assumptions!I111*sc_cogs -> 227.1591 | J9: =(bom_sq+asm_sq+pkg_sq)*(1+freight_duty)*Assumptions!J111*sc_cogs -> 227.1591 | ... AE9: =(bom_sq+asm_sq+pkg_sq)*(1+freight_duty)*Assumptions!AE111*sc_cogs -> 179.45569
A10: Landed cost per unit -- Atlas | B10: $ | C10: =(bom_atl+asm_atl+pkg_atl)*(1+freight_duty)*Assumptions!C111*sc_cogs -> 317.3925 | D10: =(bom_atl+asm_atl+pkg_atl)*(1+freight_duty)*Assumptions!D111*sc_cogs -> 317.3925 | E10: =(bom_atl+asm_atl+pkg_atl)*(1+freight_duty)*Assumptions!E111*sc_cogs -> 317.3925 | F10: =(bom_atl+asm_atl+pkg_atl)*(1+freight_duty)*Assumptions!F111*sc_cogs -> 317.3925 | G10: =(bom_atl+asm_atl+pkg_atl)*(1+freight_duty)*Assumptions!G111*sc_cogs -> 317.3925 | H10: =(bom_atl+asm_atl+pkg_atl)*(1+freight_duty)*Assumptions!H111*sc_cogs -> 317.3925 | I10: =(bom_atl+asm_atl+pkg_atl)*(1+freight_duty)*Assumptions!I111*sc_cogs -> 317.3925 | J10: =(bom_atl+asm_atl+pkg_atl)*(1+freight_duty)*Assumptions!J111*sc_cogs -> 317.3925 | ... AE10: =(bom_atl+asm_atl+pkg_atl)*(1+freight_duty)*Assumptions!AE111*sc_cogs -> 250.74007
A11: Product landed cost (units x landed) | C11: ='Pricing & Mix'!C39*'Hardware COGS'!C8+'Pricing & Mix'!C40*'Hardware COGS'!C9+'Pricing & Mix'!C41*'Hardware COGS'!C10 -> 0 | D11: ='Pricing & Mix'!D39*'Hardware COGS'!D8+'Pricing & Mix'!D40*'Hardware COGS'!D9+'Pricing & Mix'!D41*'Hardware COGS'!D10 -> 0 | E11: ='Pricing & Mix'!E39*'Hardware COGS'!E8+'Pricing & Mix'!E40*'Hardware COGS'!E9+'Pricing & Mix'!E41*'Hardware COGS'!E10 -> 0 | F11: ='Pricing & Mix'!F39*'Hardware COGS'!F8+'Pricing & Mix'!F40*'Hardware COGS'!F9+'Pricing & Mix'!F41*'Hardware COGS'!F10 -> 0 | G11: ='Pricing & Mix'!G39*'Hardware COGS'!G8+'Pricing & Mix'!G40*'Hardware COGS'!G9+'Pricing & Mix'!G41*'Hardware COGS'!G10 -> 0 | H11: ='Pricing & Mix'!H39*'Hardware COGS'!H8+'Pricing & Mix'!H40*'Hardware COGS'!H9+'Pricing & Mix'!H41*'Hardware COGS'!H10 -> 0 | I11: ='Pricing & Mix'!I39*'Hardware COGS'!I8+'Pricing & Mix'!I40*'Hardware COGS'!I9+'Pricing & Mix'!I41*'Hardware COGS'!I10 -> 0 | J11: ='Pricing & Mix'!J39*'Hardware COGS'!J8+'Pricing & Mix'!J40*'Hardware COGS'!J9+'Pricing & Mix'!J41*'Hardware COGS'!J10 -> 0 | ... AE11: ='Pricing & Mix'!AE39*'Hardware COGS'!AE8+'Pricing & Mix'!AE40*'Hardware COGS'!AE9+'Pricing & Mix'!AE41*'Hardware COGS'!AE10 -> 52666187 | AG11: =SUMIF($C$3:$AE$3,AG$3,$C11:$AE11) -> 0 | AH11: =SUMIF($C$3:$AE$3,AH$3,$C11:$AE11) -> 517894.8 | AI11: =SUMIF($C$3:$AE$3,AI$3,$C11:$AE11) -> 6307335.3 | AJ11: =SUMIF($C$3:$AE$3,AJ$3,$C11:$AE11) -> 17799838 | AK11: =SUMIF($C$3:$AE$3,AK$3,$C11:$AE11) -> 34166356 | AL11: =SUMIF($C$3:$AE$3,AL$3,$C11:$AE11) -> 52666187
A12: Fulfilment & outbound logistics | C12: ='Pricing & Mix'!C43*dtc_ship+'Pricing & Mix'!C44*retail_dist+'Pricing & Mix'!C38*ks_fulfil_net -> 0 | D12: ='Pricing & Mix'!D43*dtc_ship+'Pricing & Mix'!D44*retail_dist+'Pricing & Mix'!D38*ks_fulfil_net -> 0 | E12: ='Pricing & Mix'!E43*dtc_ship+'Pricing & Mix'!E44*retail_dist+'Pricing & Mix'!E38*ks_fulfil_net -> 0 | F12: ='Pricing & Mix'!F43*dtc_ship+'Pricing & Mix'!F44*retail_dist+'Pricing & Mix'!F38*ks_fulfil_net -> 0 | G12: ='Pricing & Mix'!G43*dtc_ship+'Pricing & Mix'!G44*retail_dist+'Pricing & Mix'!G38*ks_fulfil_net -> 0 | H12: ='Pricing & Mix'!H43*dtc_ship+'Pricing & Mix'!H44*retail_dist+'Pricing & Mix'!H38*ks_fulfil_net -> 0 | I12: ='Pricing & Mix'!I43*dtc_ship+'Pricing & Mix'!I44*retail_dist+'Pricing & Mix'!I38*ks_fulfil_net -> 0 | J12: ='Pricing & Mix'!J43*dtc_ship+'Pricing & Mix'!J44*retail_dist+'Pricing & Mix'!J38*ks_fulfil_net -> 0 | ... AE12: ='Pricing & Mix'!AE43*dtc_ship+'Pricing & Mix'!AE44*retail_dist+'Pricing & Mix'!AE38*ks_fulfil_net -> 3420000 | AG12: =SUMIF($C$3:$AE$3,AG$3,$C12:$AE12) -> 0 | AH12: =SUMIF($C$3:$AE$3,AH$3,$C12:$AE12) -> 22185 | AI12: =SUMIF($C$3:$AE$3,AI$3,$C12:$AE12) -> 371032.5 | AJ12: =SUMIF($C$3:$AE$3,AJ$3,$C12:$AE12) -> 1068000 | AK12: =SUMIF($C$3:$AE$3,AK$3,$C12:$AE12) -> 2137500 | AL12: =SUMIF($C$3:$AE$3,AL$3,$C12:$AE12) -> 3420000
A13: DTC card processing | C13: ='Revenue Build'!C10*pay_pct+'Pricing & Mix'!C43*pay_fixed -> 0 | D13: ='Revenue Build'!D10*pay_pct+'Pricing & Mix'!D43*pay_fixed -> 0 | E13: ='Revenue Build'!E10*pay_pct+'Pricing & Mix'!E43*pay_fixed -> 0 | F13: ='Revenue Build'!F10*pay_pct+'Pricing & Mix'!F43*pay_fixed -> 0 | G13: ='Revenue Build'!G10*pay_pct+'Pricing & Mix'!G43*pay_fixed -> 0 | H13: ='Revenue Build'!H10*pay_pct+'Pricing & Mix'!H43*pay_fixed -> 0 | I13: ='Revenue Build'!I10*pay_pct+'Pricing & Mix'!I43*pay_fixed -> 0 | J13: ='Revenue Build'!J10*pay_pct+'Pricing & Mix'!J43*pay_fixed -> 0 | ... AE13: ='Revenue Build'!AE10*pay_pct+'Pricing & Mix'!AE43*pay_fixed -> 2037721.4 | AG13: =SUMIF($C$3:$AE$3,AG$3,$C13:$AE13) -> 0 | AH13: =SUMIF($C$3:$AE$3,AH$3,$C13:$AE13) -> 0 | AI13: =SUMIF($C$3:$AE$3,AI$3,$C13:$AE13) -> 230765.41 | AJ13: =SUMIF($C$3:$AE$3,AJ$3,$C13:$AE13) -> 658340.76 | AK13: =SUMIF($C$3:$AE$3,AK$3,$C13:$AE13) -> 1273575.9 | AL13: =SUMIF($C$3:$AE$3,AL$3,$C13:$AE13) -> 2037721.4
A14: Warranty reserve | C14: ='Revenue Build'!C13*warranty_pct -> 0 | D14: ='Revenue Build'!D13*warranty_pct -> 0 | E14: ='Revenue Build'!E13*warranty_pct -> 0 | F14: ='Revenue Build'!F13*warranty_pct -> 0 | G14: ='Revenue Build'!G13*warranty_pct -> 0 | H14: ='Revenue Build'!H13*warranty_pct -> 0 | I14: ='Revenue Build'!I13*warranty_pct -> 0 | J14: ='Revenue Build'!J13*warranty_pct -> 0 | ... AE14: ='Revenue Build'!AE13*warranty_pct -> 1831536 | AG14: =SUMIF($C$3:$AE$3,AG$3,$C14:$AE14) -> 0 | AH14: =SUMIF($C$3:$AE$3,AH$3,$C14:$AE14) -> 12612.39 | AI14: =SUMIF($C$3:$AE$3,AI$3,$C14:$AE14) -> 187848.06 | AJ14: =SUMIF($C$3:$AE$3,AJ$3,$C14:$AE14) -> 560078.4 | AK14: =SUMIF($C$3:$AE$3,AK$3,$C14:$AE14) -> 1144710 | AL14: =SUMIF($C$3:$AE$3,AL$3,$C14:$AE14) -> 1831536
A15: HARDWARE COGS | C15: ='Hardware COGS'!C11+'Hardware COGS'!C12+'Hardware COGS'!C13+'Hardware COGS'!C14 -> 0 | D15: ='Hardware COGS'!D11+'Hardware COGS'!D12+'Hardware COGS'!D13+'Hardware COGS'!D14 -> 0 | E15: ='Hardware COGS'!E11+'Hardware COGS'!E12+'Hardware COGS'!E13+'Hardware COGS'!E14 -> 0 | F15: ='Hardware COGS'!F11+'Hardware COGS'!F12+'Hardware COGS'!F13+'Hardware COGS'!F14 -> 0 | G15: ='Hardware COGS'!G11+'Hardware COGS'!G12+'Hardware COGS'!G13+'Hardware COGS'!G14 -> 0 | H15: ='Hardware COGS'!H11+'Hardware COGS'!H12+'Hardware COGS'!H13+'Hardware COGS'!H14 -> 0 | I15: ='Hardware COGS'!I11+'Hardware COGS'!I12+'Hardware COGS'!I13+'Hardware COGS'!I14 -> 0 | J15: ='Hardware COGS'!J11+'Hardware COGS'!J12+'Hardware COGS'!J13+'Hardware COGS'!J14 -> 0 | ... AE15: ='Hardware COGS'!AE11+'Hardware COGS'!AE12+'Hardware COGS'!AE13+'Hardware COGS'!AE14 -> 59955445 | AG15: =SUMIF($C$3:$AE$3,AG$3,$C15:$AE15) -> 0 | AH15: =SUMIF($C$3:$AE$3,AH$3,$C15:$AE15) -> 552692.19 | AI15: =SUMIF($C$3:$AE$3,AI$3,$C15:$AE15) -> 7096981.3 | AJ15: =SUMIF($C$3:$AE$3,AJ$3,$C15:$AE15) -> 20086257 | AK15: =SUMIF($C$3:$AE$3,AK$3,$C15:$AE15) -> 38722142 | AL15: =SUMIF($C$3:$AE$3,AL$3,$C15:$AE15) -> 59955445
A16: Accessories COGS | C16: ='Revenue Build'!C20*acc_cogs_pct -> 0 | D16: ='Revenue Build'!D20*acc_cogs_pct -> 0 | E16: ='Revenue Build'!E20*acc_cogs_pct -> 0 | F16: ='Revenue Build'!F20*acc_cogs_pct -> 0 | G16: ='Revenue Build'!G20*acc_cogs_pct -> 0 | H16: ='Revenue Build'!H20*acc_cogs_pct -> 0 | I16: ='Revenue Build'!I20*acc_cogs_pct -> 0 | J16: ='Revenue Build'!J20*acc_cogs_pct -> 0 | ... AE16: ='Revenue Build'!AE20*acc_cogs_pct -> 2052000 | AG16: =SUMIF($C$3:$AE$3,AG$3,$C16:$AE16) -> 0 | AH16: =SUMIF($C$3:$AE$3,AH$3,$C16:$AE16) -> 18968.175 | AI16: =SUMIF($C$3:$AE$3,AI$3,$C16:$AE16) -> 201365.33 | AJ16: =SUMIF($C$3:$AE$3,AJ$3,$C16:$AE16) -> 615600 | AK16: =SUMIF($C$3:$AE$3,AK$3,$C16:$AE16) -> 1282500 | AL16: =SUMIF($C$3:$AE$3,AL$3,$C16:$AE16) -> 2052000
A17: Hardware gross margin % | B17: % | C17: =IF('Revenue Build'!C15>0,1-'Hardware COGS'!C15/'Revenue Build'!C15,0) -> 0 | D17: =IF('Revenue Build'!D15>0,1-'Hardware COGS'!D15/'Revenue Build'!D15,0) -> 0 | E17: =IF('Revenue Build'!E15>0,1-'Hardware COGS'!E15/'Revenue Build'!E15,0) -> 0 | F17: =IF('Revenue Build'!F15>0,1-'Hardware COGS'!F15/'Revenue Build'!F15,0) -> 0 | G17: =IF('Revenue Build'!G15>0,1-'Hardware COGS'!G15/'Revenue Build'!G15,0) -> 0 | H17: =IF('Revenue Build'!H15>0,1-'Hardware COGS'!H15/'Revenue Build'!H15,0) -> 0 | I17: =IF('Revenue Build'!I15>0,1-'Hardware COGS'!I15/'Revenue Build'!I15,0) -> 0 | J17: =IF('Revenue Build'!J15>0,1-'Hardware COGS'!J15/'Revenue Build'!J15,0) -> 0 | ... AE17: =IF('Revenue Build'!AE15>0,1-'Hardware COGS'!AE15/'Revenue Build'!AE15,0) -> 0.31801954 | AG17: =IF('Revenue Build'!AG15>0,1-AG15/'Revenue Build'!AG15,0) -> 0 | AH17: =IF('Revenue Build'!AH15>0,1-AH15/'Revenue Build'!AH15,0) -> 0.087054829 | AI17: =IF('Revenue Build'!AI15>0,1-AI15/'Revenue Build'!AI15,0) -> 0.21290764 | AJ17: =IF('Revenue Build'!AJ15>0,1-AJ15/'Revenue Build'!AJ15,0) -> 0.25284801 | AK17: =IF('Revenue Build'!AK15>0,1-AK15/'Revenue Build'!AK15,0) -> 0.29527017 | AL17: =IF('Revenue Build'!AL15>0,1-AL15/'Revenue Build'!AL15,0) -> 0.31801954

Sheet Cloud & AI COGS
A1: Cloud / AI / data COGS per active user
A2: Period | C2: =Timeline!C2 -> Nov-26 | D2: =Timeline!D2 -> Dec-26 | E2: =Timeline!E2 -> Jan-27 | F2: =Timeline!F2 -> Feb-27 | G2: =Timeline!G2 -> Mar-27 | H2: =Timeline!H2 -> Apr-27 | I2: =Timeline!I2 -> May-27 | J2: =Timeline!J2 -> Jun-27 | ... AE2: =Timeline!AE2 -> FY2031 | AG2: FY2026 (Nov-Dec) | AH2: FY2027 | AI2: FY2028 | AJ2: FY2029 | AK2: FY2030 | AL2: FY2031
A3: Year | C3: =Timeline!C3 -> 2026 | D3: =Timeline!D3 -> 2026 | E3: =Timeline!E3 -> 2027 | F3: =Timeline!F3 -> 2027 | G3: =Timeline!G3 -> 2027 | H3: =Timeline!H3 -> 2027 | I3: =Timeline!I3 -> 2027 | J3: =Timeline!J3 -> 2027 | ... AE3: =Timeline!AE3 -> 2031 | AG3: 2026 | AH3: 2027 | AI3: 2028 | AJ3: 2029 | AK3: 2030 | AL3: 2031
A4: Months in period | C4: =Timeline!C4 -> 1 | D4: =Timeline!D4 -> 1 | E4: =Timeline!E4 -> 1 | F4: =Timeline!F4 -> 1 | G4: =Timeline!G4 -> 1 | H4: =Timeline!H4 -> 1 | I4: =Timeline!I4 -> 1 | J4: =Timeline!J4 -> 1 | ... AE4: =Timeline!AE4 -> 12
A5: Period start | C5: =Timeline!C5 -> 46327 | D5: =Timeline!D5 -> 46357 | E5: =Timeline!E5 -> 46388 | F5: =Timeline!F5 -> 46419 | G5: =Timeline!G5 -> 46447 | H5: =Timeline!H5 -> 46478 | I5: =Timeline!I5 -> 46508 | J5: =Timeline!J5 -> 46539 | ... AE5: =Timeline!AE5 -> 47849
A6: Period key | C6: =Timeline!C6 -> 202611 | D6: =Timeline!D6 -> 202612 | E6: =Timeline!E6 -> 202701 | F6: =Timeline!F6 -> 202702 | G6: =Timeline!G6 -> 202703 | H6: =Timeline!H6 -> 202704 | I6: =Timeline!I6 -> 202705 | J6: =Timeline!J6 -> 202706 | ... AE6: =Timeline!AE6 -> 2031
A8: AI unit-cost index | C8: =1 -> 1 | D8: =1 -> 1 | E8: =1 -> 1 | F8: =1 -> 1 | G8: =1 -> 1 | H8: =1 -> 1 | I8: =1 -> 1 | J8: =1 -> 1 | ... AB8: =1 -> 1 | AC8: =(1-ai_defl)^(2029-2028) -> 0.8 | AD8: =(1-ai_defl)^(2030-2028) -> 0.64 | AE8: =(1-ai_defl)^(2031-2028) -> 0.512
A9: Data unit-cost index | C9: =1 -> 1 | D9: =1 -> 1 | E9: =1 -> 1 | F9: =1 -> 1 | G9: =1 -> 1 | H9: =1 -> 1 | I9: =1 -> 1 | J9: =1 -> 1 | ... AB9: =1 -> 1 | AC9: =(1-data_defl)^(2029-2028) -> 0.92 | AD9: =(1-data_defl)^(2030-2028) -> 0.8464 | AE9: =(1-data_defl)^(2031-2028) -> 0.778688
A10: Cost per paid (or trial) user-month | B10: $ | C10: =(llm_cost+stt_cost+tts_cost)*'Cloud & AI COGS'!C8+infra_cost+data_gb_used*data_cost_gb*'Cloud & AI COGS'!C9*'Subscription Cohorts'!C32 -> 1.9264 | D10: =(llm_cost+stt_cost+tts_cost)*'Cloud & AI COGS'!D8+infra_cost+data_gb_used*data_cost_gb*'Cloud & AI COGS'!D9*'Subscription Cohorts'!D32 -> 1.9264 | E10: =(llm_cost+stt_cost+tts_cost)*'Cloud & AI COGS'!E8+infra_cost+data_gb_used*data_cost_gb*'Cloud & AI COGS'!E9*'Subscription Cohorts'!E32 -> 1.9264 | F10: =(llm_cost+stt_cost+tts_cost)*'Cloud & AI COGS'!F8+infra_cost+data_gb_used*data_cost_gb*'Cloud & AI COGS'!F9*'Subscription Cohorts'!F32 -> 1.9264 | G10: =(llm_cost+stt_cost+tts_cost)*'Cloud & AI COGS'!G8+infra_cost+data_gb_used*data_cost_gb*'Cloud & AI COGS'!G9*'Subscription Cohorts'!G32 -> 1.9264 | H10: =(llm_cost+stt_cost+tts_cost)*'Cloud & AI COGS'!H8+infra_cost+data_gb_used*data_cost_gb*'Cloud & AI COGS'!H9*'Subscription Cohorts'!H32 -> 1.9264 | I10: =(llm_cost+stt_cost+tts_cost)*'Cloud & AI COGS'!I8+infra_cost+data_gb_used*data_cost_gb*'Cloud & AI COGS'!I9*'Subscription Cohorts'!I32 -> 1.9264 | J10: =(llm_cost+stt_cost+tts_cost)*'Cloud & AI COGS'!J8+infra_cost+data_gb_used*data_cost_gb*'Cloud & AI COGS'!J9*'Subscription Cohorts'!J32 -> 1.9264 | ... AE10: =(llm_cost+stt_cost+tts_cost)*'Cloud & AI COGS'!AE8+infra_cost+data_gb_used*data_cost_gb*'Cloud & AI COGS'!AE9*'Subscription Cohorts'!AE32 -> 1.3184718
A11: Cost per Trip Pass | B11: $ | C11: =trip_data_gb*data_cost_gb*'Cloud & AI COGS'!C9+trip_ai*'Cloud & AI COGS'!C8+sub_pay_fee*trip_price*sc_price -> 7.36 | D11: =trip_data_gb*data_cost_gb*'Cloud & AI COGS'!D9+trip_ai*'Cloud & AI COGS'!D8+sub_pay_fee*trip_price*sc_price -> 7.36 | E11: =trip_data_gb*data_cost_gb*'Cloud & AI COGS'!E9+trip_ai*'Cloud & AI COGS'!E8+sub_pay_fee*trip_price*sc_price -> 7.36 | F11: =trip_data_gb*data_cost_gb*'Cloud & AI COGS'!F9+trip_ai*'Cloud & AI COGS'!F8+sub_pay_fee*trip_price*sc_price -> 7.36 | G11: =trip_data_gb*data_cost_gb*'Cloud & AI COGS'!G9+trip_ai*'Cloud & AI COGS'!G8+sub_pay_fee*trip_price*sc_price -> 7.36 | H11: =trip_data_gb*data_cost_gb*'Cloud & AI COGS'!H9+trip_ai*'Cloud & AI COGS'!H8+sub_pay_fee*trip_price*sc_price -> 7.36 | I11: =trip_data_gb*data_cost_gb*'Cloud & AI COGS'!I9+trip_ai*'Cloud & AI COGS'!I8+sub_pay_fee*trip_price*sc_price -> 7.36 | J11: =trip_data_gb*data_cost_gb*'Cloud & AI COGS'!J9+trip_ai*'Cloud & AI COGS'!J8+sub_pay_fee*trip_price*sc_price -> 7.36 | ... AE11: =trip_data_gb*data_cost_gb*'Cloud & AI COGS'!AE9+trip_ai*'Cloud & AI COGS'!AE8+sub_pay_fee*trip_price*sc_price -> 6.084352
A12: Paid subscribers: AI + data + infra | C12: ='Subscription Cohorts'!C21*'Cloud & AI COGS'!C10 -> 0 | D12: ='Subscription Cohorts'!D21*'Cloud & AI COGS'!D10 -> 0 | E12: ='Subscription Cohorts'!E21*'Cloud & AI COGS'!E10 -> 0 | F12: ='Subscription Cohorts'!F21*'Cloud & AI COGS'!F10 -> 0 | G12: ='Subscription Cohorts'!G21*'Cloud & AI COGS'!G10 -> 0 | H12: ='Subscription Cohorts'!H21*'Cloud & AI COGS'!H10 -> 0 | I12: ='Subscription Cohorts'!I21*'Cloud & AI COGS'!I10 -> 0 | J12: ='Subscription Cohorts'!J21*'Cloud & AI COGS'!J10 -> 0 | ... AE12: ='Subscription Cohorts'!AE21*'Cloud & AI COGS'!AE10 -> 1628948.8 | AG12: =SUMIF($C$3:$AE$3,AG$3,$C12:$AE12) -> 0 | AH12: =SUMIF($C$3:$AE$3,AH$3,$C12:$AE12) -> 0 | AI12: =SUMIF($C$3:$AE$3,AI$3,$C12:$AE12) -> 76707.645 | AJ12: =SUMIF($C$3:$AE$3,AJ$3,$C12:$AE12) -> 414400.55 | AK12: =SUMIF($C$3:$AE$3,AK$3,$C12:$AE12) -> 956691.97 | AL12: =SUMIF($C$3:$AE$3,AL$3,$C12:$AE12) -> 1628948.8
A13: Subscription billing fees | C13: ='Subscription Cohorts'!C23*sub_pay_fee -> 0 | D13: ='Subscription Cohorts'!D23*sub_pay_fee -> 0 | E13: ='Subscription Cohorts'!E23*sub_pay_fee -> 0 | F13: ='Subscription Cohorts'!F23*sub_pay_fee -> 0 | G13: ='Subscription Cohorts'!G23*sub_pay_fee -> 0 | H13: ='Subscription Cohorts'!H23*sub_pay_fee -> 0 | I13: ='Subscription Cohorts'!I23*sub_pay_fee -> 0 | J13: ='Subscription Cohorts'!J23*sub_pay_fee -> 0 | ... AE13: ='Subscription Cohorts'!AE23*sub_pay_fee -> 849161.9 | AG13: =SUMIF($C$3:$AE$3,AG$3,$C13:$AE13) -> 0 | AH13: =SUMIF($C$3:$AE$3,AH$3,$C13:$AE13) -> 0 | AI13: =SUMIF($C$3:$AE$3,AI$3,$C13:$AE13) -> 26192.016 | AJ13: =SUMIF($C$3:$AE$3,AJ$3,$C13:$AE13) -> 164000.22 | AK13: =SUMIF($C$3:$AE$3,AK$3,$C13:$AE13) -> 436217.03 | AL13: =SUMIF($C$3:$AE$3,AL$3,$C13:$AE13) -> 849161.9
A14: Trial users (3 free months) | C14: ='Subscription Cohorts'!C27*'Cloud & AI COGS'!C10 -> 0 | D14: ='Subscription Cohorts'!D27*'Cloud & AI COGS'!D10 -> 0 | E14: ='Subscription Cohorts'!E27*'Cloud & AI COGS'!E10 -> 0 | F14: ='Subscription Cohorts'!F27*'Cloud & AI COGS'!F10 -> 0 | G14: ='Subscription Cohorts'!G27*'Cloud & AI COGS'!G10 -> 0 | H14: ='Subscription Cohorts'!H27*'Cloud & AI COGS'!H10 -> 0 | I14: ='Subscription Cohorts'!I27*'Cloud & AI COGS'!I10 -> 0 | J14: ='Subscription Cohorts'!J27*'Cloud & AI COGS'!J10 -> 0 | ... AE14: ='Subscription Cohorts'!AE27*'Cloud & AI COGS'!AE10 -> 1582166.2 | AG14: =SUMIF($C$3:$AE$3,AG$3,$C14:$AE14) -> 0 | AH14: =SUMIF($C$3:$AE$3,AH$3,$C14:$AE14) -> 11216.464 | AI14: =SUMIF($C$3:$AE$3,AI$3,$C14:$AE14) -> 206155.38 | AJ14: =SUMIF($C$3:$AE$3,AJ$3,$C14:$AE14) -> 625219.2 | AK14: =SUMIF($C$3:$AE$3,AK$3,$C14:$AE14) -> 1130536.8 | AL14: =SUMIF($C$3:$AE$3,AL$3,$C14:$AE14) -> 1582166.2
A15: Free-tier devices | C15: ='Subscription Cohorts'!C33*free_cost -> 0 | D15: ='Subscription Cohorts'!D33*free_cost -> 0 | E15: ='Subscription Cohorts'!E33*free_cost -> 0 | F15: ='Subscription Cohorts'!F33*free_cost -> 0 | G15: ='Subscription Cohorts'!G33*free_cost -> 0 | H15: ='Subscription Cohorts'!H33*free_cost -> 0 | I15: ='Subscription Cohorts'!I33*free_cost -> 0 | J15: ='Subscription Cohorts'!J33*free_cost -> 0 | ... AE15: ='Subscription Cohorts'!AE33*free_cost -> 393746.34 | AG15: =SUMIF($C$3:$AE$3,AG$3,$C15:$AE15) -> 0 | AH15: =SUMIF($C$3:$AE$3,AH$3,$C15:$AE15) -> 0 | AI15: =SUMIF($C$3:$AE$3,AI$3,$C15:$AE15) -> 8013.5044 | AJ15: =SUMIF($C$3:$AE$3,AJ$3,$C15:$AE15) -> 55943.495 | AK15: =SUMIF($C$3:$AE$3,AK$3,$C15:$AE15) -> 173072.52 | AL15: =SUMIF($C$3:$AE$3,AL$3,$C15:$AE15) -> 393746.34
A16: Trip Passes | C16: ='Subscription Cohorts'!C34*'Cloud & AI COGS'!C11 -> 0 | D16: ='Subscription Cohorts'!D34*'Cloud & AI COGS'!D11 -> 0 | E16: ='Subscription Cohorts'!E34*'Cloud & AI COGS'!E11 -> 0 | F16: ='Subscription Cohorts'!F34*'Cloud & AI COGS'!F11 -> 0 | G16: ='Subscription Cohorts'!G34*'Cloud & AI COGS'!G11 -> 0 | H16: ='Subscription Cohorts'!H34*'Cloud & AI COGS'!H11 -> 0 | I16: ='Subscription Cohorts'!I34*'Cloud & AI COGS'!I11 -> 0 | J16: ='Subscription Cohorts'!J34*'Cloud & AI COGS'!J11 -> 0 | ... AE16: ='Subscription Cohorts'!AE34*'Cloud & AI COGS'!AE11 -> 329407.56 | AG16: =SUMIF($C$3:$AE$3,AG$3,$C16:$AE16) -> 0 | AH16: =SUMIF($C$3:$AE$3,AH$3,$C16:$AE16) -> 0 | AI16: =SUMIF($C$3:$AE$3,AI$3,$C16:$AE16) -> 8071.3506 | AJ16: =SUMIF($C$3:$AE$3,AJ$3,$C16:$AE16) -> 52922.546 | AK16: =SUMIF($C$3:$AE$3,AK$3,$C16:$AE16) -> 153674.55 | AL16: =SUMIF($C$3:$AE$3,AL$3,$C16:$AE16) -> 329407.56
A17: B2B fleet devices | C17: ='Revenue Build'!C22*fleet_cloud*Timeline!C4 -> 0 | D17: ='Revenue Build'!D22*fleet_cloud*Timeline!D4 -> 0 | E17: ='Revenue Build'!E22*fleet_cloud*Timeline!E4 -> 0 | F17: ='Revenue Build'!F22*fleet_cloud*Timeline!F4 -> 0 | G17: ='Revenue Build'!G22*fleet_cloud*Timeline!G4 -> 0 | H17: ='Revenue Build'!H22*fleet_cloud*Timeline!H4 -> 0 | I17: ='Revenue Build'!I22*fleet_cloud*Timeline!I4 -> 0 | J17: ='Revenue Build'!J22*fleet_cloud*Timeline!J4 -> 0 | ... AE17: ='Revenue Build'!AE22*fleet_cloud*Timeline!AE4 -> 306000 | AG17: =SUMIF($C$3:$AE$3,AG$3,$C17:$AE17) -> 0 | AH17: =SUMIF($C$3:$AE$3,AH$3,$C17:$AE17) -> 0 | AI17: =SUMIF($C$3:$AE$3,AI$3,$C17:$AE17) -> 6750 | AJ17: =SUMIF($C$3:$AE$3,AJ$3,$C17:$AE17) -> 55800 | AK17: =SUMIF($C$3:$AE$3,AK$3,$C17:$AE17) -> 153000 | AL17: =SUMIF($C$3:$AE$3,AL$3,$C17:$AE17) -> 306000
A18: TOTAL CLOUD / AI / DATA COGS | C18: ='Cloud & AI COGS'!C12+'Cloud & AI COGS'!C13+'Cloud & AI COGS'!C14+'Cloud & AI COGS'!C15+'Cloud & AI COGS'!C16+'Cloud & AI COGS'!C17 -> 0 | D18: ='Cloud & AI COGS'!D12+'Cloud & AI COGS'!D13+'Cloud & AI COGS'!D14+'Cloud & AI COGS'!D15+'Cloud & AI COGS'!D16+'Cloud & AI COGS'!D17 -> 0 | E18: ='Cloud & AI COGS'!E12+'Cloud & AI COGS'!E13+'Cloud & AI COGS'!E14+'Cloud & AI COGS'!E15+'Cloud & AI COGS'!E16+'Cloud & AI COGS'!E17 -> 0 | F18: ='Cloud & AI COGS'!F12+'Cloud & AI COGS'!F13+'Cloud & AI COGS'!F14+'Cloud & AI COGS'!F15+'Cloud & AI COGS'!F16+'Cloud & AI COGS'!F17 -> 0 | G18: ='Cloud & AI COGS'!G12+'Cloud & AI COGS'!G13+'Cloud & AI COGS'!G14+'Cloud & AI COGS'!G15+'Cloud & AI COGS'!G16+'Cloud & AI COGS'!G17 -> 0 | H18: ='Cloud & AI COGS'!H12+'Cloud & AI COGS'!H13+'Cloud & AI COGS'!H14+'Cloud & AI COGS'!H15+'Cloud & AI COGS'!H16+'Cloud & AI COGS'!H17 -> 0 | I18: ='Cloud & AI COGS'!I12+'Cloud & AI COGS'!I13+'Cloud & AI COGS'!I14+'Cloud & AI COGS'!I15+'Cloud & AI COGS'!I16+'Cloud & AI COGS'!I17 -> 0 | J18: ='Cloud & AI COGS'!J12+'Cloud & AI COGS'!J13+'Cloud & AI COGS'!J14+'Cloud & AI COGS'!J15+'Cloud & AI COGS'!J16+'Cloud & AI COGS'!J17 -> 0 | ... AE18: ='Cloud & AI COGS'!AE12+'Cloud & AI COGS'!AE13+'Cloud & AI COGS'!AE14+'Cloud & AI COGS'!AE15+'Cloud & AI COGS'!AE16+'Cloud & AI COGS'!AE17 -> 5089430.7 | AG18: =SUMIF($C$3:$AE$3,AG$3,$C18:$AE18) -> 0 | AH18: =SUMIF($C$3:$AE$3,AH$3,$C18:$AE18) -> 11216.464 | AI18: =SUMIF($C$3:$AE$3,AI$3,$C18:$AE18) -> 331889.89 | AJ18: =SUMIF($C$3:$AE$3,AJ$3,$C18:$AE18) -> 1368286 | AK18: =SUMIF($C$3:$AE$3,AK$3,$C18:$AE18) -> 3003192.9 | AL18: =SUMIF($C$3:$AE$3,AL$3,$C18:$AE18) -> 5089430.7
A19: Cloud COGS per active device-month | B19: $ | C19: =IF('Subscription Cohorts'!C31>0,'Cloud & AI COGS'!C18/'Subscription Cohorts'!C31,0) -> 0 | D19: =IF('Subscription Cohorts'!D31>0,'Cloud & AI COGS'!D18/'Subscription Cohorts'!D31,0) -> 0 | E19: =IF('Subscription Cohorts'!E31>0,'Cloud & AI COGS'!E18/'Subscription Cohorts'!E31,0) -> 0 | F19: =IF('Subscription Cohorts'!F31>0,'Cloud & AI COGS'!F18/'Subscription Cohorts'!F31,0) -> 0 | G19: =IF('Subscription Cohorts'!G31>0,'Cloud & AI COGS'!G18/'Subscription Cohorts'!G31,0) -> 0 | H19: =IF('Subscription Cohorts'!H31>0,'Cloud & AI COGS'!H18/'Subscription Cohorts'!H31,0) -> 0 | I19: =IF('Subscription Cohorts'!I31>0,'Cloud & AI COGS'!I18/'Subscription Cohorts'!I31,0) -> 0 | J19: =IF('Subscription Cohorts'!J31>0,'Cloud & AI COGS'!J18/'Subscription Cohorts'!J31,0) -> 0 | ... AE19: =IF('Subscription Cohorts'!AE31>0,'Cloud & AI COGS'!AE18/'Subscription Cohorts'!AE31,0) -> 0.89027394
A20: Subscription gross margin (Explorer + Trip Pass, excl. trial & free) | B20: % | C20: =IF(('Subscription Cohorts'!C23+'Subscription Cohorts'!C35)>0,1-('Cloud & AI COGS'!C12+'Cloud & AI COGS'!C13+'Cloud & AI COGS'!C16)/('Subscription Cohorts'!C23+'Subscription Cohorts'!C35),0) -> 0 | D20: =IF(('Subscription Cohorts'!D23+'Subscription Cohorts'!D35)>0,1-('Cloud & AI COGS'!D12+'Cloud & AI COGS'!D13+'Cloud & AI COGS'!D16)/('Subscription Cohorts'!D23+'Subscription Cohorts'!D35),0) -> 0 | E20: =IF(('Subscription Cohorts'!E23+'Subscription Cohorts'!E35)>0,1-('Cloud & AI COGS'!E12+'Cloud & AI COGS'!E13+'Cloud & AI COGS'!E16)/('Subscription Cohorts'!E23+'Subscription Cohorts'!E35),0) -> 0 | F20: =IF(('Subscription Cohorts'!F23+'Subscription Cohorts'!F35)>0,1-('Cloud & AI COGS'!F12+'Cloud & AI COGS'!F13+'Cloud & AI COGS'!F16)/('Subscription Cohorts'!F23+'Subscription Cohorts'!F35),0) -> 0 | G20: =IF(('Subscription Cohorts'!G23+'Subscription Cohorts'!G35)>0,1-('Cloud & AI COGS'!G12+'Cloud & AI COGS'!G13+'Cloud & AI COGS'!G16)/('Subscription Cohorts'!G23+'Subscription Cohorts'!G35),0) -> 0 | H20: =IF(('Subscription Cohorts'!H23+'Subscription Cohorts'!H35)>0,1-('Cloud & AI COGS'!H12+'Cloud & AI COGS'!H13+'Cloud & AI COGS'!H16)/('Subscription Cohorts'!H23+'Subscription Cohorts'!H35),0) -> 0 | I20: =IF(('Subscription Cohorts'!I23+'Subscription Cohorts'!I35)>0,1-('Cloud & AI COGS'!I12+'Cloud & AI COGS'!I13+'Cloud & AI COGS'!I16)/('Subscription Cohorts'!I23+'Subscription Cohorts'!I35),0) -> 0 | J20: =IF(('Subscription Cohorts'!J23+'Subscription Cohorts'!J35)>0,1-('Cloud & AI COGS'!J12+'Cloud & AI COGS'!J13+'Cloud & AI COGS'!J16)/('Subscription Cohorts'!J23+'Subscription Cohorts'!J35),0) -> 0 | ... AE20: =IF(('Subscription Cohorts'!AE23+'Subscription Cohorts'!AE35)>0,1-('Cloud & AI COGS'!AE12+'Cloud & AI COGS'!AE13+'Cloud & AI COGS'!AE16)/('Subscription Cohorts'!AE23+'Subscription Cohorts'!AE35),0) -> 0.7726155

Sheet Headcount
A1: Headcount plan -- roles, start month, base salary (blue = input). Burden & inflation from Assumptions.
A3: Role | B3: Dept | C3: Count | D3: Start month | E3: Base salary ($/yr) | F3: Note
A4: Founder & CEO (Nimit Jain) | B4: G&A | C4: 1 | D4: 46327 | E4: 90000 | F4: Below-market founder salary until seed.
A5: Founding Eng -- Embedded / firmware | B5: R&D | C5: 1 | D5: 46327 | E5: 150000
A6: Founding Eng -- AI / story engine | B6: R&D | C6: 1 | D6: 46357 | E6: 160000
A7: Founding Eng -- mobile app / backend | B7: R&D | C7: 1 | D7: 46388 | E7: 140000
A8: Hardware lead (systems/EE, ODM mgmt) | B8: R&D | C8: 1 | D8: 46388 | E8: 165000
A9: Community & Kickstarter lead | B9: S&M | C9: 1 | D9: 46419 | E9: 95000
A10: Content editor / historian (City Packs) | B10: R&D | C10: 1 | D10: 46447 | E10: 75000 | F10: Fact-checked stories w/ sources.
A11: Head of operations & supply chain | B11: Ops & CS | C11: 1 | D11: 46600 | E11: 160000 | F11: Seed hire.
A12: Firmware engineer #2 | B12: R&D | C12: 1 | D12: 46600 | E12: 140000
A13: Map Vision / sensor-fusion engineer | B13: R&D | C13: 1 | D13: 46631 | E13: 160000
A14: Product designer (device + app UX) | B14: R&D | C14: 1 | D14: 46631 | E14: 125000
A15: Customer support lead | B15: Ops & CS | C15: 1 | D15: 46661 | E15: 65000
A16: Growth marketing manager | B16: S&M | C16: 1 | D16: 46661 | E16: 120000
A17: Finance & ops manager / controller | B17: G&A | C17: 1 | D17: 46692 | E17: 110000
A18: Backend / cloud engineer | B18: R&D | C18: 1 | D18: 46753 | E18: 150000
A19: Mechanical engineer | B19: R&D | C19: 1 | D19: 46753 | E19: 140000
A20: Content editors | B20: R&D | C20: 2 | D20: 46784 | E20: 70000 | F20: 20 cities in 2028.
A21: Customer support agents | B21: Ops & CS | C21: 2 | D21: 46813 | E21: 50000
A22: Retail & partnerships manager | B22: S&M | C22: 1 | D22: 46813 | E22: 120000
A23: B2B fleet sales lead | B23: S&M | C23: 1 | D23: 46844 | E23: 110000
A24: QA / test engineer | B24: R&D | C24: 1 | D24: 46844 | E24: 115000
A25: ML engineer #2 (on-device models) | B25: R&D | C25: 1 | D25: 46905 | E25: 165000
A26: Brand & content marketer | B26: S&M | C26: 1 | D26: 46905 | E26: 100000
A27: People & office ops | B27: G&A | C27: 1 | D27: 46997 | E27: 85000
A28: VP Engineering | B28: R&D | C28: 1 | D28: 47058 | E28: 210000 | F28: Series A hire.
A29: Customer support agents | B29: Ops & CS | C29: 3 | D29: 47058 | E29: 50000 | F29: Holiday peak.
A30: VP Marketing | B30: S&M | C30: 1 | D30: 47150 | E30: 200000
A31: R&D engineers (Gen-2, platform) | B31: R&D | C31: 8 | D31: 47178 | E31: 155000
A32: Content editors (30 new cities) | B32: R&D | C32: 4 | D32: 47178 | E32: 72000
A33: S&M team (performance, retail, EU/APAC) | B33: S&M | C33: 5 | D33: 47209 | E33: 110000
A34: Ops / supply-chain / quality | B34: Ops & CS | C34: 3 | D34: 47209 | E34: 100000
A35: Customer support agents | B35: Ops & CS | C35: 6 | D35: 47270 | E35: 50000
A36: G&A (finance, legal, people) | B36: G&A | C36: 3 | D36: 47270 | E36: 110000
A37: CFO | B37: G&A | C37: 1 | D37: 47362 | E37: 230000
A38: R&D engineers | B38: R&D | C38: 10 | D38: 47543 | E38: 160000
A39: Content editors | B39: R&D | C39: 4 | D39: 47543 | E39: 75000
A40: S&M team | B40: S&M | C40: 6 | D40: 47543 | E40: 115000
A41: Ops / CS | B41: Ops & CS | C41: 8 | D41: 47604 | E41: 60000
... A46: G&A | B46: G&A | C46: 3 | D46: 47939 | E46: 125000

Sheet Headcount Plan
A1: Headcount & personnel cost by period (formulas from 'Headcount' role table)
A2: Period | C2: =Timeline!C2 -> Nov-26 | D2: =Timeline!D2 -> Dec-26 | E2: =Timeline!E2 -> Jan-27 | F2: =Timeline!F2 -> Feb-27 | G2: =Timeline!G2 -> Mar-27 | H2: =Timeline!H2 -> Apr-27 | I2: =Timeline!I2 -> May-27 | J2: =Timeline!J2 -> Jun-27 | ... AE2: =Timeline!AE2 -> FY2031 | AG2: FY2026 (Nov-Dec) | AH2: FY2027 | AI2: FY2028 | AJ2: FY2029 | AK2: FY2030 | AL2: FY2031
A3: Year | C3: =Timeline!C3 -> 2026 | D3: =Timeline!D3 -> 2026 | E3: =Timeline!E3 -> 2027 | F3: =Timeline!F3 -> 2027 | G3: =Timeline!G3 -> 2027 | H3: =Timeline!H3 -> 2027 | I3: =Timeline!I3 -> 2027 | J3: =Timeline!J3 -> 2027 | ... AE3: =Timeline!AE3 -> 2031 | AG3: 2026 | AH3: 2027 | AI3: 2028 | AJ3: 2029 | AK3: 2030 | AL3: 2031
A4: Months in period | C4: =Timeline!C4 -> 1 | D4: =Timeline!D4 -> 1 | E4: =Timeline!E4 -> 1 | F4: =Timeline!F4 -> 1 | G4: =Timeline!G4 -> 1 | H4: =Timeline!H4 -> 1 | I4: =Timeline!I4 -> 1 | J4: =Timeline!J4 -> 1 | ... AE4: =Timeline!AE4 -> 12
A5: Period start | C5: =Timeline!C5 -> 46327 | D5: =Timeline!D5 -> 46357 | E5: =Timeline!E5 -> 46388 | F5: =Timeline!F5 -> 46419 | G5: =Timeline!G5 -> 46447 | H5: =Timeline!H5 -> 46478 | I5: =Timeline!I5 -> 46508 | J5: =Timeline!J5 -> 46539 | ... AE5: =Timeline!AE5 -> 47849
A6: Period key | C6: =Timeline!C6 -> 202611 | D6: =Timeline!D6 -> 202612 | E6: =Timeline!E6 -> 202701 | F6: =Timeline!F6 -> 202702 | G6: =Timeline!G6 -> 202703 | H6: =Timeline!H6 -> 202704 | I6: =Timeline!I6 -> 202705 | J6: =Timeline!J6 -> 202706 | ... AE6: =Timeline!AE6 -> 2031
A9: End-of-period headcount by role
A10: =Headcount!A4 -> Founder & CEO (Nimit Jain) | B10: =Headcount!B4 -> G&A | C10: =IF(Headcount!$D$4<=Timeline!C5,Headcount!$C$4,0) -> 1 | D10: =IF(Headcount!$D$4<=Timeline!D5,Headcount!$C$4,0) -> 1 | E10: =IF(Headcount!$D$4<=Timeline!E5,Headcount!$C$4,0) -> 1 | F10: =IF(Headcount!$D$4<=Timeline!F5,Headcount!$C$4,0) -> 1 | G10: =IF(Headcount!$D$4<=Timeline!G5,Headcount!$C$4,0) -> 1 | H10: =IF(Headcount!$D$4<=Timeline!H5,Headcount!$C$4,0) -> 1 | I10: =IF(Headcount!$D$4<=Timeline!I5,Headcount!$C$4,0) -> 1 | J10: =IF(Headcount!$D$4<=Timeline!J5,Headcount!$C$4,0) -> 1 | ... AB10: =IF(Headcount!$D$4<=Timeline!AB5,Headcount!$C$4,0) -> 1 | AC10: =IF(Headcount!$D$4<=DATE(2029,12,31),Headcount!$C$4,0) -> 1 | AD10: =IF(Headcount!$D$4<=DATE(2030,12,31),Headcount!$C$4,0) -> 1 | AE10: =IF(Headcount!$D$4<=DATE(2031,12,31),Headcount!$C$4,0) -> 1 | AG10: =D10 -> 1 | AH10: =P10 -> 1 | AI10: =AB10 -> 1 | AJ10: =AC10 -> 1 | AK10: =AD10 -> 1 | AL10: =AE10 -> 1
A11: =Headcount!A5 -> Founding Eng -- Embedded / firmware | B11: =Headcount!B5 -> R&D | C11: =IF(Headcount!$D$5<=Timeline!C5,Headcount!$C$5,0) -> 1 | D11: =IF(Headcount!$D$5<=Timeline!D5,Headcount!$C$5,0) -> 1 | E11: =IF(Headcount!$D$5<=Timeline!E5,Headcount!$C$5,0) -> 1 | F11: =IF(Headcount!$D$5<=Timeline!F5,Headcount!$C$5,0) -> 1 | G11: =IF(Headcount!$D$5<=Timeline!G5,Headcount!$C$5,0) -> 1 | H11: =IF(Headcount!$D$5<=Timeline!H5,Headcount!$C$5,0) -> 1 | I11: =IF(Headcount!$D$5<=Timeline!I5,Headcount!$C$5,0) -> 1 | J11: =IF(Headcount!$D$5<=Timeline!J5,Headcount!$C$5,0) -> 1 | ... AB11: =IF(Headcount!$D$5<=Timeline!AB5,Headcount!$C$5,0) -> 1 | AC11: =IF(Headcount!$D$5<=DATE(2029,12,31),Headcount!$C$5,0) -> 1 | AD11: =IF(Headcount!$D$5<=DATE(2030,12,31),Headcount!$C$5,0) -> 1 | AE11: =IF(Headcount!$D$5<=DATE(2031,12,31),Headcount!$C$5,0) -> 1 | AG11: =D11 -> 1 | AH11: =P11 -> 1 | AI11: =AB11 -> 1 | AJ11: =AC11 -> 1 | AK11: =AD11 -> 1 | AL11: =AE11 -> 1
A12: =Headcount!A6 -> Founding Eng -- AI / story engine | B12: =Headcount!B6 -> R&D | C12: =IF(Headcount!$D$6<=Timeline!C5,Headcount!$C$6,0) -> 0 | D12: =IF(Headcount!$D$6<=Timeline!D5,Headcount!$C$6,0) -> 1 | E12: =IF(Headcount!$D$6<=Timeline!E5,Headcount!$C$6,0) -> 1 | F12: =IF(Headcount!$D$6<=Timeline!F5,Headcount!$C$6,0) -> 1 | G12: =IF(Headcount!$D$6<=Timeline!G5,Headcount!$C$6,0) -> 1 | H12: =IF(Headcount!$D$6<=Timeline!H5,Headcount!$C$6,0) -> 1 | I12: =IF(Headcount!$D$6<=Timeline!I5,Headcount!$C$6,0) -> 1 | J12: =IF(Headcount!$D$6<=Timeline!J5,Headcount!$C$6,0) -> 1 | ... AB12: =IF(Headcount!$D$6<=Timeline!AB5,Headcount!$C$6,0) -> 1 | AC12: =IF(Headcount!$D$6<=DATE(2029,12,31),Headcount!$C$6,0) -> 1 | AD12: =IF(Headcount!$D$6<=DATE(2030,12,31),Headcount!$C$6,0) -> 1 | AE12: =IF(Headcount!$D$6<=DATE(2031,12,31),Headcount!$C$6,0) -> 1 | AG12: =D12 -> 1 | AH12: =P12 -> 1 | AI12: =AB12 -> 1 | AJ12: =AC12 -> 1 | AK12: =AD12 -> 1 | AL12: =AE12 -> 1
A13: =Headcount!A7 -> Founding Eng -- mobile app / backend | B13: =Headcount!B7 -> R&D | C13: =IF(Headcount!$D$7<=Timeline!C5,Headcount!$C$7,0) -> 0 | D13: =IF(Headcount!$D$7<=Timeline!D5,Headcount!$C$7,0) -> 0 | E13: =IF(Headcount!$D$7<=Timeline!E5,Headcount!$C$7,0) -> 1 | F13: =IF(Headcount!$D$7<=Timeline!F5,Headcount!$C$7,0) -> 1 | G13: =IF(Headcount!$D$7<=Timeline!G5,Headcount!$C$7,0) -> 1 | H13: =IF(Headcount!$D$7<=Timeline!H5,Headcount!$C$7,0) -> 1 | I13: =IF(Headcount!$D$7<=Timeline!I5,Headcount!$C$7,0) -> 1 | J13: =IF(Headcount!$D$7<=Timeline!J5,Headcount!$C$7,0) -> 1 | ... AB13: =IF(Headcount!$D$7<=Timeline!AB5,Headcount!$C$7,0) -> 1 | AC13: =IF(Headcount!$D$7<=DATE(2029,12,31),Headcount!$C$7,0) -> 1 | AD13: =IF(Headcount!$D$7<=DATE(2030,12,31),Headcount!$C$7,0) -> 1 | AE13: =IF(Headcount!$D$7<=DATE(2031,12,31),Headcount!$C$7,0) -> 1 | AG13: =D13 -> 0 | AH13: =P13 -> 1 | AI13: =AB13 -> 1 | AJ13: =AC13 -> 1 | AK13: =AD13 -> 1 | AL13: =AE13 -> 1
A14: =Headcount!A8 -> Hardware lead (systems/EE, ODM mgmt) | B14: =Headcount!B8 -> R&D | C14: =IF(Headcount!$D$8<=Timeline!C5,Headcount!$C$8,0) -> 0 | D14: =IF(Headcount!$D$8<=Timeline!D5,Headcount!$C$8,0) -> 0 | E14: =IF(Headcount!$D$8<=Timeline!E5,Headcount!$C$8,0) -> 1 | F14: =IF(Headcount!$D$8<=Timeline!F5,Headcount!$C$8,0) -> 1 | G14: =IF(Headcount!$D$8<=Timeline!G5,Headcount!$C$8,0) -> 1 | H14: =IF(Headcount!$D$8<=Timeline!H5,Headcount!$C$8,0) -> 1 | I14: =IF(Headcount!$D$8<=Timeline!I5,Headcount!$C$8,0) -> 1 | J14: =IF(Headcount!$D$8<=Timeline!J5,Headcount!$C$8,0) -> 1 | ... AB14: =IF(Headcount!$D$8<=Timeline!AB5,Headcount!$C$8,0) -> 1 | AC14: =IF(Headcount!$D$8<=DATE(2029,12,31),Headcount!$C$8,0) -> 1 | AD14: =IF(Headcount!$D$8<=DATE(2030,12,31),Headcount!$C$8,0) -> 1 | AE14: =IF(Headcount!$D$8<=DATE(2031,12,31),Headcount!$C$8,0) -> 1 | AG14: =D14 -> 0 | AH14: =P14 -> 1 | AI14: =AB14 -> 1 | AJ14: =AC14 -> 1 | AK14: =AD14 -> 1 | AL14: =AE14 -> 1
A15: =Headcount!A9 -> Community & Kickstarter lead | B15: =Headcount!B9 -> S&M | C15: =IF(Headcount!$D$9<=Timeline!C5,Headcount!$C$9,0) -> 0 | D15: =IF(Headcount!$D$9<=Timeline!D5,Headcount!$C$9,0) -> 0 | E15: =IF(Headcount!$D$9<=Timeline!E5,Headcount!$C$9,0) -> 0 | F15: =IF(Headcount!$D$9<=Timeline!F5,Headcount!$C$9,0) -> 1 | G15: =IF(Headcount!$D$9<=Timeline!G5,Headcount!$C$9,0) -> 1 | H15: =IF(Headcount!$D$9<=Timeline!H5,Headcount!$C$9,0) -> 1 | I15: =IF(Headcount!$D$9<=Timeline!I5,Headcount!$C$9,0) -> 1 | J15: =IF(Headcount!$D$9<=Timeline!J5,Headcount!$C$9,0) -> 1 | ... AB15: =IF(Headcount!$D$9<=Timeline!AB5,Headcount!$C$9,0) -> 1 | AC15: =IF(Headcount!$D$9<=DATE(2029,12,31),Headcount!$C$9,0) -> 1 | AD15: =IF(Headcount!$D$9<=DATE(2030,12,31),Headcount!$C$9,0) -> 1 | AE15: =IF(Headcount!$D$9<=DATE(2031,12,31),Headcount!$C$9,0) -> 1 | AG15: =D15 -> 0 | AH15: =P15 -> 1 | AI15: =AB15 -> 1 | AJ15: =AC15 -> 1 | AK15: =AD15 -> 1 | AL15: =AE15 -> 1
A16: =Headcount!A10 -> Content editor / historian (City Packs) | B16: =Headcount!B10 -> R&D | C16: =IF(Headcount!$D$10<=Timeline!C5,Headcount!$C$10,0) -> 0 | D16: =IF(Headcount!$D$10<=Timeline!D5,Headcount!$C$10,0) -> 0 | E16: =IF(Headcount!$D$10<=Timeline!E5,Headcount!$C$10,0) -> 0 | F16: =IF(Headcount!$D$10<=Timeline!F5,Headcount!$C$10,0) -> 0 | G16: =IF(Headcount!$D$10<=Timeline!G5,Headcount!$C$10,0) -> 1 | H16: =IF(Headcount!$D$10<=Timeline!H5,Headcount!$C$10,0) -> 1 | I16: =IF(Headcount!$D$10<=Timeline!I5,Headcount!$C$10,0) -> 1 | J16: =IF(Headcount!$D$10<=Timeline!J5,Headcount!$C$10,0) -> 1 | ... AB16: =IF(Headcount!$D$10<=Timeline!AB5,Headcount!$C$10,0) -> 1 | AC16: =IF(Headcount!$D$10<=DATE(2029,12,31),Headcount!$C$10,0) -> 1 | AD16: =IF(Headcount!$D$10<=DATE(2030,12,31),Headcount!$C$10,0) -> 1 | AE16: =IF(Headcount!$D$10<=DATE(2031,12,31),Headcount!$C$10,0) -> 1 | AG16: =D16 -> 0 | AH16: =P16 -> 1 | AI16: =AB16 -> 1 | AJ16: =AC16 -> 1 | AK16: =AD16 -> 1 | AL16: =AE16 -> 1
A17: =Headcount!A11 -> Head of operations & supply chain | B17: =Headcount!B11 -> Ops & CS | C17: =IF(Headcount!$D$11<=Timeline!C5,Headcount!$C$11,0) -> 0 | D17: =IF(Headcount!$D$11<=Timeline!D5,Headcount!$C$11,0) -> 0 | E17: =IF(Headcount!$D$11<=Timeline!E5,Headcount!$C$11,0) -> 0 | F17: =IF(Headcount!$D$11<=Timeline!F5,Headcount!$C$11,0) -> 0 | G17: =IF(Headcount!$D$11<=Timeline!G5,Headcount!$C$11,0) -> 0 | H17: =IF(Headcount!$D$11<=Timeline!H5,Headcount!$C$11,0) -> 0 | I17: =IF(Headcount!$D$11<=Timeline!I5,Headcount!$C$11,0) -> 0 | J17: =IF(Headcount!$D$11<=Timeline!J5,Headcount!$C$11,0) -> 0 | ... AB17: =IF(Headcount!$D$11<=Timeline!AB5,Headcount!$C$11,0) -> 1 | AC17: =IF(Headcount!$D$11<=DATE(2029,12,31),Headcount!$C$11,0) -> 1 | AD17: =IF(Headcount!$D$11<=DATE(2030,12,31),Headcount!$C$11,0) -> 1 | AE17: =IF(Headcount!$D$11<=DATE(2031,12,31),Headcount!$C$11,0) -> 1 | AG17: =D17 -> 0 | AH17: =P17 -> 1 | AI17: =AB17 -> 1 | AJ17: =AC17 -> 1 | AK17: =AD17 -> 1 | AL17: =AE17 -> 1
A18: =Headcount!A12 -> Firmware engineer #2 | B18: =Headcount!B12 -> R&D | C18: =IF(Headcount!$D$12<=Timeline!C5,Headcount!$C$12,0) -> 0 | D18: =IF(Headcount!$D$12<=Timeline!D5,Headcount!$C$12,0) -> 0 | E18: =IF(Headcount!$D$12<=Timeline!E5,Headcount!$C$12,0) -> 0 | F18: =IF(Headcount!$D$12<=Timeline!F5,Headcount!$C$12,0) -> 0 | G18: =IF(Headcount!$D$12<=Timeline!G5,Headcount!$C$12,0) -> 0 | H18: =IF(Headcount!$D$12<=Timeline!H5,Headcount!$C$12,0) -> 0 | I18: =IF(Headcount!$D$12<=Timeline!I5,Headcount!$C$12,0) -> 0 | J18: =IF(Headcount!$D$12<=Timeline!J5,Headcount!$C$12,0) -> 0 | ... AB18: =IF(Headcount!$D$12<=Timeline!AB5,Headcount!$C$12,0) -> 1 | AC18: =IF(Headcount!$D$12<=DATE(2029,12,31),Headcount!$C$12,0) -> 1 | AD18: =IF(Headcount!$D$12<=DATE(2030,12,31),Headcount!$C$12,0) -> 1 | AE18: =IF(Headcount!$D$12<=DATE(2031,12,31),Headcount!$C$12,0) -> 1 | AG18: =D18 -> 0 | AH18: =P18 -> 1 | AI18: =AB18 -> 1 | AJ18: =AC18 -> 1 | AK18: =AD18 -> 1 | AL18: =AE18 -> 1
A19: =Headcount!A13 -> Map Vision / sensor-fusion engineer | B19: =Headcount!B13 -> R&D | C19: =IF(Headcount!$D$13<=Timeline!C5,Headcount!$C$13,0) -> 0 | D19: =IF(Headcount!$D$13<=Timeline!D5,Headcount!$C$13,0) -> 0 | E19: =IF(Headcount!$D$13<=Timeline!E5,Headcount!$C$13,0) -> 0 | F19: =IF(Headcount!$D$13<=Timeline!F5,Headcount!$C$13,0) -> 0 | G19: =IF(Headcount!$D$13<=Timeline!G5,Headcount!$C$13,0) -> 0 | H19: =IF(Headcount!$D$13<=Timeline!H5,Headcount!$C$13,0) -> 0 | I19: =IF(Headcount!$D$13<=Timeline!I5,Headcount!$C$13,0) -> 0 | J19: =IF(Headcount!$D$13<=Timeline!J5,Headcount!$C$13,0) -> 0 | ... AB19: =IF(Headcount!$D$13<=Timeline!AB5,Headcount!$C$13,0) -> 1 | AC19: =IF(Headcount!$D$13<=DATE(2029,12,31),Headcount!$C$13,0) -> 1 | AD19: =IF(Headcount!$D$13<=DATE(2030,12,31),Headcount!$C$13,0) -> 1 | AE19: =IF(Headcount!$D$13<=DATE(2031,12,31),Headcount!$C$13,0) -> 1 | AG19: =D19 -> 0 | AH19: =P19 -> 1 | AI19: =AB19 -> 1 | AJ19: =AC19 -> 1 | AK19: =AD19 -> 1 | AL19: =AE19 -> 1
A20: =Headcount!A14 -> Product designer (device + app UX) | B20: =Headcount!B14 -> R&D | C20: =IF(Headcount!$D$14<=Timeline!C5,Headcount!$C$14,0) -> 0 | D20: =IF(Headcount!$D$14<=Timeline!D5,Headcount!$C$14,0) -> 0 | E20: =IF(Headcount!$D$14<=Timeline!E5,Headcount!$C$14,0) -> 0 | F20: =IF(Headcount!$D$14<=Timeline!F5,Headcount!$C$14,0) -> 0 | G20: =IF(Headcount!$D$14<=Timeline!G5,Headcount!$C$14,0) -> 0 | H20: =IF(Headcount!$D$14<=Timeline!H5,Headcount!$C$14,0) -> 0 | I20: =IF(Headcount!$D$14<=Timeline!I5,Headcount!$C$14,0) -> 0 | J20: =IF(Headcount!$D$14<=Timeline!J5,Headcount!$C$14,0) -> 0 | ... AB20: =IF(Headcount!$D$14<=Timeline!AB5,Headcount!$C$14,0) -> 1 | AC20: =IF(Headcount!$D$14<=DATE(2029,12,31),Headcount!$C$14,0) -> 1 | AD20: =IF(Headcount!$D$14<=DATE(2030,12,31),Headcount!$C$14,0) -> 1 | AE20: =IF(Headcount!$D$14<=DATE(2031,12,31),Headcount!$C$14,0) -> 1 | AG20: =D20 -> 0 | AH20: =P20 -> 1 | AI20: =AB20 -> 1 | AJ20: =AC20 -> 1 | AK20: =AD20 -> 1 | AL20: =AE20 -> 1
A21: =Headcount!A15 -> Customer support lead | B21: =Headcount!B15 -> Ops & CS | C21: =IF(Headcount!$D$15<=Timeline!C5,Headcount!$C$15,0) -> 0 | D21: =IF(Headcount!$D$15<=Timeline!D5,Headcount!$C$15,0) -> 0 | E21: =IF(Headcount!$D$15<=Timeline!E5,Headcount!$C$15,0) -> 0 | F21: =IF(Headcount!$D$15<=Timeline!F5,Headcount!$C$15,0) -> 0 | G21: =IF(Headcount!$D$15<=Timeline!G5,Headcount!$C$15,0) -> 0 | H21: =IF(Headcount!$D$15<=Timeline!H5,Headcount!$C$15,0) -> 0 | I21: =IF(Headcount!$D$15<=Timeline!I5,Headcount!$C$15,0) -> 0 | J21: =IF(Headcount!$D$15<=Timeline!J5,Headcount!$C$15,0) -> 0 | ... AB21: =IF(Headcount!$D$15<=Timeline!AB5,Headcount!$C$15,0) -> 1 | AC21: =IF(Headcount!$D$15<=DATE(2029,12,31),Headcount!$C$15,0) -> 1 | AD21: =IF(Headcount!$D$15<=DATE(2030,12,31),Headcount!$C$15,0) -> 1 | AE21: =IF(Headcount!$D$15<=DATE(2031,12,31),Headcount!$C$15,0) -> 1 | AG21: =D21 -> 0 | AH21: =P21 -> 1 | AI21: =AB21 -> 1 | AJ21: =AC21 -> 1 | AK21: =AD21 -> 1 | AL21: =AE21 -> 1
A22: =Headcount!A16 -> Growth marketing manager | B22: =Headcount!B16 -> S&M | C22: =IF(Headcount!$D$16<=Timeline!C5,Headcount!$C$16,0) -> 0 | D22: =IF(Headcount!$D$16<=Timeline!D5,Headcount!$C$16,0) -> 0 | E22: =IF(Headcount!$D$16<=Timeline!E5,Headcount!$C$16,0) -> 0 | F22: =IF(Headcount!$D$16<=Timeline!F5,Headcount!$C$16,0) -> 0 | G22: =IF(Headcount!$D$16<=Timeline!G5,Headcount!$C$16,0) -> 0 | H22: =IF(Headcount!$D$16<=Timeline!H5,Headcount!$C$16,0) -> 0 | I22: =IF(Headcount!$D$16<=Timeline!I5,Headcount!$C$16,0) -> 0 | J22: =IF(Headcount!$D$16<=Timeline!J5,Headcount!$C$16,0) -> 0 | ... AB22: =IF(Headcount!$D$16<=Timeline!AB5,Headcount!$C$16,0) -> 1 | AC22: =IF(Headcount!$D$16<=DATE(2029,12,31),Headcount!$C$16,0) -> 1 | AD22: =IF(Headcount!$D$16<=DATE(2030,12,31),Headcount!$C$16,0) -> 1 | AE22: =IF(Headcount!$D$16<=DATE(2031,12,31),Headcount!$C$16,0) -> 1 | AG22: =D22 -> 0 | AH22: =P22 -> 1 | AI22: =AB22 -> 1 | AJ22: =AC22 -> 1 | AK22: =AD22 -> 1 | AL22: =AE22 -> 1
A23: =Headcount!A17 -> Finance & ops manager / controller | B23: =Headcount!B17 -> G&A | C23: =IF(Headcount!$D$17<=Timeline!C5,Headcount!$C$17,0) -> 0 | D23: =IF(Headcount!$D$17<=Timeline!D5,Headcount!$C$17,0) -> 0 | E23: =IF(Headcount!$D$17<=Timeline!E5,Headcount!$C$17,0) -> 0 | F23: =IF(Headcount!$D$17<=Timeline!F5,Headcount!$C$17,0) -> 0 | G23: =IF(Headcount!$D$17<=Timeline!G5,Headcount!$C$17,0) -> 0 | H23: =IF(Headcount!$D$17<=Timeline!H5,Headcount!$C$17,0) -> 0 | I23: =IF(Headcount!$D$17<=Timeline!I5,Headcount!$C$17,0) -> 0 | J23: =IF(Headcount!$D$17<=Timeline!J5,Headcount!$C$17,0) -> 0 | ... AB23: =IF(Headcount!$D$17<=Timeline!AB5,Headcount!$C$17,0) -> 1 | AC23: =IF(Headcount!$D$17<=DATE(2029,12,31),Headcount!$C$17,0) -> 1 | AD23: =IF(Headcount!$D$17<=DATE(2030,12,31),Headcount!$C$17,0) -> 1 | AE23: =IF(Headcount!$D$17<=DATE(2031,12,31),Headcount!$C$17,0) -> 1 | AG23: =D23 -> 0 | AH23: =P23 -> 1 | AI23: =AB23 -> 1 | AJ23: =AC23 -> 1 | AK23: =AD23 -> 1 | AL23: =AE23 -> 1
A24: =Headcount!A18 -> Backend / cloud engineer | B24: =Headcount!B18 -> R&D | C24: =IF(Headcount!$D$18<=Timeline!C5,Headcount!$C$18,0) -> 0 | D24: =IF(Headcount!$D$18<=Timeline!D5,Headcount!$C$18,0) -> 0 | E24: =IF(Headcount!$D$18<=Timeline!E5,Headcount!$C$18,0) -> 0 | F24: =IF(Headcount!$D$18<=Timeline!F5,Headcount!$C$18,0) -> 0 | G24: =IF(Headcount!$D$18<=Timeline!G5,Headcount!$C$18,0) -> 0 | H24: =IF(Headcount!$D$18<=Timeline!H5,Headcount!$C$18,0) -> 0 | I24: =IF(Headcount!$D$18<=Timeline!I5,Headcount!$C$18,0) -> 0 | J24: =IF(Headcount!$D$18<=Timeline!J5,Headcount!$C$18,0) -> 0 | ... AB24: =IF(Headcount!$D$18<=Timeline!AB5,Headcount!$C$18,0) -> 1 | AC24: =IF(Headcount!$D$18<=DATE(2029,12,31),Headcount!$C$18,0) -> 1 | AD24: =IF(Headcount!$D$18<=DATE(2030,12,31),Headcount!$C$18,0) -> 1 | AE24: =IF(Headcount!$D$18<=DATE(2031,12,31),Headcount!$C$18,0) -> 1 | AG24: =D24 -> 0 | AH24: =P24 -> 0 | AI24: =AB24 -> 1 | AJ24: =AC24 -> 1 | AK24: =AD24 -> 1 | AL24: =AE24 -> 1
A25: =Headcount!A19 -> Mechanical engineer | B25: =Headcount!B19 -> R&D | C25: =IF(Headcount!$D$19<=Timeline!C5,Headcount!$C$19,0) -> 0 | D25: =IF(Headcount!$D$19<=Timeline!D5,Headcount!$C$19,0) -> 0 | E25: =IF(Headcount!$D$19<=Timeline!E5,Headcount!$C$19,0) -> 0 | F25: =IF(Headcount!$D$19<=Timeline!F5,Headcount!$C$19,0) -> 0 | G25: =IF(Headcount!$D$19<=Timeline!G5,Headcount!$C$19,0) -> 0 | H25: =IF(Headcount!$D$19<=Timeline!H5,Headcount!$C$19,0) -> 0 | I25: =IF(Headcount!$D$19<=Timeline!I5,Headcount!$C$19,0) -> 0 | J25: =IF(Headcount!$D$19<=Timeline!J5,Headcount!$C$19,0) -> 0 | ... AB25: =IF(Headcount!$D$19<=Timeline!AB5,Headcount!$C$19,0) -> 1 | AC25: =IF(Headcount!$D$19<=DATE(2029,12,31),Headcount!$C$19,0) -> 1 | AD25: =IF(Headcount!$D$19<=DATE(2030,12,31),Headcount!$C$19,0) -> 1 | AE25: =IF(Headcount!$D$19<=DATE(2031,12,31),Headcount!$C$19,0) -> 1 | AG25: =D25 -> 0 | AH25: =P25 -> 0 | AI25: =AB25 -> 1 | AJ25: =AC25 -> 1 | AK25: =AD25 -> 1 | AL25: =AE25 -> 1
A26: =Headcount!A20 -> Content editors | B26: =Headcount!B20 -> R&D | C26: =IF(Headcount!$D$20<=Timeline!C5,Headcount!$C$20,0) -> 0 | D26: =IF(Headcount!$D$20<=Timeline!D5,Headcount!$C$20,0) -> 0 | E26: =IF(Headcount!$D$20<=Timeline!E5,Headcount!$C$20,0) -> 0 | F26: =IF(Headcount!$D$20<=Timeline!F5,Headcount!$C$20,0) -> 0 | G26: =IF(Headcount!$D$20<=Timeline!G5,Headcount!$C$20,0) -> 0 | H26: =IF(Headcount!$D$20<=Timeline!H5,Headcount!$C$20,0) -> 0 | I26: =IF(Headcount!$D$20<=Timeline!I5,Headcount!$C$20,0) -> 0 | J26: =IF(Headcount!$D$20<=Timeline!J5,Headcount!$C$20,0) -> 0 | ... AB26: =IF(Headcount!$D$20<=Timeline!AB5,Headcount!$C$20,0) -> 2 | AC26: =IF(Headcount!$D$20<=DATE(2029,12,31),Headcount!$C$20,0) -> 2 | AD26: =IF(Headcount!$D$20<=DATE(2030,12,31),Headcount!$C$20,0) -> 2 | AE26: =IF(Headcount!$D$20<=DATE(2031,12,31),Headcount!$C$20,0) -> 2 | AG26: =D26 -> 0 | AH26: =P26 -> 0 | AI26: =AB26 -> 2 | AJ26: =AC26 -> 2 | AK26: =AD26 -> 2 | AL26: =AE26 -> 2
A27: =Headcount!A21 -> Customer support agents | B27: =Headcount!B21 -> Ops & CS | C27: =IF(Headcount!$D$21<=Timeline!C5,Headcount!$C$21,0) -> 0 | D27: =IF(Headcount!$D$21<=Timeline!D5,Headcount!$C$21,0) -> 0 | E27: =IF(Headcount!$D$21<=Timeline!E5,Headcount!$C$21,0) -> 0 | F27: =IF(Headcount!$D$21<=Timeline!F5,Headcount!$C$21,0) -> 0 | G27: =IF(Headcount!$D$21<=Timeline!G5,Headcount!$C$21,0) -> 0 | H27: =IF(Headcount!$D$21<=Timeline!H5,Headcount!$C$21,0) -> 0 | I27: =IF(Headcount!$D$21<=Timeline!I5,Headcount!$C$21,0) -> 0 | J27: =IF(Headcount!$D$21<=Timeline!J5,Headcount!$C$21,0) -> 0 | ... AB27: =IF(Headcount!$D$21<=Timeline!AB5,Headcount!$C$21,0) -> 2 | AC27: =IF(Headcount!$D$21<=DATE(2029,12,31),Headcount!$C$21,0) -> 2 | AD27: =IF(Headcount!$D$21<=DATE(2030,12,31),Headcount!$C$21,0) -> 2 | AE27: =IF(Headcount!$D$21<=DATE(2031,12,31),Headcount!$C$21,0) -> 2 | AG27: =D27 -> 0 | AH27: =P27 -> 0 | AI27: =AB27 -> 2 | AJ27: =AC27 -> 2 | AK27: =AD27 -> 2 | AL27: =AE27 -> 2
A28: =Headcount!A22 -> Retail & partnerships manager | B28: =Headcount!B22 -> S&M | C28: =IF(Headcount!$D$22<=Timeline!C5,Headcount!$C$22,0) -> 0 | D28: =IF(Headcount!$D$22<=Timeline!D5,Headcount!$C$22,0) -> 0 | E28: =IF(Headcount!$D$22<=Timeline!E5,Headcount!$C$22,0) -> 0 | F28: =IF(Headcount!$D$22<=Timeline!F5,Headcount!$C$22,0) -> 0 | G28: =IF(Headcount!$D$22<=Timeline!G5,Headcount!$C$22,0) -> 0 | H28: =IF(Headcount!$D$22<=Timeline!H5,Headcount!$C$22,0) -> 0 | I28: =IF(Headcount!$D$22<=Timeline!I5,Headcount!$C$22,0) -> 0 | J28: =IF(Headcount!$D$22<=Timeline!J5,Headcount!$C$22,0) -> 0 | ... AB28: =IF(Headcount!$D$22<=Timeline!AB5,Headcount!$C$22,0) -> 1 | AC28: =IF(Headcount!$D$22<=DATE(2029,12,31),Headcount!$C$22,0) -> 1 | AD28: =IF(Headcount!$D$22<=DATE(2030,12,31),Headcount!$C$22,0) -> 1 | AE28: =IF(Headcount!$D$22<=DATE(2031,12,31),Headcount!$C$22,0) -> 1 | AG28: =D28 -> 0 | AH28: =P28 -> 0 | AI28: =AB28 -> 1 | AJ28: =AC28 -> 1 | AK28: =AD28 -> 1 | AL28: =AE28 -> 1
A29: =Headcount!A23 -> B2B fleet sales lead | B29: =Headcount!B23 -> S&M | C29: =IF(Headcount!$D$23<=Timeline!C5,Headcount!$C$23,0) -> 0 | D29: =IF(Headcount!$D$23<=Timeline!D5,Headcount!$C$23,0) -> 0 | E29: =IF(Headcount!$D$23<=Timeline!E5,Headcount!$C$23,0) -> 0 | F29: =IF(Headcount!$D$23<=Timeline!F5,Headcount!$C$23,0) -> 0 | G29: =IF(Headcount!$D$23<=Timeline!G5,Headcount!$C$23,0) -> 0 | H29: =IF(Headcount!$D$23<=Timeline!H5,Headcount!$C$23,0) -> 0 | I29: =IF(Headcount!$D$23<=Timeline!I5,Headcount!$C$23,0) -> 0 | J29: =IF(Headcount!$D$23<=Timeline!J5,Headcount!$C$23,0) -> 0 | ... AB29: =IF(Headcount!$D$23<=Timeline!AB5,Headcount!$C$23,0) -> 1 | AC29: =IF(Headcount!$D$23<=DATE(2029,12,31),Headcount!$C$23,0) -> 1 | AD29: =IF(Headcount!$D$23<=DATE(2030,12,31),Headcount!$C$23,0) -> 1 | AE29: =IF(Headcount!$D$23<=DATE(2031,12,31),Headcount!$C$23,0) -> 1 | AG29: =D29 -> 0 | AH29: =P29 -> 0 | AI29: =AB29 -> 1 | AJ29: =AC29 -> 1 | AK29: =AD29 -> 1 | AL29: =AE29 -> 1
A30: =Headcount!A24 -> QA / test engineer | B30: =Headcount!B24 -> R&D | C30: =IF(Headcount!$D$24<=Timeline!C5,Headcount!$C$24,0) -> 0 | D30: =IF(Headcount!$D$24<=Timeline!D5,Headcount!$C$24,0) -> 0 | E30: =IF(Headcount!$D$24<=Timeline!E5,Headcount!$C$24,0) -> 0 | F30: =IF(Headcount!$D$24<=Timeline!F5,Headcount!$C$24,0) -> 0 | G30: =IF(Headcount!$D$24<=Timeline!G5,Headcount!$C$24,0) -> 0 | H30: =IF(Headcount!$D$24<=Timeline!H5,Headcount!$C$24,0) -> 0 | I30: =IF(Headcount!$D$24<=Timeline!I5,Headcount!$C$24,0) -> 0 | J30: =IF(Headcount!$D$24<=Timeline!J5,Headcount!$C$24,0) -> 0 | ... AB30: =IF(Headcount!$D$24<=Timeline!AB5,Headcount!$C$24,0) -> 1 | AC30: =IF(Headcount!$D$24<=DATE(2029,12,31),Headcount!$C$24,0) -> 1 | AD30: =IF(Headcount!$D$24<=DATE(2030,12,31),Headcount!$C$24,0) -> 1 | AE30: =IF(Headcount!$D$24<=DATE(2031,12,31),Headcount!$C$24,0) -> 1 | AG30: =D30 -> 0 | AH30: =P30 -> 0 | AI30: =AB30 -> 1 | AJ30: =AC30 -> 1 | AK30: =AD30 -> 1 | AL30: =AE30 -> 1
A31: =Headcount!A25 -> ML engineer #2 (on-device models) | B31: =Headcount!B25 -> R&D | C31: =IF(Headcount!$D$25<=Timeline!C5,Headcount!$C$25,0) -> 0 | D31: =IF(Headcount!$D$25<=Timeline!D5,Headcount!$C$25,0) -> 0 | E31: =IF(Headcount!$D$25<=Timeline!E5,Headcount!$C$25,0) -> 0 | F31: =IF(Headcount!$D$25<=Timeline!F5,Headcount!$C$25,0) -> 0 | G31: =IF(Headcount!$D$25<=Timeline!G5,Headcount!$C$25,0) -> 0 | H31: =IF(Headcount!$D$25<=Timeline!H5,Headcount!$C$25,0) -> 0 | I31: =IF(Headcount!$D$25<=Timeline!I5,Headcount!$C$25,0) -> 0 | J31: =IF(Headcount!$D$25<=Timeline!J5,Headcount!$C$25,0) -> 0 | ... AB31: =IF(Headcount!$D$25<=Timeline!AB5,Headcount!$C$25,0) -> 1 | AC31: =IF(Headcount!$D$25<=DATE(2029,12,31),Headcount!$C$25,0) -> 1 | AD31: =IF(Headcount!$D$25<=DATE(2030,12,31),Headcount!$C$25,0) -> 1 | AE31: =IF(Headcount!$D$25<=DATE(2031,12,31),Headcount!$C$25,0) -> 1 | AG31: =D31 -> 0 | AH31: =P31 -> 0 | AI31: =AB31 -> 1 | AJ31: =AC31 -> 1 | AK31: =AD31 -> 1 | AL31: =AE31 -> 1
A32: =Headcount!A26 -> Brand & content marketer | B32: =Headcount!B26 -> S&M | C32: =IF(Headcount!$D$26<=Timeline!C5,Headcount!$C$26,0) -> 0 | D32: =IF(Headcount!$D$26<=Timeline!D5,Headcount!$C$26,0) -> 0 | E32: =IF(Headcount!$D$26<=Timeline!E5,Headcount!$C$26,0) -> 0 | F32: =IF(Headcount!$D$26<=Timeline!F5,Headcount!$C$26,0) -> 0 | G32: =IF(Headcount!$D$26<=Timeline!G5,Headcount!$C$26,0) -> 0 | H32: =IF(Headcount!$D$26<=Timeline!H5,Headcount!$C$26,0) -> 0 | I32: =IF(Headcount!$D$26<=Timeline!I5,Headcount!$C$26,0) -> 0 | J32: =IF(Headcount!$D$26<=Timeline!J5,Headcount!$C$26,0) -> 0 | ... AB32: =IF(Headcount!$D$26<=Timeline!AB5,Headcount!$C$26,0) -> 1 | AC32: =IF(Headcount!$D$26<=DATE(2029,12,31),Headcount!$C$26,0) -> 1 | AD32: =IF(Headcount!$D$26<=DATE(2030,12,31),Headcount!$C$26,0) -> 1 | AE32: =IF(Headcount!$D$26<=DATE(2031,12,31),Headcount!$C$26,0) -> 1 | AG32: =D32 -> 0 | AH32: =P32 -> 0 | AI32: =AB32 -> 1 | AJ32: =AC32 -> 1 | AK32: =AD32 -> 1 | AL32: =AE32 -> 1
A33: =Headcount!A27 -> People & office ops | B33: =Headcount!B27 -> G&A | C33: =IF(Headcount!$D$27<=Timeline!C5,Headcount!$C$27,0) -> 0 | D33: =IF(Headcount!$D$27<=Timeline!D5,Headcount!$C$27,0) -> 0 | E33: =IF(Headcount!$D$27<=Timeline!E5,Headcount!$C$27,0) -> 0 | F33: =IF(Headcount!$D$27<=Timeline!F5,Headcount!$C$27,0) -> 0 | G33: =IF(Headcount!$D$27<=Timeline!G5,Headcount!$C$27,0) -> 0 | H33: =IF(Headcount!$D$27<=Timeline!H5,Headcount!$C$27,0) -> 0 | I33: =IF(Headcount!$D$27<=Timeline!I5,Headcount!$C$27,0) -> 0 | J33: =IF(Headcount!$D$27<=Timeline!J5,Headcount!$C$27,0) -> 0 | ... AB33: =IF(Headcount!$D$27<=Timeline!AB5,Headcount!$C$27,0) -> 1 | AC33: =IF(Headcount!$D$27<=DATE(2029,12,31),Headcount!$C$27,0) -> 1 | AD33: =IF(Headcount!$D$27<=DATE(2030,12,31),Headcount!$C$27,0) -> 1 | AE33: =IF(Headcount!$D$27<=DATE(2031,12,31),Headcount!$C$27,0) -> 1 | AG33: =D33 -> 0 | AH33: =P33 -> 0 | AI33: =AB33 -> 1 | AJ33: =AC33 -> 1 | AK33: =AD33 -> 1 | AL33: =AE33 -> 1
A34: =Headcount!A28 -> VP Engineering | B34: =Headcount!B28 -> R&D | C34: =IF(Headcount!$D$28<=Timeline!C5,Headcount!$C$28,0) -> 0 | D34: =IF(Headcount!$D$28<=Timeline!D5,Headcount!$C$28,0) -> 0 | E34: =IF(Headcount!$D$28<=Timeline!E5,Headcount!$C$28,0) -> 0 | F34: =IF(Headcount!$D$28<=Timeline!F5,Headcount!$C$28,0) -> 0 | G34: =IF(Headcount!$D$28<=Timeline!G5,Headcount!$C$28,0) -> 0 | H34: =IF(Headcount!$D$28<=Timeline!H5,Headcount!$C$28,0) -> 0 | I34: =IF(Headcount!$D$28<=Timeline!I5,Headcount!$C$28,0) -> 0 | J34: =IF(Headcount!$D$28<=Timeline!J5,Headcount!$C$28,0) -> 0 | ... AB34: =IF(Headcount!$D$28<=Timeline!AB5,Headcount!$C$28,0) -> 1 | AC34: =IF(Headcount!$D$28<=DATE(2029,12,31),Headcount!$C$28,0) -> 1 | AD34: =IF(Headcount!$D$28<=DATE(2030,12,31),Headcount!$C$28,0) -> 1 | AE34: =IF(Headcount!$D$28<=DATE(2031,12,31),Headcount!$C$28,0) -> 1 | AG34: =D34 -> 0 | AH34: =P34 -> 0 | AI34: =AB34 -> 1 | AJ34: =AC34 -> 1 | AK34: =AD34 -> 1 | AL34: =AE34 -> 1
A35: =Headcount!A29 -> Customer support agents | B35: =Headcount!B29 -> Ops & CS | C35: =IF(Headcount!$D$29<=Timeline!C5,Headcount!$C$29,0) -> 0 | D35: =IF(Headcount!$D$29<=Timeline!D5,Headcount!$C$29,0) -> 0 | E35: =IF(Headcount!$D$29<=Timeline!E5,Headcount!$C$29,0) -> 0 | F35: =IF(Headcount!$D$29<=Timeline!F5,Headcount!$C$29,0) -> 0 | G35: =IF(Headcount!$D$29<=Timeline!G5,Headcount!$C$29,0) -> 0 | H35: =IF(Headcount!$D$29<=Timeline!H5,Headcount!$C$29,0) -> 0 | I35: =IF(Headcount!$D$29<=Timeline!I5,Headcount!$C$29,0) -> 0 | J35: =IF(Headcount!$D$29<=Timeline!J5,Headcount!$C$29,0) -> 0 | ... AB35: =IF(Headcount!$D$29<=Timeline!AB5,Headcount!$C$29,0) -> 3 | AC35: =IF(Headcount!$D$29<=DATE(2029,12,31),Headcount!$C$29,0) -> 3 | AD35: =IF(Headcount!$D$29<=DATE(2030,12,31),Headcount!$C$29,0) -> 3 | AE35: =IF(Headcount!$D$29<=DATE(2031,12,31),Headcount!$C$29,0) -> 3 | AG35: =D35 -> 0 | AH35: =P35 -> 0 | AI35: =AB35 -> 3 | AJ35: =AC35 -> 3 | AK35: =AD35 -> 3 | AL35: =AE35 -> 3
A36: =Headcount!A30 -> VP Marketing | B36: =Headcount!B30 -> S&M | C36: =IF(Headcount!$D$30<=Timeline!C5,Headcount!$C$30,0) -> 0 | D36: =IF(Headcount!$D$30<=Timeline!D5,Headcount!$C$30,0) -> 0 | E36: =IF(Headcount!$D$30<=Timeline!E5,Headcount!$C$30,0) -> 0 | F36: =IF(Headcount!$D$30<=Timeline!F5,Headcount!$C$30,0) -> 0 | G36: =IF(Headcount!$D$30<=Timeline!G5,Headcount!$C$30,0) -> 0 | H36: =IF(Headcount!$D$30<=Timeline!H5,Headcount!$C$30,0) -> 0 | I36: =IF(Headcount!$D$30<=Timeline!I5,Headcount!$C$30,0) -> 0 | J36: =IF(Headcount!$D$30<=Timeline!J5,Headcount!$C$30,0) -> 0 | ... AB36: =IF(Headcount!$D$30<=Timeline!AB5,Headcount!$C$30,0) -> 0 | AC36: =IF(Headcount!$D$30<=DATE(2029,12,31),Headcount!$C$30,0) -> 1 | AD36: =IF(Headcount!$D$30<=DATE(2030,12,31),Headcount!$C$30,0) -> 1 | AE36: =IF(Headcount!$D$30<=DATE(2031,12,31),Headcount!$C$30,0) -> 1 | AG36: =D36 -> 0 | AH36: =P36 -> 0 | AI36: =AB36 -> 0 | AJ36: =AC36 -> 1 | AK36: =AD36 -> 1 | AL36: =AE36 -> 1
A37: =Headcount!A31 -> R&D engineers (Gen-2, platform) | B37: =Headcount!B31 -> R&D | C37: =IF(Headcount!$D$31<=Timeline!C5,Headcount!$C$31,0) -> 0 | D37: =IF(Headcount!$D$31<=Timeline!D5,Headcount!$C$31,0) -> 0 | E37: =IF(Headcount!$D$31<=Timeline!E5,Headcount!$C$31,0) -> 0 | F37: =IF(Headcount!$D$31<=Timeline!F5,Headcount!$C$31,0) -> 0 | G37: =IF(Headcount!$D$31<=Timeline!G5,Headcount!$C$31,0) -> 0 | H37: =IF(Headcount!$D$31<=Timeline!H5,Headcount!$C$31,0) -> 0 | I37: =IF(Headcount!$D$31<=Timeline!I5,Headcount!$C$31,0) -> 0 | J37: =IF(Headcount!$D$31<=Timeline!J5,Headcount!$C$31,0) -> 0 | ... AB37: =IF(Headcount!$D$31<=Timeline!AB5,Headcount!$C$31,0) -> 0 | AC37: =IF(Headcount!$D$31<=DATE(2029,12,31),Headcount!$C$31,0) -> 8 | AD37: =IF(Headcount!$D$31<=DATE(2030,12,31),Headcount!$C$31,0) -> 8 | AE37: =IF(Headcount!$D$31<=DATE(2031,12,31),Headcount!$C$31,0) -> 8 | AG37: =D37 -> 0 | AH37: =P37 -> 0 | AI37: =AB37 -> 0 | AJ37: =AC37 -> 8 | AK37: =AD37 -> 8 | AL37: =AE37 -> 8
A38: =Headcount!A32 -> Content editors (30 new cities) | B38: =Headcount!B32 -> R&D | C38: =IF(Headcount!$D$32<=Timeline!C5,Headcount!$C$32,0) -> 0 | D38: =IF(Headcount!$D$32<=Timeline!D5,Headcount!$C$32,0) -> 0 | E38: =IF(Headcount!$D$32<=Timeline!E5,Headcount!$C$32,0) -> 0 | F38: =IF(Headcount!$D$32<=Timeline!F5,Headcount!$C$32,0) -> 0 | G38: =IF(Headcount!$D$32<=Timeline!G5,Headcount!$C$32,0) -> 0 | H38: =IF(Headcount!$D$32<=Timeline!H5,Headcount!$C$32,0) -> 0 | I38: =IF(Headcount!$D$32<=Timeline!I5,Headcount!$C$32,0) -> 0 | J38: =IF(Headcount!$D$32<=Timeline!J5,Headcount!$C$32,0) -> 0 | ... AB38: =IF(Headcount!$D$32<=Timeline!AB5,Headcount!$C$32,0) -> 0 | AC38: =IF(Headcount!$D$32<=DATE(2029,12,31),Headcount!$C$32,0) -> 4 | AD38: =IF(Headcount!$D$32<=DATE(2030,12,31),Headcount!$C$32,0) -> 4 | AE38: =IF(Headcount!$D$32<=DATE(2031,12,31),Headcount!$C$32,0) -> 4 | AG38: =D38 -> 0 | AH38: =P38 -> 0 | AI38: =AB38 -> 0 | AJ38: =AC38 -> 4 | AK38: =AD38 -> 4 | AL38: =AE38 -> 4
A39: =Headcount!A33 -> S&M team (performance, retail, EU/APAC) | B39: =Headcount!B33 -> S&M | C39: =IF(Headcount!$D$33<=Timeline!C5,Headcount!$C$33,0) -> 0 | D39: =IF(Headcount!$D$33<=Timeline!D5,Headcount!$C$33,0) -> 0 | E39: =IF(Headcount!$D$33<=Timeline!E5,Headcount!$C$33,0) -> 0 | F39: =IF(Headcount!$D$33<=Timeline!F5,Headcount!$C$33,0) -> 0 | G39: =IF(Headcount!$D$33<=Timeline!G5,Headcount!$C$33,0) -> 0 | H39: =IF(Headcount!$D$33<=Timeline!H5,Headcount!$C$33,0) -> 0 | I39: =IF(Headcount!$D$33<=Timeline!I5,Headcount!$C$33,0) -> 0 | J39: =IF(Headcount!$D$33<=Timeline!J5,Headcount!$C$33,0) -> 0 | ... AB39: =IF(Headcount!$D$33<=Timeline!AB5,Headcount!$C$33,0) -> 0 | AC39: =IF(Headcount!$D$33<=DATE(2029,12,31),Headcount!$C$33,0) -> 5 | AD39: =IF(Headcount!$D$33<=DATE(2030,12,31),Headcount!$C$33,0) -> 5 | AE39: =IF(Headcount!$D$33<=DATE(2031,12,31),Headcount!$C$33,0) -> 5 | AG39: =D39 -> 0 | AH39: =P39 -> 0 | AI39: =AB39 -> 0 | AJ39: =AC39 -> 5 | AK39: =AD39 -> 5 | AL39: =AE39 -> 5
A40: =Headcount!A34 -> Ops / supply-chain / quality | B40: =Headcount!B34 -> Ops & CS | C40: =IF(Headcount!$D$34<=Timeline!C5,Headcount!$C$34,0) -> 0 | D40: =IF(Headcount!$D$34<=Timeline!D5,Headcount!$C$34,0) -> 0 | E40: =IF(Headcount!$D$34<=Timeline!E5,Headcount!$C$34,0) -> 0 | F40: =IF(Headcount!$D$34<=Timeline!F5,Headcount!$C$34,0) -> 0 | G40: =IF(Headcount!$D$34<=Timeline!G5,Headcount!$C$34,0) -> 0 | H40: =IF(Headcount!$D$34<=Timeline!H5,Headcount!$C$34,0) -> 0 | I40: =IF(Headcount!$D$34<=Timeline!I5,Headcount!$C$34,0) -> 0 | J40: =IF(Headcount!$D$34<=Timeline!J5,Headcount!$C$34,0) -> 0 | ... AB40: =IF(Headcount!$D$34<=Timeline!AB5,Headcount!$C$34,0) -> 0 | AC40: =IF(Headcount!$D$34<=DATE(2029,12,31),Headcount!$C$34,0) -> 3 | AD40: =IF(Headcount!$D$34<=DATE(2030,12,31),Headcount!$C$34,0) -> 3 | AE40: =IF(Headcount!$D$34<=DATE(2031,12,31),Headcount!$C$34,0) -> 3 | AG40: =D40 -> 0 | AH40: =P40 -> 0 | AI40: =AB40 -> 0 | AJ40: =AC40 -> 3 | AK40: =AD40 -> 3 | AL40: =AE40 -> 3
A41: =Headcount!A35 -> Customer support agents | B41: =Headcount!B35 -> Ops & CS | C41: =IF(Headcount!$D$35<=Timeline!C5,Headcount!$C$35,0) -> 0 | D41: =IF(Headcount!$D$35<=Timeline!D5,Headcount!$C$35,0) -> 0 | E41: =IF(Headcount!$D$35<=Timeline!E5,Headcount!$C$35,0) -> 0 | F41: =IF(Headcount!$D$35<=Timeline!F5,Headcount!$C$35,0) -> 0 | G41: =IF(Headcount!$D$35<=Timeline!G5,Headcount!$C$35,0) -> 0 | H41: =IF(Headcount!$D$35<=Timeline!H5,Headcount!$C$35,0) -> 0 | I41: =IF(Headcount!$D$35<=Timeline!I5,Headcount!$C$35,0) -> 0 | J41: =IF(Headcount!$D$35<=Timeline!J5,Headcount!$C$35,0) -> 0 | ... AB41: =IF(Headcount!$D$35<=Timeline!AB5,Headcount!$C$35,0) -> 0 | AC41: =IF(Headcount!$D$35<=DATE(2029,12,31),Headcount!$C$35,0) -> 6 | AD41: =IF(Headcount!$D$35<=DATE(2030,12,31),Headcount!$C$35,0) -> 6 | AE41: =IF(Headcount!$D$35<=DATE(2031,12,31),Headcount!$C$35,0) -> 6 | AG41: =D41 -> 0 | AH41: =P41 -> 0 | AI41: =AB41 -> 0 | AJ41: =AC41 -> 6 | AK41: =AD41 -> 6 | AL41: =AE41 -> 6
A42: =Headcount!A36 -> G&A (finance, legal, people) | B42: =Headcount!B36 -> G&A | C42: =IF(Headcount!$D$36<=Timeline!C5,Headcount!$C$36,0) -> 0 | D42: =IF(Headcount!$D$36<=Timeline!D5,Headcount!$C$36,0) -> 0 | E42: =IF(Headcount!$D$36<=Timeline!E5,Headcount!$C$36,0) -> 0 | F42: =IF(Headcount!$D$36<=Timeline!F5,Headcount!$C$36,0) -> 0 | G42: =IF(Headcount!$D$36<=Timeline!G5,Headcount!$C$36,0) -> 0 | H42: =IF(Headcount!$D$36<=Timeline!H5,Headcount!$C$36,0) -> 0 | I42: =IF(Headcount!$D$36<=Timeline!I5,Headcount!$C$36,0) -> 0 | J42: =IF(Headcount!$D$36<=Timeline!J5,Headcount!$C$36,0) -> 0 | ... AB42: =IF(Headcount!$D$36<=Timeline!AB5,Headcount!$C$36,0) -> 0 | AC42: =IF(Headcount!$D$36<=DATE(2029,12,31),Headcount!$C$36,0) -> 3 | AD42: =IF(Headcount!$D$36<=DATE(2030,12,31),Headcount!$C$36,0) -> 3 | AE42: =IF(Headcount!$D$36<=DATE(2031,12,31),Headcount!$C$36,0) -> 3 | AG42: =D42 -> 0 | AH42: =P42 -> 0 | AI42: =AB42 -> 0 | AJ42: =AC42 -> 3 | AK42: =AD42 -> 3 | AL42: =AE42 -> 3
A43: =Headcount!A37 -> CFO | B43: =Headcount!B37 -> G&A | C43: =IF(Headcount!$D$37<=Timeline!C5,Headcount!$C$37,0) -> 0 | D43: =IF(Headcount!$D$37<=Timeline!D5,Headcount!$C$37,0) -> 0 | E43: =IF(Headcount!$D$37<=Timeline!E5,Headcount!$C$37,0) -> 0 | F43: =IF(Headcount!$D$37<=Timeline!F5,Headcount!$C$37,0) -> 0 | G43: =IF(Headcount!$D$37<=Timeline!G5,Headcount!$C$37,0) -> 0 | H43: =IF(Headcount!$D$37<=Timeline!H5,Headcount!$C$37,0) -> 0 | I43: =IF(Headcount!$D$37<=Timeline!I5,Headcount!$C$37,0) -> 0 | J43: =IF(Headcount!$D$37<=Timeline!J5,Headcount!$C$37,0) -> 0 | ... AB43: =IF(Headcount!$D$37<=Timeline!AB5,Headcount!$C$37,0) -> 0 | AC43: =IF(Headcount!$D$37<=DATE(2029,12,31),Headcount!$C$37,0) -> 1 | AD43: =IF(Headcount!$D$37<=DATE(2030,12,31),Headcount!$C$37,0) -> 1 | AE43: =IF(Headcount!$D$37<=DATE(2031,12,31),Headcount!$C$37,0) -> 1 | AG43: =D43 -> 0 | AH43: =P43 -> 0 | AI43: =AB43 -> 0 | AJ43: =AC43 -> 1 | AK43: =AD43 -> 1 | AL43: =AE43 -> 1
A44: =Headcount!A38 -> R&D engineers | B44: =Headcount!B38 -> R&D | C44: =IF(Headcount!$D$38<=Timeline!C5,Headcount!$C$38,0) -> 0 | D44: =IF(Headcount!$D$38<=Timeline!D5,Headcount!$C$38,0) -> 0 | E44: =IF(Headcount!$D$38<=Timeline!E5,Headcount!$C$38,0) -> 0 | F44: =IF(Headcount!$D$38<=Timeline!F5,Headcount!$C$38,0) -> 0 | G44: =IF(Headcount!$D$38<=Timeline!G5,Headcount!$C$38,0) -> 0 | H44: =IF(Headcount!$D$38<=Timeline!H5,Headcount!$C$38,0) -> 0 | I44: =IF(Headcount!$D$38<=Timeline!I5,Headcount!$C$38,0) -> 0 | J44: =IF(Headcount!$D$38<=Timeline!J5,Headcount!$C$38,0) -> 0 | ... AB44: =IF(Headcount!$D$38<=Timeline!AB5,Headcount!$C$38,0) -> 0 | AC44: =IF(Headcount!$D$38<=DATE(2029,12,31),Headcount!$C$38,0) -> 0 | AD44: =IF(Headcount!$D$38<=DATE(2030,12,31),Headcount!$C$38,0) -> 10 | AE44: =IF(Headcount!$D$38<=DATE(2031,12,31),Headcount!$C$38,0) -> 10 | AG44: =D44 -> 0 | AH44: =P44 -> 0 | AI44: =AB44 -> 0 | AJ44: =AC44 -> 0 | AK44: =AD44 -> 10 | AL44: =AE44 -> 10
A45: =Headcount!A39 -> Content editors | B45: =Headcount!B39 -> R&D | C45: =IF(Headcount!$D$39<=Timeline!C5,Headcount!$C$39,0) -> 0 | D45: =IF(Headcount!$D$39<=Timeline!D5,Headcount!$C$39,0) -> 0 | E45: =IF(Headcount!$D$39<=Timeline!E5,Headcount!$C$39,0) -> 0 | F45: =IF(Headcount!$D$39<=Timeline!F5,Headcount!$C$39,0) -> 0 | G45: =IF(Headcount!$D$39<=Timeline!G5,Headcount!$C$39,0) -> 0 | H45: =IF(Headcount!$D$39<=Timeline!H5,Headcount!$C$39,0) -> 0 | I45: =IF(Headcount!$D$39<=Timeline!I5,Headcount!$C$39,0) -> 0 | J45: =IF(Headcount!$D$39<=Timeline!J5,Headcount!$C$39,0) -> 0 | ... AB45: =IF(Headcount!$D$39<=Timeline!AB5,Headcount!$C$39,0) -> 0 | AC45: =IF(Headcount!$D$39<=DATE(2029,12,31),Headcount!$C$39,0) -> 0 | AD45: =IF(Headcount!$D$39<=DATE(2030,12,31),Headcount!$C$39,0) -> 4 | AE45: =IF(Headcount!$D$39<=DATE(2031,12,31),Headcount!$C$39,0) -> 4 | AG45: =D45 -> 0 | AH45: =P45 -> 0 | AI45: =AB45 -> 0 | AJ45: =AC45 -> 0 | AK45: =AD45 -> 4 | AL45: =AE45 -> 4
A46: =Headcount!A40 -> S&M team | B46: =Headcount!B40 -> S&M | C46: =IF(Headcount!$D$40<=Timeline!C5,Headcount!$C$40,0) -> 0 | D46: =IF(Headcount!$D$40<=Timeline!D5,Headcount!$C$40,0) -> 0 | E46: =IF(Headcount!$D$40<=Timeline!E5,Headcount!$C$40,0) -> 0 | F46: =IF(Headcount!$D$40<=Timeline!F5,Headcount!$C$40,0) -> 0 | G46: =IF(Headcount!$D$40<=Timeline!G5,Headcount!$C$40,0) -> 0 | H46: =IF(Headcount!$D$40<=Timeline!H5,Headcount!$C$40,0) -> 0 | I46: =IF(Headcount!$D$40<=Timeline!I5,Headcount!$C$40,0) -> 0 | J46: =IF(Headcount!$D$40<=Timeline!J5,Headcount!$C$40,0) -> 0 | ... AB46: =IF(Headcount!$D$40<=Timeline!AB5,Headcount!$C$40,0) -> 0 | AC46: =IF(Headcount!$D$40<=DATE(2029,12,31),Headcount!$C$40,0) -> 0 | AD46: =IF(Headcount!$D$40<=DATE(2030,12,31),Headcount!$C$40,0) -> 6 | AE46: =IF(Headcount!$D$40<=DATE(2031,12,31),Headcount!$C$40,0) -> 6 | AG46: =D46 -> 0 | AH46: =P46 -> 0 | AI46: =AB46 -> 0 | AJ46: =AC46 -> 0 | AK46: =AD46 -> 6 | AL46: =AE46 -> 6
A47: =Headcount!A41 -> Ops / CS | B47: =Headcount!B41 -> Ops & CS | C47: =IF(Headcount!$D$41<=Timeline!C5,Headcount!$C$41,0) -> 0 | D47: =IF(Headcount!$D$41<=Timeline!D5,Headcount!$C$41,0) -> 0 | E47: =IF(Headcount!$D$41<=Timeline!E5,Headcount!$C$41,0) -> 0 | F47: =IF(Headcount!$D$41<=Timeline!F5,Headcount!$C$41,0) -> 0 | G47: =IF(Headcount!$D$41<=Timeline!G5,Headcount!$C$41,0) -> 0 | H47: =IF(Headcount!$D$41<=Timeline!H5,Headcount!$C$41,0) -> 0 | I47: =IF(Headcount!$D$41<=Timeline!I5,Headcount!$C$41,0) -> 0 | J47: =IF(Headcount!$D$41<=Timeline!J5,Headcount!$C$41,0) -> 0 | ... AB47: =IF(Headcount!$D$41<=Timeline!AB5,Headcount!$C$41,0) -> 0 | AC47: =IF(Headcount!$D$41<=DATE(2029,12,31),Headcount!$C$41,0) -> 0 | AD47: =IF(Headcount!$D$41<=DATE(2030,12,31),Headcount!$C$41,0) -> 8 | AE47: =IF(Headcount!$D$41<=DATE(2031,12,31),Headcount!$C$41,0) -> 8 | AG47: =D47 -> 0 | AH47: =P47 -> 0 | AI47: =AB47 -> 0 | AJ47: =AC47 -> 0 | AK47: =AD47 -> 8 | AL47: =AE47 -> 8
A48: =Headcount!A42 -> G&A | B48: =Headcount!B42 -> G&A | C48: =IF(Headcount!$D$42<=Timeline!C5,Headcount!$C$42,0) -> 0 | D48: =IF(Headcount!$D$42<=Timeline!D5,Headcount!$C$42,0) -> 0 | E48: =IF(Headcount!$D$42<=Timeline!E5,Headcount!$C$42,0) -> 0 | F48: =IF(Headcount!$D$42<=Timeline!F5,Headcount!$C$42,0) -> 0 | G48: =IF(Headcount!$D$42<=Timeline!G5,Headcount!$C$42,0) -> 0 | H48: =IF(Headcount!$D$42<=Timeline!H5,Headcount!$C$42,0) -> 0 | I48: =IF(Headcount!$D$42<=Timeline!I5,Headcount!$C$42,0) -> 0 | J48: =IF(Headcount!$D$42<=Timeline!J5,Headcount!$C$42,0) -> 0 | ... AB48: =IF(Headcount!$D$42<=Timeline!AB5,Headcount!$C$42,0) -> 0 | AC48: =IF(Headcount!$D$42<=DATE(2029,12,31),Headcount!$C$42,0) -> 0 | AD48: =IF(Headcount!$D$42<=DATE(2030,12,31),Headcount!$C$42,0) -> 3 | AE48: =IF(Headcount!$D$42<=DATE(2031,12,31),Headcount!$C$42,0) -> 3 | AG48: =D48 -> 0 | AH48: =P48 -> 0 | AI48: =AB48 -> 0 | AJ48: =AC48 -> 0 | AK48: =AD48 -> 3 | AL48: =AE48 -> 3
A49: =Headcount!A43 -> R&D engineers | B49: =Headcount!B43 -> R&D | C49: =IF(Headcount!$D$43<=Timeline!C5,Headcount!$C$43,0) -> 0 | D49: =IF(Headcount!$D$43<=Timeline!D5,Headcount!$C$43,0) -> 0 | E49: =IF(Headcount!$D$43<=Timeline!E5,Headcount!$C$43,0) -> 0 | F49: =IF(Headcount!$D$43<=Timeline!F5,Headcount!$C$43,0) -> 0 | G49: =IF(Headcount!$D$43<=Timeline!G5,Headcount!$C$43,0) -> 0 | H49: =IF(Headcount!$D$43<=Timeline!H5,Headcount!$C$43,0) -> 0 | I49: =IF(Headcount!$D$43<=Timeline!I5,Headcount!$C$43,0) -> 0 | J49: =IF(Headcount!$D$43<=Timeline!J5,Headcount!$C$43,0) -> 0 | ... AB49: =IF(Headcount!$D$43<=Timeline!AB5,Headcount!$C$43,0) -> 0 | AC49: =IF(Headcount!$D$43<=DATE(2029,12,31),Headcount!$C$43,0) -> 0 | AD49: =IF(Headcount!$D$43<=DATE(2030,12,31),Headcount!$C$43,0) -> 0 | AE49: =IF(Headcount!$D$43<=DATE(2031,12,31),Headcount!$C$43,0) -> 10 | AG49: =D49 -> 0 | AH49: =P49 -> 0 | AI49: =AB49 -> 0 | AJ49: =AC49 -> 0 | AK49: =AD49 -> 0 | AL49: =AE49 -> 10
A50: =Headcount!A44 -> S&M team | B50: =Headcount!B44 -> S&M | C50: =IF(Headcount!$D$44<=Timeline!C5,Headcount!$C$44,0) -> 0 | D50: =IF(Headcount!$D$44<=Timeline!D5,Headcount!$C$44,0) -> 0 | E50: =IF(Headcount!$D$44<=Timeline!E5,Headcount!$C$44,0) -> 0 | F50: =IF(Headcount!$D$44<=Timeline!F5,Headcount!$C$44,0) -> 0 | G50: =IF(Headcount!$D$44<=Timeline!G5,Headcount!$C$44,0) -> 0 | H50: =IF(Headcount!$D$44<=Timeline!H5,Headcount!$C$44,0) -> 0 | I50: =IF(Headcount!$D$44<=Timeline!I5,Headcount!$C$44,0) -> 0 | J50: =IF(Headcount!$D$44<=Timeline!J5,Headcount!$C$44,0) -> 0 | ... AB50: =IF(Headcount!$D$44<=Timeline!AB5,Headcount!$C$44,0) -> 0 | AC50: =IF(Headcount!$D$44<=DATE(2029,12,31),Headcount!$C$44,0) -> 0 | AD50: =IF(Headcount!$D$44<=DATE(2030,12,31),Headcount!$C$44,0) -> 0 | AE50: =IF(Headcount!$D$44<=DATE(2031,12,31),Headcount!$C$44,0) -> 6 | AG50: =D50 -> 0 | AH50: =P50 -> 0 | AI50: =AB50 -> 0 | AJ50: =AC50 -> 0 | AK50: =AD50 -> 0 | AL50: =AE50 -> 6
A51: =Headcount!A45 -> Ops / CS | B51: =Headcount!B45 -> Ops & CS | C51: =IF(Headcount!$D$45<=Timeline!C5,Headcount!$C$45,0) -> 0 | D51: =IF(Headcount!$D$45<=Timeline!D5,Headcount!$C$45,0) -> 0 | E51: =IF(Headcount!$D$45<=Timeline!E5,Headcount!$C$45,0) -> 0 | F51: =IF(Headcount!$D$45<=Timeline!F5,Headcount!$C$45,0) -> 0 | G51: =IF(Headcount!$D$45<=Timeline!G5,Headcount!$C$45,0) -> 0 | H51: =IF(Headcount!$D$45<=Timeline!H5,Headcount!$C$45,0) -> 0 | I51: =IF(Headcount!$D$45<=Timeline!I5,Headcount!$C$45,0) -> 0 | J51: =IF(Headcount!$D$45<=Timeline!J5,Headcount!$C$45,0) -> 0 | ... AB51: =IF(Headcount!$D$45<=Timeline!AB5,Headcount!$C$45,0) -> 0 | AC51: =IF(Headcount!$D$45<=DATE(2029,12,31),Headcount!$C$45,0) -> 0 | AD51: =IF(Headcount!$D$45<=DATE(2030,12,31),Headcount!$C$45,0) -> 0 | AE51: =IF(Headcount!$D$45<=DATE(2031,12,31),Headcount!$C$45,0) -> 10 | AG51: =D51 -> 0 | AH51: =P51 -> 0 | AI51: =AB51 -> 0 | AJ51: =AC51 -> 0 | AK51: =AD51 -> 0 | AL51: =AE51 -> 10
A52: =Headcount!A46 -> G&A | B52: =Headcount!B46 -> G&A | C52: =IF(Headcount!$D$46<=Timeline!C5,Headcount!$C$46,0) -> 0 | D52: =IF(Headcount!$D$46<=Timeline!D5,Headcount!$C$46,0) -> 0 | E52: =IF(Headcount!$D$46<=Timeline!E5,Headcount!$C$46,0) -> 0 | F52: =IF(Headcount!$D$46<=Timeline!F5,Headcount!$C$46,0) -> 0 | G52: =IF(Headcount!$D$46<=Timeline!G5,Headcount!$C$46,0) -> 0 | H52: =IF(Headcount!$D$46<=Timeline!H5,Headcount!$C$46,0) -> 0 | I52: =IF(Headcount!$D$46<=Timeline!I5,Headcount!$C$46,0) -> 0 | J52: =IF(Headcount!$D$46<=Timeline!J5,Headcount!$C$46,0) -> 0 | ... AB52: =IF(Headcount!$D$46<=Timeline!AB5,Headcount!$C$46,0) -> 0 | AC52: =IF(Headcount!$D$46<=DATE(2029,12,31),Headcount!$C$46,0) -> 0 | AD52: =IF(Headcount!$D$46<=DATE(2030,12,31),Headcount!$C$46,0) -> 0 | AE52: =IF(Headcount!$D$46<=DATE(2031,12,31),Headcount!$C$46,0) -> 3 | AG52: =D52 -> 0 | AH52: =P52 -> 0 | AI52: =AB52 -> 0 | AJ52: =AC52 -> 0 | AK52: =AD52 -> 0 | AL52: =AE52 -> 3
A54: Personnel cost by role (salary x (1+burden) x inflation)
